Workbook

Sheet CPI-U-RS
C6: Series Reported at https://www.bls.gov/cpi/research-series/r-cpi-u-rs-home.htm
C7: 1947 | D7: 37.5
C8: 1948 | D8: 40.5
C9: 1949 | D9: 40
C10: 1950 | D10: 40.5
C11: 1951 | D11: 43.7
C12: 1952 | D12: 44.5
C13: 1953 | D13: 44.8
C14: 1954 | D14: 45.2
C15: 1955 | D15: 45
C16: 1956 | D16: 45.7
C17: 1957 | D17: 47.2
C18: 1958 | D18: 48.5
... C73: 2013 | D73: 342
C74: =+C73+1 -> 2014 | D74: 347.7
C75: =+C74+1 -> 2015 | D75: 348.3
C76: =+C75+1 -> 2016 | D76: 352.8
C77: 2017 | D77: 360.3
C78: 2018 | D78: 369.1
C79: 2019 | D79: 375.8
C80: 2020 | D80: 380.8
C81: 2021 | D81: 399.2
C82: 2022 | D82: 431.5

Sheet CPI-U
AA1: From: http://numbrary.com/sources/8e7dbdcd8a7a-cuur000-cpi-all-items or http://data.bls.gov/timeseries/CUUR0000SA0?include_graphs=false&output_type=column&years_option=all_years
AA2: Year & Month | AB2: CPI
A3: Year | B3: CPI-U | H3: Series Id: CUUR0000SA0,CUUS0000SA0 | AA3: 4750 | AB3: 9.8
A4: 1947 | B4: =+U10 -> 22.3 | H4: Not Seasonally Adjusted | AA4: 4781 | AB4: 9.8
A5: 1948 | B5: =+U11 -> 24.1 | H5: Area: U.S. city average | AA5: 4809 | AB5: 9.8
A6: 1949 | B6: =+U12 -> 23.8 | H6: Item: All items | AA6: 4840 | AB6: 9.8
A7: 1950 | B7: =+U13 -> 24.1 | H7: Base Period: 1982-84=100 | AA7: 4870 | AB7: 9.7
A8: 1951 | B8: =+U14 -> 26 | AA8: 4901 | AB8: 9.8
A9: 1952 | B9: =+U15 -> 26.5 | H9: Year | I9: Jan | J9: Feb | K9: Mar | L9: Apr | M9: May | N9: Jun | O9: Jul | P9: Aug | Q9: Sep | R9: Oct | S9: Nov | T9: Dec | U9: Annual | V9: HALF1 | W9: HALF2 | AA9: 4931 | AB9: 9.9
A10: 1953 | B10: =+U16 -> 26.7 | H10: 1947 | I10: 21.5 | J10: 21.5 | K10: 21.9 | L10: 21.9 | M10: 21.9 | N10: 22 | O10: 22.2 | P10: 22.5 | Q10: 23 | R10: 23 | S10: 23.1 | T10: 23.4 | U10: 22.3 | AA10: 4962 | AB10: 9.9
A11: 1954 | B11: =+U17 -> 26.9 | H11: 1948 | I11: 23.7 | J11: 23.5 | K11: 23.4 | L11: 23.8 | M11: 23.9 | N11: 24.1 | O11: 24.4 | P11: 24.5 | Q11: 24.5 | R11: 24.4 | S11: 24.2 | T11: 24.1 | U11: 24.1 | AA11: 4993 | AB11: 10
A12: 1955 | B12: =+U18 -> 26.8 | H12: 1949 | I12: 24 | J12: 23.8 | K12: 23.8 | L12: 23.9 | M12: 23.8 | N12: 23.9 | O12: 23.7 | P12: 23.8 | Q12: 23.9 | R12: 23.7 | S12: 23.8 | T12: 23.6 | U12: 23.8 | AA12: 5023 | AB12: 10
A13: 1956 | B13: =+U19 -> 27.2 | H13: 1950 | I13: 23.5 | J13: 23.5 | K13: 23.6 | L13: 23.6 | M13: 23.7 | N13: 23.8 | O13: 24.1 | P13: 24.3 | Q13: 24.4 | R13: 24.6 | S13: 24.7 | T13: 25 | U13: 24.1 | AA13: 5054 | AB13: 10.1
A14: 1957 | B14: =+U20 -> 28.1 | H14: 1951 | I14: 25.4 | J14: 25.7 | K14: 25.8 | L14: 25.8 | M14: 25.9 | N14: 25.9 | O14: 25.9 | P14: 25.9 | Q14: 26.1 | R14: 26.2 | S14: 26.4 | T14: 26.5 | U14: 26 | AA14: 5084 | AB14: 10
A15: 1958 | B15: =+U21 -> 28.9 | H15: 1952 | I15: 26.5 | J15: 26.3 | K15: 26.3 | L15: 26.4 | M15: 26.4 | N15: 26.5 | O15: 26.7 | P15: 26.7 | Q15: 26.7 | R15: 26.7 | S15: 26.7 | T15: 26.7 | U15: 26.5 | AA15: 5115 | AB15: 10
A16: 1959 | B16: =+U22 -> 29.1 | H16: 1953 | I16: 26.6 | J16: 26.5 | K16: 26.6 | L16: 26.6 | M16: 26.7 | N16: 26.8 | O16: 26.8 | P16: 26.9 | Q16: 26.9 | R16: 27 | S16: 26.9 | T16: 26.9 | U16: 26.7 | AA16: 5146 | AB16: 9.9
A17: 1960 | B17: =+U23 -> 29.6 | H17: 1954 | I17: 26.9 | J17: 26.9 | K17: 26.9 | L17: 26.8 | M17: 26.9 | N17: 26.9 | O17: 26.9 | P17: 26.9 | Q17: 26.8 | R17: 26.8 | S17: 26.8 | T17: 26.7 | U17: 26.9 | AA17: 5174 | AB17: 9.9
A18: 1961 | B18: =+U24 -> 29.9 | H18: 1955 | I18: 26.7 | J18: 26.7 | K18: 26.7 | L18: 26.7 | M18: 26.7 | N18: 26.7 | O18: 26.8 | P18: 26.8 | Q18: 26.9 | R18: 26.9 | S18: 26.9 | T18: 26.8 | U18: 26.8 | AA18: 5205 | AB18: 9.8
A19: 1962 | B19: =+U25 -> 30.2 | H19: 1956 | I19: 26.8 | J19: 26.8 | K19: 26.8 | L19: 26.9 | M19: 27 | N19: 27.2 | O19: 27.4 | P19: 27.3 | Q19: 27.4 | R19: 27.5 | S19: 27.5 | T19: 27.6 | U19: 27.2 | AA19: 5235 | AB19: 9.9
A20: 1963 | B20: =+U26 -> 30.6 | H20: 1957 | I20: 27.6 | J20: 27.7 | K20: 27.8 | L20: 27.9 | M20: 28 | N20: 28.1 | O20: 28.3 | P20: 28.3 | Q20: 28.3 | R20: 28.3 | S20: 28.4 | T20: 28.4 | U20: 28.1 | AA20: 5266 | AB20: 9.9
A21: 1964 | B21: =+U27 -> 31 | H21: 1958 | I21: 28.6 | J21: 28.6 | K21: 28.8 | L21: 28.9 | M21: 28.9 | N21: 28.9 | O21: 29 | P21: 28.9 | Q21: 28.9 | R21: 28.9 | S21: 29 | T21: 28.9 | U21: 28.9 | AA21: 5296 | AB21: 10
... A46: 1989 | B46: =+U52 -> 124 | H46: 1983 | I46: 97.8 | J46: 97.9 | K46: 97.9 | L46: 98.6 | M46: 99.2 | N46: 99.5 | O46: 99.9 | P46: 100.2 | Q46: 100.7 | R46: 101 | S46: 101.2 | T46: 101.3 | U46: 99.6 | AA46: 6058 | AB46: 10.9
A47: 1990 | B47: =+U53 -> 130.7 | H47: 1984 | I47: 101.9 | J47: 102.4 | K47: 102.6 | L47: 103.1 | M47: 103.4 | N47: 103.7 | O47: 104.1 | P47: 104.5 | Q47: 105 | R47: 105.3 | S47: 105.3 | T47: 105.3 | U47: 103.9 | V47: 102.9 | W47: 104.9 | AA47: 6089 | AB47: 11.1
A48: 1991 | B48: =+U54 -> 136.2 | H48: 1985 | I48: 105.5 | J48: 106 | K48: 106.4 | L48: 106.9 | M48: 107.3 | N48: 107.6 | O48: 107.8 | P48: 108 | Q48: 108.3 | R48: 108.7 | S48: 109 | T48: 109.3 | U48: 107.6 | V48: 106.6 | W48: 108.5 | AA48: 6119 | AB48: 11.3
A49: 1992 | B49: =+U55 -> 140.3 | H49: 1986 | I49: 109.6 | J49: 109.3 | K49: 108.8 | L49: 108.6 | M49: 108.9 | N49: 109.5 | O49: 109.5 | P49: 109.7 | Q49: 110.2 | R49: 110.3 | S49: 110.4 | T49: 110.5 | U49: 109.6 | V49: 109.1 | W49: 110.1 | AA49: 6150 | AB49: 11.5
A50: 1993 | B50: =+U56 -> 144.5 | H50: 1987 | I50: 111.2 | J50: 111.6 | K50: 112.1 | L50: 112.7 | M50: 113.1 | N50: 113.5 | O50: 113.8 | P50: 114.4 | Q50: 115 | R50: 115.3 | S50: 115.4 | T50: 115.4 | U50: 113.6 | V50: 112.4 | W50: 114.9 | AA50: 6180 | AB50: 11.6
A51: 1994 | B51: =+U57 -> 148.2 | H51: 1988 | I51: 115.7 | J51: 116 | K51: 116.5 | L51: 117.1 | M51: 117.5 | N51: 118 | O51: 118.5 | P51: 119 | Q51: 119.8 | R51: 120.2 | S51: 120.3 | T51: 120.5 | U51: 118.3 | V51: 116.8 | W51: 119.7 | AA51: 6211 | AB51: 11.7
A52: 1995 | B52: =+U58 -> 152.4 | H52: 1989 | I52: 121.1 | J52: 121.6 | K52: 122.3 | L52: 123.1 | M52: 123.8 | N52: 124.1 | O52: 124.4 | P52: 124.6 | Q52: 125 | R52: 125.6 | S52: 125.9 | T52: 126.1 | U52: 124 | V52: 122.7 | W52: 125.3 | AA52: 6242 | AB52: 12
A53: 1996 | B53: =+U59 -> 156.9 | H53: 1990 | I53: 127.4 | J53: 128 | K53: 128.7 | L53: 128.9 | M53: 129.2 | N53: 129.9 | O53: 130.4 | P53: 131.6 | Q53: 132.7 | R53: 133.5 | S53: 133.8 | T53: 133.8 | U53: 130.7 | V53: 128.7 | W53: 132.6 | AA53: 6270 | AB53: 12
A54: 1997 | B54: =+U60 -> 160.5 | H54: 1991 | I54: 134.6 | J54: 134.8 | K54: 135 | L54: 135.2 | M54: 135.6 | N54: 136 | O54: 136.2 | P54: 136.6 | Q54: 137.2 | R54: 137.4 | S54: 137.8 | T54: 137.9 | U54: 136.2 | V54: 135.2 | W54: 137.2 | AA54: 6301 | AB54: 12.6
A55: 1998 | B55: =+U61 -> 163 | H55: 1992 | I55: 138.1 | J55: 138.6 | K55: 139.3 | L55: 139.5 | M55: 139.7 | N55: 140.2 | O55: 140.5 | P55: 140.9 | Q55: 141.3 | R55: 141.8 | S55: 142 | T55: 141.9 | U55: 140.3 | V55: 139.2 | W55: 141.4 | AA55: 6331 | AB55: 12.8
A56: 1999 | B56: =+U62 -> 166.6 | H56: 1993 | I56: 142.6 | J56: 143.1 | K56: 143.6 | L56: 144 | M56: 144.2 | N56: 144.4 | O56: 144.4 | P56: 144.8 | Q56: 145.1 | R56: 145.7 | S56: 145.8 | T56: 145.8 | U56: 144.5 | V56: 143.7 | W56: 145.3 | AA56: 6362 | AB56: 13
A57: 2000 | B57: =+U63 -> 172.2 | H57: 1994 | I57: 146.2 | J57: 146.7 | K57: 147.2 | L57: 147.4 | M57: 147.5 | N57: 148 | O57: 148.4 | P57: 149 | Q57: 149.4 | R57: 149.5 | S57: 149.7 | T57: 149.7 | U57: 148.2 | V57: 147.2 | W57: 149.3 | AA57: 6392 | AB57: 12.8
A58: 2001 | B58: =+U64 -> 177.1 | H58: 1995 | I58: 150.3 | J58: 150.9 | K58: 151.4 | L58: 151.9 | M58: 152.2 | N58: 152.5 | O58: 152.5 | P58: 152.9 | Q58: 153.2 | R58: 153.7 | S58: 153.6 | T58: 153.5 | U58: 152.4 | V58: 151.5 | W58: 153.2 | AA58: 6423 | AB58: 13
... A62: 2005 | B62: =+U68 -> 195.3 | H62: 1999 | I62: 164.3 | J62: 164.5 | K62: 165 | L62: 166.2 | M62: 166.2 | N62: 166.2 | O62: 166.7 | P62: 167.1 | Q62: 167.9 | R62: 168.2 | S62: 168.3 | T62: 168.3 | U62: 166.6 | V62: 165.4 | W62: 167.8 | AA62: 6545 | AB62: 13.7
A63: =+A62+1 -> 2006 | B63: =+AVERAGE(I81:T81) -> 201.59167 | H63: 2000 | I63: 168.8 | J63: 169.8 | K63: 171.2 | L63: 171.3 | M63: 171.5 | N63: 172.4 | O63: 172.8 | P63: 172.8 | Q63: 173.7 | R63: 174 | S63: 174.1 | T63: 174 | U63: 172.2 | V63: 170.8 | W63: 173.6 | AA63: 6576 | AB63: 14
A64: =+A63+1 -> 2007 | B64: =+AVERAGE(I82:T82) -> 207.34242 | H64: 2001 | I64: 175.1 | J64: 175.8 | K64: 176.2 | L64: 176.9 | M64: 177.7 | N64: 178 | O64: 177.5 | P64: 177.5 | Q64: 178.3 | R64: 177.7 | S64: 177.4 | T64: 176.7 | U64: 177.1 | V64: 176.6 | W64: 177.5 | AA64: 6607 | AB64: 14.1
A65: =+A64+1 -> 2008 | B65: =+AVERAGE(I83:T83) -> 215.3025 | H65: 2002 | I65: 177.1 | J65: 177.8 | K65: 178.8 | L65: 179.8 | M65: 179.8 | N65: 179.9 | O65: 180.1 | P65: 180.7 | Q65: 181 | R65: 181.3 | S65: 181.3 | T65: 180.9 | U65: 179.9 | V65: 178.9 | W65: 180.9 | AA65: 6635 | AB65: 14
A66: =+A65+1 -> 2009 | B66: =+AVERAGE(I84:T84) -> 214.537 | H66: 2003 | I66: 181.7 | J66: 183.1 | K66: 184.2 | L66: 183.8 | M66: 183.5 | N66: 183.7 | O66: 183.9 | P66: 184.6 | Q66: 185.2 | R66: 185 | S66: 184.5 | T66: 184.3 | U66: 184 | V66: 183.3 | W66: 184.6 | AA66: 6666 | AB66: 14.2
A67: =+A66+1 -> 2010 | B67: =+AVERAGE(I85:T85) -> 218.0555 | H67: 2004 | I67: 185.2 | J67: 186.2 | K67: 187.4 | L67: 188 | M67: 189.1 | N67: 189.7 | O67: 189.4 | P67: 189.5 | Q67: 189.9 | R67: 190.9 | S67: 191 | T67: 190.3 | U67: 188.9 | V67: 187.6 | W67: 190.2 | AA67: 6696 | AB67: 14.5
A68: =+A67+1 -> 2011 | B68: =+AVERAGE(I86:T86) -> 224.93917 | H68: 2005 | I68: 190.7 | J68: 191.8 | K68: 193.3 | L68: 194.6 | M68: 194.4 | N68: 194.5 | O68: 195.4 | P68: 196.4 | Q68: 198.8 | R68: 199.2 | S68: 197.6 | T68: 196.8 | U68: 195.3 | V68: 193.2 | W68: 197.4 | AA68: 6727 | AB68: 14.7
A69: 2012 | B69: =+AVERAGE(I87:T87) -> 229.59392 | AA69: 6757 | AB69: 15.1
A70: 2013 | B70: =+AVERAGE(I88:T88) -> 232.95708 | H70: Consumer Price Index - All Urban Consumers | AA70: 6788 | AB70: 15.4
A71: =+A70+1 -> 2014 | B71: =+AVERAGE(I89:T89) -> 236.73617 | H71: Original Data Value | AA71: 6819 | AB71: 15.7
A72: =+A71+1 -> 2015 | B72: =+AVERAGE(I90:T90) -> 237.017 | AA72: 6849 | AB72: 16
A73: =+A72+1 -> 2016 | B73: =+AVERAGE(I91:T91) -> 240.00717 | H73: Series Id: | I73: CUUR0000SA0 | AA73: 6880 | AB73: 16.3
A74: =+A73+1 -> 2017 | B74: =U92 -> 245.12 | H74: Not Seasonally Adjusted | AA74: 6910 | AB74: 16.5
A75: =+A74+1 -> 2018 | B75: =U93 -> 251.107 | H75: Area: | I75: U.S. city average | AA75: 6941 | AB75: 16.5
A76: =+A75+1 -> 2019 | B76: =U94 -> 255.657 | H76: Item: | I76: All items | AA76: 6972 | AB76: 16.2
A77: =+A76+1 -> 2020 | B77: =U95 -> 258.811 | H77: Base Period: | I77: 1982-84=100 | AA77: 7000 | AB77: 16.4
A78: =+A77+1 -> 2021 | B78: =U96 -> 270.96975 | H78: Years: | I78: 1960 to 2017 | AA78: 7031 | AB78: 16.7
A79: 2022 | B79: =U97 -> 292.655 | AA79: 7061 | AB79: 16.9
H80: Year | I80: Jan | J80: Feb | K80: Mar | L80: Apr | M80: May | N80: Jun | O80: Jul | P80: Aug | Q80: Sep | R80: Oct | S80: Nov | T80: Dec | U80: Annual | V80: HALF1 | W80: HALF2 | AA80: 7092 | AB80: 16.9
H81: 2006 | I81: 198.3 | J81: 198.7 | K81: 199.8 | L81: 201.5 | M81: 202.5 | N81: 202.9 | O81: 203.5 | P81: 203.9 | Q81: 202.9 | R81: 201.8 | S81: 201.5 | T81: 201.8 | U81: 201.6 | V81: 200.6 | W81: 202.6 | AA81: 7122 | AB81: 17.4
H82: 2007 | I82: 202.416 | J82: 203.499 | K82: 205.352 | L82: 206.686 | M82: 207.949 | N82: 208.352 | O82: 208.299 | P82: 207.917 | Q82: 208.49 | R82: 208.936 | S82: 210.177 | T82: 210.036 | U82: 207.342 | V82: 205.709 | W82: 208.976 | AA82: 7153 | AB82: 17.7
H83: 2008 | I83: 211.08 | J83: 211.693 | K83: 213.528 | L83: 214.823 | M83: 216.632 | N83: 218.815 | O83: 219.964 | P83: 219.086 | Q83: 218.783 | R83: 216.573 | S83: 212.425 | T83: 210.228 | U83: 215.303 | V83: 214.429 | W83: 216.177 | AA83: 7184 | AB83: 17.8
H84: 2009 | I84: 211.143 | J84: 212.193 | K84: 212.709 | L84: 213.24 | M84: 213.856 | N84: 215.693 | O84: 215.351 | P84: 215.834 | Q84: 215.969 | R84: 216.177 | S84: 216.33 | T84: 215.949 | U84: 214.537 | V84: 213.139 | W84: 215.935 | AA84: 7214 | AB84: 18.1
H85: 2010 | I85: 216.687 | J85: 216.741 | K85: 217.631 | L85: 218.009 | M85: 218.178 | N85: 217.965 | O85: 218.011 | P85: 218.312 | Q85: 218.439 | R85: 218.711 | S85: 218.803 | T85: 219.179 | U85: 218.056 | V85: 217.535 | W85: 218.576 | AA85: 7245 | AB85: 18.5
H86: 2011 | I86: 220.223 | J86: 221.309 | K86: 223.467 | L86: 224.906 | M86: 225.964 | N86: 225.722 | O86: 225.922 | P86: 226.545 | Q86: 226.889 | R86: 226.421 | S86: 226.23 | T86: 225.672 | U86: 224.939 | V86: 223.598 | W86: 226.28 | AA86: 7275 | AB86: 18.9
H87: 2012 | I87: 226.665 | J87: 227.663 | K87: 229.392 | L87: 230.085 | M87: 229.815 | N87: 229.478 | O87: 229.104 | P87: 230.379 | Q87: 231.407 | R87: 231.317 | S87: 230.221 | T87: 229.601 | U87: 229.594 | V87: 228.85 | W87: 230.338 | AA87: 7306 | AB87: 19.3
H88: 2013 | I88: 230.28 | J88: 232.166 | K88: 232.773 | L88: 232.531 | M88: 232.945 | N88: 233.504 | O88: 233.596 | P88: 233.877 | Q88: 234.149 | R88: 233.546 | S88: 233.069 | T88: 233.049 | U88: 232.957 | V88: 232.366 | W88: 233.548 | AA88: 7337 | AB88: 19.5
H89: 2014 | I89: 233.916 | J89: 234.781 | K89: 236.293 | L89: 237.072 | M89: 237.9 | N89: 238.343 | O89: 238.25 | P89: 237.852 | Q89: 238.031 | R89: 237.433 | S89: 236.151 | T89: 234.812 | U89: 236.736 | V89: 236.384 | W89: 237.088 | AA89: 7366 | AB89: 19.7
H90: 2015 | I90: 233.707 | J90: 234.722 | K90: 236.119 | L90: 236.599 | M90: 237.805 | N90: 238.638 | O90: 238.654 | P90: 238.316 | Q90: 237.945 | R90: 237.838 | S90: 237.336 | T90: 236.525 | U90: 237.017 | V90: 236.265 | W90: 237.769 | AA90: 7397 | AB90: 20.3
H91: 2016 | I91: 236.916 | J91: 237.111 | K91: 238.132 | L91: 239.261 | M91: 240.229 | N91: 241.018 | O91: 240.628 | P91: 240.849 | Q91: 241.428 | R91: 241.729 | S91: 241.353 | T91: 241.432 | U91: 240.007 | V91: 238.778 | W91: 241.237 | AA91: 7427 | AB91: 20.6
H92: 2017 | I92: 242.839 | J92: 243.603 | K92: 243.801 | L92: 244.524 | M92: 244.733 | N92: 244.955 | O92: 244.786 | P92: 245.519 | Q92: 246.819 | R92: 246.663 | S92: 246.669 | T92: 246.524 | U92: 245.12 | V92: 244.076 | W92: 246.163 | AA92: 7458 | AB92: 20.9
... H95: 2020 | I95: 257.971 | J95: 258.678 | K95: 258.115 | L95: 256.389 | M95: 256.394 | N95: 257.797 | O95: 259.101 | P95: 259.918 | Q95: 260.28 | R95: 260.388 | S95: 260.229 | T95: 260.474 | U95: 258.811 | V95: 257.557 | W95: 260.065 | AA95: 7550 | AB95: 20
H96: 2021 | I96: 261.582 | J96: 263.014 | K96: 264.877 | L96: 267.054 | M96: 269.195 | N96: 271.696 | O96: 273.003 | P96: 273.567 | Q96: 274.31 | R96: 276.589 | S96: 277.948 | T96: 278.802 | U96: =AVERAGE(I96:T96) -> 270.96975 | V96: 266.236 | W96: 275.703 | AA96: 7580 | AB96: 19.9
U97: 292.655 | AA97: 7611 | AB97: 19.8
AA98: 7641 | AB98: 19.4
AA99: 7672 | AB99: 19
AA100: 7703 | AB100: 18.4
AA101: 7731 | AB101: 18.3
AA102: 7762 | AB102: 18.1
AA103: 7792 | AB103: 17.7
AA104: 7823 | AB104: 17.6
AA105: 7853 | AB105: 17.7
AA106: 7884 | AB106: 17.7
AA107: 7915 | AB107: 17.5
AA108: 7945 | AB108: 17.5
AA109: 7976 | AB109: 17.4
... AA1175: 40429 | AB1175: 218.439
AA1176: =+AA1175+30 -> 40459 | AB1176: 218.711
AA1177: =+AA1176+30 -> 40489 | AB1177: 218.803
AA1178: =+AA1177+30 -> 40519 | AB1178: 219.179
AA1179: =+AA1178+30 -> 40549 | AB1179: 220.223
AA1180: =+AA1179+30 -> 40579 | AB1180: 221.309
AA1181: =+AA1180+30 -> 40609 | AB1181: 223.467
AA1182: =+AA1181+30 -> 40639 | AB1182: 224.906
AA1183: =+AA1182+30 -> 40669 | AB1183: 225.964
AA1184: =+AA1183+30 -> 40699 | AB1184: 225.722
AA1185: =+AA1184+30 -> 40729 | AB1185: 225.922
AA1186: =+AA1185+30 -> 40759 | AB1186: 226.545
AA1187: =+AA1186+30 -> 40789 | AB1187: 226.889
AA1188: =AA1187+30 -> 40819 | AB1188: 226.421
AA1189: =AA1188+30 -> 40849 | AB1189: 226.23
AA1190: =AA1189+30 -> 40879 | AB1190: 225.672
AA1191: 40923 | AB1191: 226.665
AA1192: =AA1191+30 -> 40953 | AB1192: 227.663
AA1193: =AA1192+30 -> 40983 | AB1193: 229.392
AA1194: =AA1193+30 -> 41013 | AB1194: 230.085
...

Sheet PCE
D1: http://alfred.stlouisfed.org/series/downloaddata?seid=PCECTPI&cid=21 | K1: observation_date | L1: PCECTPI_20210930
B2: Year | C2: Index | D2: Base=2012 | K2: 17168 | L2: 12.226 | N2: Series ID: PCECTPI
B3: 1947 | C3: 15.702 | D3: =AVERAGE(L2:L5) -> 12.49225 | K3: 17258 | L3: 12.324 | N3: Link: http://alfred.stlouisfed.org/series?seid=PCECTPI
B4: 1948 | C4: 16.59875 | D4: =AVERAGE(L6:L9) -> 13.1995 | K4: 17349 | L4: 12.553 | N4: Help: http://alfred.stlouisfed.org/help
B5: 1949 | C5: 16.4745 | D5: =AVERAGE(L10:L13) -> 13.09575 | K5: 17441 | L5: 12.866
B6: 1950 | C6: 16.67525 | D6: =AVERAGE(L14:L17) -> 13.25175 | K6: 17533 | L6: 13.009 | N6: ALFRED (ArchivaL Federal Reserve Economic Data)
B7: 1951 | C7: 17.805 | D7: =AVERAGE(L18:L21) -> 14.1545 | K7: 17624 | L7: 13.143 | N7: Economic Research Division
B8: 1952 | C8: 18.169 | D8: =AVERAGE(L22:L25) -> 14.44475 | K8: 17715 | L8: 13.344 | N8: Federal Reserve Bank of St. Louis
B9: 1953 | C9: 18.4155 | D9: =AVERAGE(L26:L29) -> 14.6345 | K9: 17807 | L9: 13.302
B10: 1954 | C10: 18.58475 | D10: =AVERAGE(L30:L33) -> 14.758 | K10: 17899 | L10: 13.197 | N10: Output Format: Observations by Vintage Date, All Observations
B11: 1955 | C11: 18.6765 | D11: =AVERAGE(L34:L37) -> 14.8155 | K11: 17989 | L11: 13.116 | N11: File Created: 2014-10-16 1:31 PM CDT
B12: 1956 | C12: 19.0585 | D12: =AVERAGE(L38:L41) -> 15.11075 | K12: 18080 | L12: 13.04
B13: 1957 | C13: 19.63925 | D13: =AVERAGE(L42:L45) -> 15.56975 | K13: 18172 | L13: 13.03 | O13: Real-Time | P13: Period | S13: observation_date | T13: PCECTPI_20150925
B14: 1958 | C14: 20.11725 | D14: =AVERAGE(L46:L49) -> 15.93825 | K14: 18264 | L14: 13.009 | N14: Title: | O14: Start | P14: End | S14: 17168 | T14: 13.04
B15: 1959 | C15: 20.4315 | D15: =AVERAGE(L50:L53) -> 16.17575 | K15: 18354 | L15: 13.071 | N15: Personal Consumption Expenditures: Chain-type Price Index | O15: 35083 | P15: Current | S15: 17258 | T15: 13.145
B16: 1960 | C16: 20.76675 | D16: =AVERAGE(L54:L57) -> 16.44125 | K16: 18445 | L16: 13.345 | S16: 17349 | T16: 13.39
B17: 1961 | C17: 20.98475 | D17: =AVERAGE(L58:L61) -> 16.6115 | K17: 18537 | L17: 13.582 | N17: Source: | S17: 17441 | T17: 13.723
B18: 1962 | C18: 21.23175 | D18: =AVERAGE(L62:L65) -> 16.80625 | K18: 18629 | L18: 14.014 | N18: U.S. Department of Commerce: Bureau of Economic Analysis | O18: 35083 | P18: Current | S18: 17533 | T18: 13.875
B19: 1963 | C19: 21.479 | D19: =AVERAGE(L66:L69) -> 17.00725 | K19: 18719 | L19: 14.126 | S19: 17624 | T19: 14.018
B20: 1964 | C20: 21.78625 | D20: =AVERAGE(L70:L73) -> 17.2535 | K20: 18810 | L20: 14.145 | N20: Release: | S20: 17715 | T20: 14.233
B21: 1965 | C21: 22.10325 | D21: =AVERAGE(L74:L77) -> 17.502 | K21: 18902 | L21: 14.333 | N21: Gross Domestic Product | O21: 35083 | P21: Current | S21: 17807 | T21: 14.188
B22: 1966 | C22: 22.66225 | D22: =AVERAGE(L78:L81) -> 17.9445 | K22: 18994 | L22: 14.394 | S22: 17899 | T22: 14.076
B23: 1967 | C23: 23.237 | D23: =AVERAGE(L82:L85) -> 18.39525 | K23: 19085 | L23: 14.391 | N23: Units: | S23: 17989 | T23: 13.99
B24: 1968 | C24: 24.1515 | D24: =AVERAGE(L86:L89) -> 19.11525 | K24: 19176 | L24: 14.485 | N24: Index 2009=100 | O24: 41486 | P24: Current | S24: 18080 | T24: 13.91
B25: 1969 | C25: 25.255 | D25: =AVERAGE(L90:L93) -> 19.976 | K25: 19268 | L25: 14.509 | S25: 18172 | T25: 13.899
B26: 1970 | C26: 26.4485 | D26: =AVERAGE(L94:L97) -> 20.91 | K26: 19360 | L26: 14.563 | N26: Frequency: | S26: 18264 | T26: 13.876
B27: 1971 | C27: 27.5735 | D27: =AVERAGE(L98:L101) -> 21.798 | K27: 19450 | L27: 14.585 | N27: Quarterly | O27: 35083 | P27: Current | S27: 18354 | T27: 13.943
B28: 1972 | C28: 28.52775 | D28: =AVERAGE(L102:L105) -> 22.54175 | K28: 19541 | L28: 14.663 | S28: 18445 | T28: 14.235
B29: 1973 | C29: 30.08075 | D29: =AVERAGE(L106:L109) -> 23.7555 | K29: 19633 | L29: 14.727 | N29: Seasonal Adjustment: | S29: 18537 | T29: 14.488
B30: 1974 | C30: 33.191 | D30: =AVERAGE(L110:L113) -> 26.22875 | K30: 19725 | L30: 14.801 | N30: Seasonally Adjusted | O30: 35083 | P30: Current | S30: 18629 | T30: 14.949
B31: 1975 | C31: 35.95475 | D31: =AVERAGE(L114:L117) -> 28.415 | K31: 19815 | L31: 14.781 | S31: 18719 | T31: 15.068
B32: 1976 | C32: 37.94825 | D32: =AVERAGE(L118:L121) -> 29.97375 | K32: 19906 | L32: 14.732 | N32: Notes: | S32: 18810 | T32: 15.088
B33: 1977 | C33: 40.40975 | D33: =AVERAGE(L122:L125) -> 31.92325 | K33: 19998 | L33: 14.718 | N33: BEA Account Code: DPCERG3 | O33: 35083 | P33: Current | S33: 18902 | T33: 15.288
B34: 1978 | C34: 43.2485 | D34: =AVERAGE(L126:L129) -> 34.1445 | K34: 20090 | L34: 14.765 | S34: 18994 | T34: 15.353
B35: 1979 | C35: 47.059 | D35: =AVERAGE(L130:L133) -> 37.17825 | K35: 20180 | L35: 14.78 | N35: A Guide to the National Income and Product Accounts of the United | S35: 19085 | T35: 15.35
B36: 1980 | C36: 52.0775 | D36: =AVERAGE(L134:L137) -> 41.1815 | K36: 20271 | L36: 14.838 | N36: States (NIPA) - (http://www.bea.gov/national/pdf/nipaguid.pdf) | S36: 19176 | T36: 15.451
B37: 1981 | C37: 56.71975 | D37: =AVERAGE(L138:L141) -> 44.871 | K37: 20363 | L37: 14.879 | S37: 19268 | T37: 15.477
B38: 1982 | C38: 59.8585 | D38: =AVERAGE(L142:L145) -> 47.3635 | K38: 20455 | L38: 14.94 | S38: 19360 | T38: 15.536
B39: 1983 | C39: 62.436 | D39: =AVERAGE(L146:L149) -> 49.37825 | K39: 20546 | L39: 15.04 | N39: Vintage Dates Specified: | S39: 19450 | T39: 15.56
B40: 1984 | C40: 64.79525 | D40: =AVERAGE(L150:L153) -> 51.243 | K40: 20637 | L40: 15.187 | S40: 19541 | T40: 15.644
B41: 1985 | C41: 66.9355 | D41: =AVERAGE(L154:L157) -> 53.03075 | K41: 20729 | L41: 15.276 | N41: 41908 | S41: 19633 | T41: 15.713
B42: 1986 | C42: 68.56875 | D42: =AVERAGE(L158:L161) -> 54.18425 | K42: 20821 | L42: 15.413 | S42: 19725 | T42: 15.792
B43: 1987 | C43: 70.94675 | D43: =AVERAGE(L162:L165) -> 55.855 | K43: 20911 | L43: 15.511 | S43: 19815 | T43: 15.77
B44: 1988 | C44: 73.7555 | D44: =AVERAGE(L166:L169) -> 58.0375 | K44: 21002 | L44: 15.637 | S44: 19906 | T44: 15.718
B45: 1989 | C45: 76.97225 | D45: =AVERAGE(L170:L173) -> 60.572 | K45: 21094 | L45: 15.718 | S45: 19998 | T45: 15.703
B46: 1990 | C46: 80.49775 | D46: =AVERAGE(L174:L177) -> 63.2315 | K46: 21186 | L46: 15.912 | S46: 20090 | T46: 15.755
B47: 1991 | C47: 83.4185 | D47: =AVERAGE(L178:L181) -> 65.3455 | K47: 21276 | L47: 15.941 | S47: 20180 | T47: 15.771
B48: 1992 | C48: 85.8245 | D48: =AVERAGE(L182:L185) -> 67.08725 | K48: 21367 | L48: 15.953 | S48: 20271 | T48: 15.834
B49: 1993 | C49: 87.804 | D49: =AVERAGE(L186:L189) -> 68.7585 | K49: 21459 | L49: 15.947 | S49: 20363 | T49: 15.878
B50: 1994 | C50: 89.6535 | D50: =AVERAGE(L190:L193) -> 70.193 | K50: 21551 | L50: 16.056 | S50: 20455 | T50: 15.943
B51: 1995 | C51: 91.57675 | D51: =AVERAGE(L194:L197) -> 71.67125 | K51: 21641 | L51: 16.121 | S51: 20546 | T51: 16.051
B52: 1996 | C52: 93.54675 | D52: =AVERAGE(L198:L201) -> 73.20375 | K52: 21732 | L52: 16.219 | S52: 20637 | T52: 16.208
B53: 1997 | C53: 95.124 | D53: =AVERAGE(L202:L205) -> 74.478 | K53: 21824 | L53: 16.307 | S53: 20729 | T53: 16.303
B54: 1998 | C54: 95.978 | D54: =AVERAGE(L206:L209) -> 75.0705 | K54: 21916 | L54: 16.328 | S54: 20821 | T54: 16.45
B55: 1999 | C55: 97.57475 | D55: =AVERAGE(L210:L213) -> 76.16425 | K55: 22007 | L55: 16.414 | S55: 20911 | T55: 16.554
B56: 2000 | C56: 99.99975 | D56: =AVERAGE(L214:L217) -> 78.0905 | K56: 22098 | L56: 16.475 | S56: 21002 | T56: 16.687
B57: 2001 | C57: 102.094 | D57: =AVERAGE(L218:L221) -> 79.65625 | K57: 22190 | L57: 16.548 | S57: 21094 | T57: 16.773
B58: 2002 | C58: 103.54175 | D58: =AVERAGE(L222:L225) -> 80.70175 | K58: 22282 | L58: 16.579 | S58: 21186 | T58: 16.979
B59: 2003 | C59: 105.52025 | D59: =AVERAGE(L226:L229) -> 82.3975 | K59: 22372 | L59: 16.577 | S59: 21276 | T59: 17.009
B60: 2004 | C60: 108.24575 | D60: =AVERAGE(L230:L233) -> 84.443 | K60: 22463 | L60: 16.636 | S60: 21367 | T60: 17.023
B61: 2005 | C61: 111.31275 | D61: =AVERAGE(L234:L237) -> 86.87575 | E61: =AVERAGE(O246:O249) -> #DIV/0! | K61: 22555 | L61: 16.654 | S61: 21459 | T61: 17.018
B62: =+B61+1 -> 2006 | C62: =+C61*D62/D61 -> 114.4471 | D62: =AVERAGE(L238:L241) -> 89.322 | E62: =AVERAGE(O250:O253) -> #DIV/0! | K62: 22647 | L62: 16.726 | S62: 21551 | T62: 17.137
B63: =+B62+1 -> 2007 | C63: =+C62*D63/D62 -> 117.38413 | D63: =AVERAGE(L242:L245) -> 91.61425 | E63: =AVERAGE(O254:O257) -> #DIV/0! | K63: 22737 | L63: 16.786 | S63: 21641 | T63: 17.204
B64: =+B63+1 -> 2008 | C64: =+C63*D64/D63 -> 120.85802 | D64: =AVERAGE(L246:L249) -> 94.3255 | E64: =AVERAGE(O258:O261) -> #DIV/0! | K64: 22828 | L64: 16.831 | S64: 21732 | T64: 17.307
B65: =+B64+1 -> 2009 | C65: =+C64*E65/E64 -> #DIV/0! | D65: =AVERAGE(L250:L253) -> 94.06275 | E65: =AVERAGE(O262:O265) -> #DIV/0! | K65: 22920 | L65: 16.882 | S65: 21824 | T65: 17.401
B66: =+B65+1 -> 2010 | C66: =+C65*E66/E65 -> #DIV/0! | D66: =AVERAGE(L254:L257) -> 95.74725 | E66: =AVERAGE(O266:O269) -> #DIV/0! | K66: 23012 | L66: 16.931 | S66: 21916 | T66: 17.424
B67: =+B66+1 -> 2011 | D67: =AVERAGE(L258:L261) -> 98.1695 | K67: 23102 | L67: 16.957 | S67: 22007 | T67: 17.516
B68: =+B67+1 -> 2012 | D68: =AVERAGE(L262:L265) -> 100 | K68: 23193 | L68: 17.039 | S68: 22098 | T68: 17.583
B69: =+B68+1 -> 2013 | D69: =AVERAGE(L266:L269) -> 101.35425 | K69: 23285 | L69: 17.102 | S69: 22190 | T69: 17.661
B70: =+B69+1 -> 2014 | D70: =AVERAGE(L270:L273) -> 102.8865 | K70: 23377 | L70: 17.183 | S70: 22282 | T70: 17.694
B71: =+B70+1 -> 2015 | D71: =AVERAGE(L274:L277) -> 103.1155 | K71: 23468 | L71: 17.22 | S71: 22372 | T71: 17.692
B72: =+B71+1 -> 2016 | D72: =AVERAGE(L278:L281) -> 104.14825 | K72: 23559 | L72: 17.277 | S72: 22463 | T72: 17.757
B73: =+B72+1 -> 2017 | D73: =AVERAGE(L282:L285) -> 106.05375 | K73: 23651 | L73: 17.334 | S73: 22555 | T73: 17.777
B74: =+B73+1 -> 2018 | D74: =AVERAGE(L286:L289) -> 108.31675 | K74: 23743 | L74: 17.39 | S74: 22647 | T74: 17.856
B75: =+B74+1 -> 2019 | D75: =AVERAGE(L290:L293) -> 109.933 | K75: 23833 | L75: 17.478 | S75: 22737 | T75: 17.918
B76: =+B75+1 -> 2020 | D76: =AVERAGE(L294:L297) -> 111.1445 | K76: 23924 | L76: 17.543 | S76: 22828 | T76: 17.965
B77: =+B76+1 -> 2021 | D77: =AVERAGE(L298:L301) -> 115.62075 | K77: 24016 | L77: 17.597 | S77: 22920 | T77: 18.018
B78: =+B77+1 -> 2022 | D78: =AVERAGE(L302:L305) -> 122.861 | K78: 24108 | L78: 17.733 | S78: 23012 | T78: 18.069
K79: 24198 | L79: 17.878 | S79: 23102 | T79: 18.095
K80: 24289 | L80: 18.014 | S80: 23193 | T80: 18.181
K81: 24381 | L81: 18.153 | S81: 23285 | T81: 18.249
K82: 24473 | L82: 18.206 | S82: 23377 | T82: 18.336
K83: 24563 | L83: 18.292 | S83: 23468 | T83: 18.378
K84: 24654 | L84: 18.462 | S84: 23559 | T84: 18.44
K85: 24746 | L85: 18.621 | S85: 23651 | T85: 18.503
K86: 24838 | L86: 18.819 | S86: 23743 | T86: 18.562
K87: 24929 | L87: 19.012 | S87: 23833 | T87: 18.655
K88: 25020 | L88: 19.209 | S88: 23924 | T88: 18.725
K89: 25112 | L89: 19.421 | S89: 24016 | T89: 18.782
K90: 25204 | L90: 19.609 | S90: 24108 | T90: 18.928
... K287: 43191 | L287: 108.166 | S287: 42095 | T287: 109.391
K288: 43282 | L288: 108.552
K289: 43374 | L289: 108.961
K290: 43466 | L290: 109.188
K291: 43556 | L291: 109.857
K292: 43647 | L292: 110.144
K293: 43739 | L293: 110.543
K294: 43831 | L294: 110.946
K295: 43922 | L295: 110.445
K296: 44013 | L296: 111.366
...

Sheet Sheet3
A1: Year | B1: pce | C1: cpi-u-rs | D1: cpiu | E1: cpiu-rs67 | F1: cpiu67 | G1: ratio | H1: cpiu-rs78 | I1: cpiu78 | J1: ratio | K1: pce2 | L1: cpi-u-rs2 | M1: cpiu2 | N1: cpiux | O1: pce84 | P1: cpi-u-rs84 | Q1: cpiu84
A2: 1947 | B2: =PCE!D3 -> 12.49225 | C2: =+'CPI-U-RS'!D7 -> 37.5 | D2: 22.3 | E2: =+C$22/C2 -> 1.496 | F2: =+D$22/D2 -> 1.4977578 | G2: =+E2/F2 -> 0.99882635 | H2: =+C$33/C2 -> 2.784 | I2: =+D$33/D2 -> 2.9237668 | J2: =+H2/I2 -> 0.95219632 | K2: =+B2/B$39 -> 0.24378452 | L2: =+C2/C$39 -> 0.2340824 | M2: =+D2/D$39 -> 0.21462945 | N2: 0 | O2: =+B$39/B2 -> 4.1019832 | P2: =+C$39/C2 -> 4.272 | Q2: =+D$39/D2 -> 4.6591928 | R2: 0 | S2: =+ROUND(J2,4) -> 0.9522
A3: 1948 | B3: =PCE!D4 -> 13.1995 | C3: =+'CPI-U-RS'!D8 -> 40.5 | D3: 24.1 | E3: =+C$22/C3 -> 1.3851852 | F3: =+D$22/D3 -> 1.3858921 | G3: =+E3/F3 -> 0.99948991 | H3: =+C$33/C3 -> 2.5777778 | I3: =+D$33/D3 -> 2.7053942 | J3: =+H3/I3 -> 0.9528289 | K3: =+B3/$B$39 -> 0.2575864 | L3: =+C3/C$39 -> 0.25280899 | M3: =+D3/D$39 -> 0.2319538 | N3: 0 | O3: =+B$39/B3 -> 3.8821925 | P3: =+C$39/C3 -> 3.9555556 | Q3: =+D$39/D3 -> 4.3112033 | R3: 0 | S3: =+ROUND(J3,4) -> 0.9528
A4: 1949 | B4: =PCE!D5 -> 13.09575 | C4: =+'CPI-U-RS'!D9 -> 40 | D4: 23.8 | E4: =+C$22/C4 -> 1.4025 | F4: =+D$22/D4 -> 1.4033613 | G4: =+E4/F4 -> 0.99938623 | H4: =+C$33/C4 -> 2.61 | I4: =+D$33/D4 -> 2.7394958 | J4: =+H4/I4 -> 0.95273006 | K4: =+B4/$B$39 -> 0.25556174 | L4: =+C4/C$39 -> 0.24968789 | M4: =+D4/D$39 -> 0.22906641 | N4: 0 | O4: =+B$39/B4 -> 3.9129489 | P4: =+C$39/C4 -> 4.005 | Q4: =+D$39/D4 -> 4.3655462 | R4: 0 | S4: =+ROUND(J4,4) -> 0.9527
A5: 1950 | B5: =PCE!D6 -> 13.25175 | C5: =+'CPI-U-RS'!D10 -> 40.5 | D5: 24.1 | E5: =+C$22/C5 -> 1.3851852 | F5: =+D$22/D5 -> 1.3858921 | G5: =+E5/F5 -> 0.99948991 | H5: =+C$33/C5 -> 2.5777778 | I5: =+D$33/D5 -> 2.7053942 | J5: =+H5/I5 -> 0.9528289 | K5: =+B5/$B$39 -> 0.25860605 | L5: =+C5/C$39 -> 0.25280899 | M5: =+D5/D$39 -> 0.2319538 | N5: 0.2518797 | O5: =+B$39/B5 -> 3.8668855 | P5: =+C$39/C5 -> 3.9555556 | Q5: =+D$39/D5 -> 4.3112033 | R5: 0 | S5: =+ROUND(J5,4) -> 0.9528
A6: 1951 | B6: =PCE!D7 -> 14.1545 | C6: =+'CPI-U-RS'!D11 -> 43.7 | D6: 26 | E6: =+C$22/C6 -> 1.2837529 | F6: =+D$22/D6 -> 1.2846154 | G6: =+E6/F6 -> 0.99932857 | H6: =+C$33/C6 -> 2.389016 | I6: =+D$33/D6 -> 2.5076923 | J6: =+H6/I6 -> 0.9526751 | K6: =+B6/$B$39 -> 0.27622309 | L6: =+C6/C$39 -> 0.27278402 | M6: =+D6/D$39 -> 0.25024062 | N6: 0.27255639 | O6: =+B$39/B6 -> 3.6202621 | P6: =+C$39/C6 -> 3.6659039 | Q6: =+D$39/D6 -> 3.9961538 | R6: 0 | S6: =+ROUND(J6,4) -> 0.9527
A7: 1952 | B7: =PCE!D8 -> 14.44475 | C7: =+'CPI-U-RS'!D12 -> 44.5 | D7: 26.5 | E7: =+C$22/C7 -> 1.2606742 | F7: =+D$22/D7 -> 1.2603774 | G7: =+E7/F7 -> 1.0002355 | H7: =+C$33/C7 -> 2.3460674 | I7: =+D$33/D7 -> 2.4603774 | J7: =+H7/I7 -> 0.95353967 | K7: =+B7/$B$39 -> 0.28188728 | L7: =+C7/C$39 -> 0.27777778 | M7: =+D7/D$39 -> 0.25505294 | N7: 0.27631579 | O7: =+B$39/B7 -> 3.5475173 | P7: =+C$39/C7 -> 3.6 | Q7: =+D$39/D7 -> 3.9207547 | R7: 0 | S7: =+ROUND(J7,4) -> 0.9535
A8: 1953 | B8: =PCE!D9 -> 14.6345 | C8: =+'CPI-U-RS'!D13 -> 44.8 | D8: 26.7 | E8: =+C$22/C8 -> 1.2522321 | F8: =+D$22/D8 -> 1.2509363 | G8: =+E8/F8 -> 1.0010359 | H8: =+C$33/C8 -> 2.3303571 | I8: =+D$33/D8 -> 2.4419476 | J8: =+H8/I8 -> 0.9543027 | K8: =+B8/$B$39 -> 0.28559023 | L8: =+C8/C$39 -> 0.27965044 | M8: =+D8/D$39 -> 0.25697786 | N8: 0.27819549 | O8: =+B$39/B8 -> 3.5015204 | P8: =+C$39/C8 -> 3.5758929 | Q8: =+D$39/D8 -> 3.8913858 | R8: 0 | S8: =+ROUND(J8,4) -> 0.9543
A9: 1954 | B9: =PCE!D10 -> 14.758 | C9: =+'CPI-U-RS'!D14 -> 45.2 | D9: 26.9 | E9: =+C$22/C9 -> 1.2411504 | F9: =+D$22/D9 -> 1.2416357 | G9: =+E9/F9 -> 0.99960919 | H9: =+C$33/C9 -> 2.3097345 | I9: =+D$33/D9 -> 2.4237918 | J9: =+H9/I9 -> 0.95294261 | K9: =+B9/$B$39 -> 0.28800031 | L9: =+C9/C$39 -> 0.28214732 | M9: =+D9/D$39 -> 0.25890279 | N9: 0.28195489 | O9: =+B$39/B9 -> 3.4722185 | P9: =+C$39/C9 -> 3.5442478 | Q9: =+D$39/D9 -> 3.8624535 | R9: 0 | S9: =+ROUND(J9,4) -> 0.9529
A10: 1955 | B10: =PCE!D11 -> 14.8155 | C10: =+'CPI-U-RS'!D15 -> 45 | D10: 26.8 | E10: =+C$22/C10 -> 1.2466667 | F10: =+D$22/D10 -> 1.2462687 | G10: =+E10/F10 -> 1.0003194 | H10: =+C$33/C10 -> 2.32 | I10: =+D$33/D10 -> 2.4328358 | J10: =+H10/I10 -> 0.95361963 | K10: =+B10/$B$39 -> 0.28912242 | L10: =+C10/C$39 -> 0.28089888 | M10: =+D10/D$39 -> 0.25794033 | N10: 0.28007519 | O10: =+B$39/B10 -> 3.4587425 | P10: =+C$39/C10 -> 3.56 | Q10: =+D$39/D10 -> 3.8768657 | R10: 0 | S10: =+ROUND(J10,4) -> 0.9536
A11: 1956 | B11: =PCE!D12 -> 15.11075 | C11: =+'CPI-U-RS'!D16 -> 45.7 | D11: 27.2 | E11: =+C$22/C11 -> 1.2275711 | F11: =+D$22/D11 -> 1.2279412 | G11: =+E11/F11 -> 0.99969863 | H11: =+C$33/C11 -> 2.2844639 | I11: =+D$33/D11 -> 2.3970588 | J11: =+H11/I11 -> 0.95302788 | K11: =+B11/$B$39 -> 0.29488418 | L11: =+C11/C$39 -> 0.28526841 | M11: =+D11/D$39 -> 0.26179018 | N11: 0.28571429 | O11: =+B$39/B11 -> 3.3911619 | P11: =+C$39/C11 -> 3.5054705 | Q11: =+D$39/D11 -> 3.8198529 | R11: 0 | S11: =+ROUND(J11,4) -> 0.953
A12: 1957 | B12: =PCE!D13 -> 15.56975 | C12: =+'CPI-U-RS'!D17 -> 47.2 | D12: 28.1 | E12: =+C$22/C12 -> 1.1885593 | F12: =+D$22/D12 -> 1.1886121 | G12: =+E12/F12 -> 0.9999556 | H12: =+C$33/C12 -> 2.2118644 | I12: =+D$33/D12 -> 2.3202847 | J12: =+H12/I12 -> 0.95327285 | K12: =+B12/$B$39 -> 0.3038415 | L12: =+C12/C$39 -> 0.29463171 | M12: =+D12/D$39 -> 0.27045236 | N12: 0.29323308 | O12: =+B$39/B12 -> 3.2911896 | P12: =+C$39/C12 -> 3.3940678 | Q12: =+D$39/D12 -> 3.6975089 | R12: 0 | S12: =+ROUND(J12,4) -> 0.9533
A13: 1958 | B13: =PCE!D14 -> 15.93825 | C13: =+'CPI-U-RS'!D18 -> 48.5 | D13: 28.9 | E13: =+C$22/C13 -> 1.156701 | F13: =+D$22/D13 -> 1.1557093 | G13: =+E13/F13 -> 1.0008581 | H13: =+C$33/C13 -> 2.1525773 | I13: =+D$33/D13 -> 2.2560554 | J13: =+H13/I13 -> 0.9541332 | K13: =+B13/$B$39 -> 0.31103273 | L13: =+C13/C$39 -> 0.30274657 | M13: =+D13/D$39 -> 0.27815207 | N13: 0.30263158 | O13: =+B$39/B13 -> 3.2150958 | P13: =+C$39/C13 -> 3.3030928 | Q13: =+D$39/D13 -> 3.5951557 | R13: 0 | S13: =+ROUND(J13,4) -> 0.9541
A14: 1959 | B14: =PCE!D15 -> 16.17575 | C14: =+'CPI-U-RS'!D19 -> 48.9 | D14: 29.1 | E14: =+C$22/C14 -> 1.1472393 | F14: =+D$22/D14 -> 1.1477663 | G14: =+E14/F14 -> 0.9995408 | H14: =+C$33/C14 -> 2.1349693 | I14: =+D$33/D14 -> 2.2405498 | J14: =+H14/I14 -> 0.95287741 | K14: =+B14/$B$39 -> 0.31566751 | L14: =+C14/C$39 -> 0.30524345 | M14: =+D14/D$39 -> 0.280077 | N14: 0.30451128 | O14: =+B$39/B14 -> 3.1678902 | P14: =+C$39/C14 -> 3.2760736 | Q14: =+D$39/D14 -> 3.5704467 | R14: 0 | S14: =+ROUND(J14,4) -> 0.9529
... A19: 1964 | B19: =PCE!D20 -> 17.2535 | C19: =+'CPI-U-RS'!D24 -> 52.1 | D19: 31 | E19: =+C$22/C19 -> 1.0767754 | F19: =+D$22/D19 -> 1.0774194 | G19: =+E19/F19 -> 0.99940235 | H19: =+C$33/C19 -> 2.0038388 | I19: =+D$33/D19 -> 2.1032258 | J19: =+H19/I19 -> 0.95274543 | K19: =+B19/$B$39 -> 0.33669965 | L19: =+C19/C$39 -> 0.32521848 | M19: =+D19/D$39 -> 0.29836381 | N19: 0.32518797 | O19: =+B$39/B19 -> 2.9700061 | P19: =+C$39/C19 -> 3.074856 | Q19: =+D$39/D19 -> 3.3516129 | R19: 0 | S19: =+ROUND(J19,4) -> 0.9527
A20: 1965 | B20: =PCE!D21 -> 17.502 | C20: =+'CPI-U-RS'!D25 -> 52.9 | D20: 31.5 | E20: =+C$22/C20 -> 1.0604915 | F20: =+D$22/D20 -> 1.0603175 | G20: =+E20/F20 -> 1.0001641 | H20: =+C$33/C20 -> 1.973535 | I20: =+D$33/D20 -> 2.0698413 | J20: =+H20/I20 -> 0.95347165 | K20: =+B20/$B$39 -> 0.34154909 | L20: =+C20/C$39 -> 0.33021223 | M20: =+D20/D$39 -> 0.30317613 | N20: 0.32894737 | O20: =+B$39/B20 -> 2.9278368 | P20: =+C$39/C20 -> 3.0283554 | Q20: =+D$39/D20 -> 3.2984127 | R20: 0 | S20: =+ROUND(J20,4) -> 0.9535 | U20: =+C35/C39 -> 0.79338327
A21: 1966 | B21: =PCE!D22 -> 17.9445 | C21: =+'CPI-U-RS'!D26 -> 54.4 | D21: 32.4 | E21: =+C$22/C21 -> 1.03125 | F21: =+D$22/D21 -> 1.0308642 | G21: =+E21/F21 -> 1.0003743 | H21: =+C$33/C21 -> 1.9191176 | I21: =+D$33/D21 -> 2.0123457 | J21: =+H21/I21 -> 0.95367196 | K21: =+B21/$B$39 -> 0.35018442 | L21: =+C21/C$39 -> 0.33957553 | M21: =+D21/D$39 -> 0.31183831 | N21: 0.33834586 | O21: =+B$39/B21 -> 2.8556382 | P21: =+C$39/C21 -> 2.9448529 | Q21: =+D$39/D21 -> 3.2067901 | R21: 0 | S21: =+ROUND(J21,4) -> 0.9537 | U21: =+L35/L39 -> 0.79338327
A22: 1967 | B22: =PCE!D23 -> 18.39525 | C22: =+'CPI-U-RS'!D27 -> 56.1 | D22: 33.4 | E22: =+C$22/C22 -> 1 | F22: =+D$22/D22 -> 1 | G22: =+E22/F22 -> 1 | H22: =+C$33/C22 -> 1.8609626 | I22: =+D$33/D22 -> 1.9520958 | J22: =+H22/I22 -> 0.95331518 | K22: =+B22/$B$39 -> 0.35898074 | L22: =+C22/C$39 -> 0.35018727 | M22: =+D22/D$39 -> 0.32146295 | N22: 0.34962406 | O22: =+B$39/B22 -> 2.7856648 | P22: =+C$39/C22 -> 2.855615 | Q22: =+D$39/D22 -> 3.1107784 | R22: 0 | S22: =+ROUND(J22,4) -> 0.9533
A23: 1968 | B23: =PCE!D24 -> 19.11525 | C23: =+'CPI-U-RS'!D28 -> 58.3 | D23: 34.8 | E23: =+C$22/C23 -> 0.96226415 | F23: =+D$22/D23 -> 0.95977011 | G23: =+E23/F23 -> 1.0025986 | H23: =+C$33/C23 -> 1.7907376 | I23: =+D$33/D23 -> 1.8735632 | J23: =+H23/I23 -> 0.95579244 | K23: =+B23/$B$39 -> 0.37303144 | L23: =+C23/C$39 -> 0.3639201 | M23: =+D23/D$39 -> 0.33493744 | N23: 0.36278195 | O23: =+B$39/B23 -> 2.6807392 | P23: =+C$39/C23 -> 2.7478559 | Q23: =+D$39/D23 -> 2.9856322 | R23: 0 | S23: =+ROUND(J23,4) -> 0.9558
A24: 1969 | B24: =PCE!D25 -> 19.976 | C24: =+'CPI-U-RS'!D29 -> 60.9 | D24: 36.7 | E24: =+C$22/C24 -> 0.92118227 | F24: =+D$22/D24 -> 0.91008174 | G24: =+E24/F24 -> 1.0121973 | H24: =+C$33/C24 -> 1.7142857 | I24: =+D$33/D24 -> 1.7765668 | J24: =+H24/I24 -> 0.96494303 | K24: =+B24/$B$39 -> 0.38982885 | L24: =+C24/C$39 -> 0.38014981 | M24: =+D24/D$39 -> 0.35322425 | N24: 0.37969925 | O24: =+B$39/B24 -> 2.5652283 | P24: =+C$39/C24 -> 2.6305419 | Q24: =+D$39/D24 -> 2.8310627 | R24: 0 | S24: =+ROUND(J24,4) -> 0.9649
A25: 1970 | B25: =PCE!D26 -> 20.91 | C25: =+'CPI-U-RS'!D30 -> 63.9 | D25: 38.8 | E25: =+C$22/C25 -> 0.87793427 | F25: =+D$22/D25 -> 0.86082474 | G25: =+E25/F25 -> 1.0198757 | H25: =+C$33/C25 -> 1.6338028 | I25: =+D$33/D25 -> 1.6804124 | J25: =+H25/I25 -> 0.97226303 | K25: =+B25/$B$39 -> 0.40805573 | L25: =+C25/C$39 -> 0.3988764 | M25: =+D25/D$39 -> 0.373436 | N25: 0.39661654 | O25: =+B$39/B25 -> 2.4506456 | P25: =+C$39/C25 -> 2.5070423 | Q25: =+D$39/D25 -> 2.6778351 | R25: 0 | S25: =+ROUND(J25,4) -> 0.9723
A26: 1971 | B26: =PCE!D27 -> 21.798 | C26: =+'CPI-U-RS'!D31 -> 66.7 | D26: 40.5 | E26: =+C$22/C26 -> 0.84107946 | F26: =+D$22/D26 -> 0.82469136 | G26: =+E26/F26 -> 1.0198718 | H26: =+C$33/C26 -> 1.5652174 | I26: =+D$33/D26 -> 1.6098765 | J26: =+H26/I26 -> 0.97225927 | K26: =+B26/$B$39 -> 0.42538493 | L26: =+C26/C$39 -> 0.41635456 | M26: =+D26/D$39 -> 0.38979788 | N26: 0.41541353 | O26: =+B$39/B26 -> 2.350812 | P26: =+C$39/C26 -> 2.4017991 | Q26: =+D$39/D26 -> 2.5654321 | R26: 0 | S26: =+ROUND(J26,4) -> 0.9723
A27: 1972 | B27: =PCE!D28 -> 22.54175 | C27: =+'CPI-U-RS'!D32 -> 68.7 | D27: 41.8 | E27: =+C$22/C27 -> 0.81659389 | F27: =+D$22/D27 -> 0.79904306 | G27: =+E27/F27 -> 1.0219648 | H27: =+C$33/C27 -> 1.5196507 | I27: =+D$33/D27 -> 1.5598086 | J27: =+H27/I27 -> 0.97425456 | K27: =+B27/$B$39 -> 0.43989911 | L27: =+C27/C$39 -> 0.42883895 | M27: =+D27/D$39 -> 0.40230991 | N27: 0.42669173 | O27: =+B$39/B27 -> 2.2732485 | P27: =+C$39/C27 -> 2.3318777 | Q27: =+D$39/D27 -> 2.4856459 | R27: 0 | S27: =+ROUND(J27,4) -> 0.9743
A28: 1973 | B28: =PCE!D29 -> 23.7555 | C28: =+'CPI-U-RS'!D33 -> 73 | D28: 44.4 | E28: =+C$22/C28 -> 0.76849315 | F28: =+D$22/D28 -> 0.75225225 | G28: =+E28/F28 -> 1.0215897 | H28: =+C$33/C28 -> 1.430137 | I28: =+D$33/D28 -> 1.4684685 | J28: =+H28/I28 -> 0.97389697 | K28: =+B28/$B$39 -> 0.46358527 | L28: =+C28/C$39 -> 0.4556804 | M28: =+D28/D$39 -> 0.42733397 | N28: 0.45488722 | O28: =+B$39/B28 -> 2.1571005 | P28: =+C$39/C28 -> 2.1945205 | Q28: =+D$39/D28 -> 2.3400901 | R28: 0 | S28: =+ROUND(J28,4) -> 0.9739 | X28: =60.6/62.1 -> 0.97584541
A29: 1974 | B29: =PCE!D30 -> 26.22875 | C29: =+'CPI-U-RS'!D34 -> 80.3 | D29: 49.3 | E29: =+C$22/C29 -> 0.69863014 | F29: =+D$22/D29 -> 0.67748479 | G29: =+E29/F29 -> 1.0312115 | H29: =+C$33/C29 -> 1.3001245 | I29: =+D$33/D29 -> 1.3225152 | J29: =+H29/I29 -> 0.98306962 | K29: =+B29/$B$39 -> 0.5118504 | L29: =+C29/C$39 -> 0.50124844 | M29: =+D29/D$39 -> 0.47449471 | N29: 0.5 | O29: =+B$39/B29 -> 1.9536958 | P29: =+C$39/C29 -> 1.9950187 | Q29: =+D$39/D29 -> 2.1075051 | R29: 0 | S29: =+ROUND(J29,4) -> 0.9831
A30: 1975 | B30: =PCE!D31 -> 28.415 | C30: =+'CPI-U-RS'!D35 -> 86.9 | D30: 53.8 | E30: =+C$22/C30 -> 0.64556962 | F30: =+D$22/D30 -> 0.62081784 | G30: =+E30/F30 -> 1.0398696 | H30: =+C$33/C30 -> 1.2013809 | I30: =+D$33/D30 -> 1.2118959 | J30: =+H30/I30 -> 0.9913235 | K30: =+B30/$B$39 -> 0.55451476 | L30: =+C30/C$39 -> 0.54244694 | M30: =+D30/D$39 -> 0.51780558 | N30: 0.54135338 | O30: =+B$39/B30 -> 1.8033785 | P30: =+C$39/C30 -> 1.8434983 | Q30: =+D$39/D30 -> 1.9312268 | R30: 0 | S30: =+ROUND(J30,4) -> 0.9913
A31: 1976 | B31: =PCE!D32 -> 29.97375 | C31: =+'CPI-U-RS'!D36 -> 91.9 | D31: 56.9 | E31: =+C$22/C31 -> 0.61044614 | F31: =+D$22/D31 -> 0.58699473 | G31: =+E31/F31 -> 1.0399517 | H31: =+C$33/C31 -> 1.1360174 | I31: =+D$33/D31 -> 1.1458699 | J31: =+H31/I31 -> 0.9914017 | K31: =+B31/$B$39 -> 0.58493355 | L31: =+C31/C$39 -> 0.57365793 | M31: =+D31/D$39 -> 0.54764196 | N31: 0.57142857 | O31: =+B$39/B31 -> 1.7095959 | P31: =+C$39/C31 -> 1.7431991 | Q31: =+D$39/D31 -> 1.8260105 | R31: 0 | S31: =+ROUND(J31,4) -> 0.9914 | V31: =+D32/D31 -> 1.0650264 | W31: =97.7/91.9 -> 1.0631121
A32: 1977 | B32: =PCE!D33 -> 31.92325 | C32: =+'CPI-U-RS'!D37 -> 97.7 | D32: 60.6 | E32: =+C$22/C32 -> 0.57420676 | F32: =+D$22/D32 -> 0.55115512 | G32: =+E32/F32 -> 1.0418242 | H32: =+C$33/C32 -> 1.0685773 | I32: =+D$33/D32 -> 1.0759076 | J32: =+H32/I32 -> 0.99318686 | K32: =+B32/$B$39 -> 0.62297777 | L32: =+C32/C$39 -> 0.60986267 | M32: =+D32/D$39 -> 0.58325313 | N32: 0.60902256 | O32: =+B$39/B32 -> 1.6051937 | P32: =+C$39/C32 -> 1.6397134 | Q32: =+D$39/D32 -> 1.7145215 | R32: 0 | S32: =+ROUND(J32,4) -> 0.9932 | U32: =(C32-C$33)/C$33 -> -0.064176245 | V32: =+D33/D32 -> 1.0759076 | W32: =+V32-U32 -> 1.1400838 | X32: =+D32/$D$32*97.7 -> 97.7
A33: 1978 | B33: =PCE!D34 -> 34.1445 | C33: =+'CPI-U-RS'!D38 -> 104.4 | D33: 65.2 | E33: =+C$22/C33 -> 0.53735632 | F33: =+D$22/D33 -> 0.51226994 | G33: =+E33/F33 -> 1.048971 | H33: =+C$33/C33 -> 1 | I33: =+D$33/D33 -> 1 | J33: =+H33/I33 -> 1 | K33: =+B33/$B$39 -> 0.66632516 | L33: =+C33/C$39 -> 0.65168539 | M33: =+D33/D$39 -> 0.62752647 | N33: 0.65037594 | O33: =+B$39/B33 -> 1.5007688 | P33: =+C$39/C33 -> 1.5344828 | Q33: =+D$39/D33 -> 1.5935583 | R33: 0 | S33: =+ROUND(J33,4) -> 1 | U33: =(C33-C$33)/C$33 -> 0 | V33: =(D33-D$33)/D$33 -> 0 | W33: =+V33-U33 -> 0 | X33: =+D33/$D$32*97.7 -> 105.11617 | Y33: =+X33/X32 -> 1.0759076
A34: 1979 | B34: =PCE!D35 -> 37.17825 | C34: =+'CPI-U-RS'!D39 -> 114.3 | D34: 72.6 | E34: =+C$22/C34 -> 0.49081365 | F34: =+D$22/D34 -> 0.4600551 | G34: =+E34/F34 -> 1.0668584 | H34: =+C$33/C34 -> 0.91338583 | I34: =+D$33/D34 -> 0.89807163 | J34: =+H34/I34 -> 1.0170523 | K34: =+B34/$B$39 -> 0.72552836 | L34: =+C34/C$39 -> 0.71348315 | M34: =+D34/D$39 -> 0.6987488 | N34: 0.71240602 | O34: =+B$39/B34 -> 1.3783059 | P34: =+C$39/C34 -> 1.4015748 | Q34: =+D$39/D34 -> 1.4311295 | R34: 0 | S34: =+ROUND(J34,4) -> 1.0171 | U34: =(C34-C$33)/C$33 -> 0.094827586 | V34: =(D34-D$33)/D$33 -> 0.11349693 | W34: =+V34-U34 -> 0.018669346
A35: 1980 | B35: =PCE!D36 -> 41.1815 | C35: =+'CPI-U-RS'!D40 -> 127.1 | D35: 82.4 | E35: =+C$22/C35 -> 0.44138474 | F35: =+D$22/D35 -> 0.40533981 | G35: =+E35/F35 -> 1.0889252 | H35: =+C$33/C35 -> 0.82140047 | I35: =+D$33/D35 -> 0.79126214 | J35: =+H35/I35 -> 1.0380889 | K35: =+B35/$B$39 -> 0.80365123 | L35: =+C35/C$39 -> 0.79338327 | M35: =+D35/D$39 -> 0.79307026 | N35: 0.79135338 | O35: =+B$39/B35 -> 1.2443209 | P35: =+C$39/C35 -> 1.2604249 | Q35: =+D$39/D35 -> 1.2609223 | R35: 0 | S35: =+ROUND(J35,4) -> 1.0381 | U35: =(C35-C$33)/C$33 -> 0.21743295 | V35: =(D35-D$33)/D$33 -> 0.26380368 | W35: =+V35-U35 -> 0.046370731
A36: 1981 | B36: =PCE!D37 -> 44.871 | C36: =+'CPI-U-RS'!D41 -> 139.1 | D36: 90.9 | E36: =+C$22/C36 -> 0.40330697 | F36: =+D$22/D36 -> 0.36743674 | G36: =+E36/F36 -> 1.0976229 | H36: =+C$33/C36 -> 0.75053918 | I36: =+D$33/D36 -> 0.71727173 | J36: =+H36/I36 -> 1.0463805 | K36: =+B36/$B$39 -> 0.87565131 | L36: =+C36/C$39 -> 0.86828964 | M36: =+D36/D$39 -> 0.87487969 | N36: 0.86654135 | O36: =+B$39/B36 -> 1.1420071 | P36: =+C$39/C36 -> 1.1516894 | Q36: =+D$39/D36 -> 1.1430143 | R36: 0 | S36: =+ROUND(J36,4) -> 1.0464 | U36: =(C36-C$33)/C$33 -> 0.33237548 | V36: =(D36-D$33)/D$33 -> 0.39417178 | W36: =+V36-U36 -> 0.0617963
A37: 1982 | B37: =PCE!D38 -> 47.3635 | C37: =+'CPI-U-RS'!D42 -> 147.5 | D37: 96.5 | E37: =+C$22/C37 -> 0.38033898 | F37: =+D$22/D37 -> 0.34611399 | G37: =+E37/F37 -> 1.0988836 | H37: =+C$33/C37 -> 0.70779661 | I37: =+D$33/D37 -> 0.67564767 | J37: =+H37/I37 -> 1.0475824 | K37: =+B37/$B$39 -> 0.9242921 | L37: =+C37/C$39 -> 0.92072409 | M37: =+D37/D$39 -> 0.92877767 | N37: 0.92105263 | O37: =+B$39/B37 -> 1.0819091 | P37: =+C$39/C37 -> 1.0861017 | Q37: =+D$39/D37 -> 1.0766839 | R37: 0 | S37: =+ROUND(J37,4) -> 1.0476 | U37: =(C37-C$33)/C$33 -> 0.41283525 | V37: =(D37-D$33)/D$33 -> 0.48006135 | W37: =+V37-U37 -> 0.067226101
A38: 1983 | B38: =PCE!D39 -> 49.37825 | C38: =+'CPI-U-RS'!D43 -> 153.8 | D38: 99.6 | E38: =+C$22/C38 -> 0.36475943 | F38: =+D$22/D38 -> 0.33534137 | G38: =+E38/F38 -> 1.0877257 | H38: =+C$33/C38 -> 0.67880364 | I38: =+D$33/D38 -> 0.65461847 | J38: =+H38/I38 -> 1.0369454 | K38: =+B38/$B$39 -> 0.96360966 | L38: =+C38/C$39 -> 0.96004994 | M38: =+D38/D$39 -> 0.95861405 | N38: 0.95864662 | O38: =+B$39/B38 -> 1.0377646 | P38: =+C$39/C38 -> 1.0416125 | Q38: =+D$39/D38 -> 1.0431727 | R38: 0 | S38: =+ROUND(J38,4) -> 1.0369 | U38: =(C38-C$33)/C$33 -> 0.47318008 | V38: =(D38-D$33)/D$33 -> 0.52760736 | W38: =+V38-U38 -> 0.054427285
A39: 1984 | B39: =PCE!D40 -> 51.243 | C39: =+'CPI-U-RS'!D44 -> 160.2 | D39: 103.9 | E39: =+C$22/C39 -> 0.35018727 | F39: =+D$22/D39 -> 0.32146295 | G39: =+E39/F39 -> 1.089355 | H39: =+C$33/C39 -> 0.65168539 | I39: =+D$33/D39 -> 0.62752647 | J39: =+H39/I39 -> 1.0384987 | K39: =+B39/$B$39 -> 1 | L39: =+C39/C$39 -> 1 | M39: =+D39/D$39 -> 1 | N39: 1 | O39: =+B$39/B39 -> 1 | P39: =+C$39/C39 -> 1 | Q39: =+D$39/D39 -> 1 | R39: 0 | S39: =+ROUND(J39,4) -> 1.0385 | U39: =(C39-C$33)/C$33 -> 0.53448276 | V39: =(D39-D$33)/D$33 -> 0.59355828 | W39: =+V39-U39 -> 0.059075524
A40: 1985 | B40: =PCE!D41 -> 53.03075 | C40: =+'CPI-U-RS'!D45 -> 165.6 | D40: 107.6 | E40: =+C$22/C40 -> 0.33876812 | F40: =+D$22/D40 -> 0.31040892 | G40: =+E40/F40 -> 1.0913608 | H40: =+C$33/C40 -> 0.63043478 | I40: =+D$33/D40 -> 0.60594796 | J40: =+H40/I40 -> 1.0404108 | K40: =+B40/$B$39 -> 1.0348877 | L40: =+C40/C$39 -> 1.0337079 | M40: =+D40/D$39 -> 1.0356112 | N40: 1.0357143 | O40: =+B$39/B40 -> 0.96628843 | P40: =+C$39/C40 -> 0.9673913 | Q40: =+D$39/D40 -> 0.96561338 | R40: 0 | S40: =+ROUND(J40,4) -> 1.0404 | U40: =(C40-C$33)/C$33 -> 0.5862069 | V40: =(D40-D$33)/D$33 -> 0.65030675 | W40: =+V40-U40 -> 0.064099852
A41: 1986 | B41: =PCE!D42 -> 54.18425 | C41: =+'CPI-U-RS'!D46 -> 168.4 | D41: 109.6 | E41: =+C$22/C41 -> 0.33313539 | F41: =+D$22/D41 -> 0.30474453 | G41: =+E41/F41 -> 1.0931628 | H41: =+C$33/C41 -> 0.61995249 | I41: =+D$33/D41 -> 0.59489051 | J41: =+H41/I41 -> 1.0421287 | K41: =+B41/$B$39 -> 1.0573981 | L41: =+C41/C$39 -> 1.051186 | M41: =+D41/D$39 -> 1.0548604 | N41: 1.0545113 | O41: =+B$39/B41 -> 0.94571762 | P41: =+C$39/C41 -> 0.95130641 | Q41: =+D$39/D41 -> 0.9479927 | R41: 0 | S41: =+ROUND(J41,4) -> 1.0421 | U41: =(C41-C$33)/C$33 -> 0.61302682 | V41: =(D41-D$33)/D$33 -> 0.6809816 | W41: =+V41-U41 -> 0.067954775
A42: 1987 | B42: =PCE!D43 -> 55.855 | C42: =+'CPI-U-RS'!D47 -> 174.1 | D42: 113.6 | E42: =+C$22/C42 -> 0.3222286 | F42: =+D$22/D42 -> 0.29401408 | G42: =+E42/F42 -> 1.0959632 | H42: =+C$33/C42 -> 0.59965537 | I42: =+D$33/D42 -> 0.57394366 | J42: =+H42/I42 -> 1.0447983 | K42: =+B42/$B$39 -> 1.0900025 | L42: =+C42/C$39 -> 1.0867665 | M42: =+D42/D$39 -> 1.093359 | N42: 1.093985 | O42: =+B$39/B42 -> 0.91742906 | P42: =+C$39/C42 -> 0.92016083 | Q42: =+D$39/D42 -> 0.91461268 | R42: 0 | S42: =+ROUND(J42,4) -> 1.0448 | U42: =(C42-C$33)/C$33 -> 0.66762452 | V42: =(D42-D$33)/D$33 -> 0.74233129 | W42: =+V42-U42 -> 0.074706767
A43: 1988 | B43: =PCE!D44 -> 58.0375 | C43: =+'CPI-U-RS'!D48 -> 180.5 | D43: 118.3 | E43: =+C$22/C43 -> 0.31080332 | F43: =+D$22/D43 -> 0.28233305 | G43: =+E43/F43 -> 1.1008393 | H43: =+C$33/C43 -> 0.57839335 | I43: =+D$33/D43 -> 0.55114117 | J43: =+H43/I43 -> 1.0494468 | K43: =+B43/$B$39 -> 1.1325937 | L43: =+C43/C$39 -> 1.1267166 | M43: =+D43/D$39 -> 1.1385948 | N43: 1.1390977 | O43: =+B$39/B43 -> 0.88292914 | P43: =+C$39/C43 -> 0.88753463 | Q43: =+D$39/D43 -> 0.87827557 | R43: 0 | S43: =+ROUND(J43,4) -> 1.0494 | U43: =(C43-C$33)/C$33 -> 0.7289272 | V43: =(D43-D$33)/D$33 -> 0.81441718 | W43: =+V43-U43 -> 0.085489975
A44: 1989 | B44: =PCE!D45 -> 60.572 | C44: =+'CPI-U-RS'!D49 -> 188.3 | D44: 124 | E44: =+C$22/C44 -> 0.29792884 | F44: =+D$22/D44 -> 0.26935484 | G44: =+E44/F44 -> 1.1060831 | H44: =+C$33/C44 -> 0.55443441 | I44: =+D$33/D44 -> 0.52580645 | J44: =+H44/I44 -> 1.0544458 | K44: =+B44/$B$39 -> 1.1820541 | L44: =+C44/C$39 -> 1.1754057 | M44: =+D44/D$39 -> 1.1934552 | N44: 1.193609 | O44: =+B$39/B44 -> 0.84598494 | P44: =+C$39/C44 -> 0.85077005 | Q44: =+D$39/D44 -> 0.83790323 | R44: 0 | S44: =+ROUND(J44,4) -> 1.0544 | U44: =(C44-C$33)/C$33 -> 0.80363985 | V44: =(D44-D$33)/D$33 -> 0.90184049 | W44: =+V44-U44 -> 0.098200644
A45: 1990 | B45: =PCE!D46 -> 63.2315 | C45: =+'CPI-U-RS'!D50 -> 197.6 | D45: 130.7 | E45: =+C$22/C45 -> 0.28390688 | F45: =+D$22/D45 -> 0.25554705 | G45: =+E45/F45 -> 1.1109769 | H45: =+C$33/C45 -> 0.52834008 | I45: =+D$33/D45 -> 0.49885233 | J45: =+H45/I45 -> 1.0591112 | K45: =+B45/$B$39 -> 1.2339539 | L45: =+C45/C$39 -> 1.2334582 | M45: =+D45/D$39 -> 1.2579403 | N45: 1.2575188 | O45: =+B$39/B45 -> 0.81040304 | P45: =+C$39/C45 -> 0.81072874 | Q45: =+D$39/D45 -> 0.79495027 | R45: 0 | S45: =+ROUND(J45,4) -> 1.0591 | U45: =(C45-C$33)/C$33 -> 0.89272031 | V45: =(D45-D$33)/D$33 -> 1.0046012 | W45: =+V45-U45 -> 0.11188092
... A58: 2003 | B58: =PCE!D59 -> 82.3975 | C58: =+'CPI-U-RS'!D63 -> 269.8 | D58: 184 | E58: =+C$22/C58 -> 0.2079318 | F58: =+D$22/D58 -> 0.18152174 | G58: =+E58/F58 -> 1.1454926 | H58: =+C$33/C58 -> 0.3869533 | I58: =+D$33/D58 -> 0.35434783 | J58: =+H58/I58 -> 1.0920154 | K58: =+B58/$B$39 -> 1.6079757 | L58: =+C58/C$39 -> 1.6841448 | M58: =+D58/D$39 -> 1.7709336 | N58: 1.7706767 | O58: =+B$39/B58 -> 0.62189994 | P58: =+C$39/C58 -> 0.59377317 | Q58: =+D$39/D58 -> 0.56467391 | R58: 0 | S58: =+ROUND(J58,4) -> 1.092 | U58: =(C58-C$33)/C$33 -> 1.5842912 | V58: =(D58-D$33)/D$33 -> 1.8220859 | W58: =+V58-U58 -> 0.2377947
A59: 2004 | B59: =PCE!D60 -> 84.443 | C59: =+'CPI-U-RS'!D64 -> 277 | D59: 188.9 | E59: =+C$22/C59 -> 0.20252708 | F59: =+D$22/D59 -> 0.17681313 | G59: =+E59/F59 -> 1.1454301 | H59: =+C$33/C59 -> 0.37689531 | I59: =+D$33/D59 -> 0.34515617 | J59: =+H59/I59 -> 1.0919559 | K59: =+B59/$B$39 -> 1.6478934 | L59: =+C59/C$39 -> 1.7290886 | M59: =+D59/D$39 -> 1.8180943 | N59: 1.8176692 | O59: =+B$39/B59 -> 0.60683538 | P59: =+C$39/C59 -> 0.57833935 | Q59: =+D$39/D59 -> 0.55002647 | R59: 0 | S59: =+ROUND(J59,4) -> 1.092
A60: 2005 | B60: =PCE!D61 -> 86.87575 | C60: =+'CPI-U-RS'!D65 -> 286.4 | D60: 195.3 | E60: =+C$22/C60 -> 0.19587989 | F60: =+D$22/D60 -> 0.17101895 | G60: =+E60/F60 -> 1.1453695 | H60: =+C$33/C60 -> 0.36452514 | I60: =+D$33/D60 -> 0.33384537 | J60: =+H60/I60 -> 1.0918982 | K60: =+B60/$B$39 -> 1.6953681 | L60: =+C60/C$39 -> 1.7877653 | M60: =+D60/D$39 -> 1.879692 | N60: 1.8796992 | O60: =+B$39/B60 -> 0.58984239 | P60: =+C$39/C60 -> 0.55935754 | Q60: =+D$39/D60 -> 0.53200205 | R60: 0 | S60: =+ROUND(J60,4) -> 1.0919
A61: =+A60+1 -> 2006 | B61: =PCE!D62 -> 89.322 | C61: =+'CPI-U-RS'!D66 -> 295.7 | D61: =+'CPI-U'!B63 -> 201.59167 | E61: =+C$22/C61 -> 0.18971931 | F61: =+D$22/D61 -> 0.16568145 | G61: =+E61/F61 -> 1.1450848 | H61: =+C$33/C61 -> 0.35306053 | I61: =+D$33/D61 -> 0.32342607 | J61: =+H61/I61 -> 1.0916267
A62: =+A61+1 -> 2007 | B62: =PCE!D63 -> 91.61425 | C62: =+'CPI-U-RS'!D67 -> 304.1 | D62: =+'CPI-U'!B64 -> 207.34242 | E62: =+C$22/C62 -> 0.18447879 | F62: =+D$22/D62 -> 0.16108619 | G62: =+E62/F62 -> 1.1452179 | H62: =+C$33/C62 -> 0.34330812 | I62: =+D$33/D62 -> 0.31445568 | J62: =+H62/I62 -> 1.0917536
A63: =+A62+1 -> 2008 | B63: =PCE!D64 -> 94.3255 | C63: =+'CPI-U-RS'!D68 -> 315.8 | D63: =+'CPI-U'!B65 -> 215.3025 | E63: =+C$22/C63 -> 0.17764408 | F63: =+D$22/D63 -> 0.15513057 | G63: =+E63/F63 -> 1.1451262 | H63: =+C$33/C63 -> 0.33058898 | I63: =+D$33/D63 -> 0.30282974 | J63: =+H63/I63 -> 1.0916662
A64: =+A63+1 -> 2009 | B64: =PCE!D65 -> 94.06275 | C64: =+'CPI-U-RS'!D69 -> 314.7 | D64: =+'CPI-U'!B66 -> 214.537 | E64: =+C$22/C64 -> 0.17826501 | F64: =+D$22/D64 -> 0.1556841 | G64: =+E64/F64 -> 1.1450432 | H64: =+C$33/C64 -> 0.33174452 | I64: =+D$33/D64 -> 0.30391028 | J64: =+H64/I64 -> 1.091587
A65: =+A64+1 -> 2010 | B65: =PCE!D66 -> 95.74725 | C65: =+'CPI-U-RS'!D70 -> 319.8 | D65: =+'CPI-U'!B67 -> 218.0555 | E65: =+C$22/C65 -> 0.17542214 | F65: =+D$22/D65 -> 0.15317201 | G65: =+E65/F65 -> 1.1452623 | H65: =+C$33/C65 -> 0.32645403 | I65: =+D$33/D65 -> 0.29900645 | J65: =+H65/I65 -> 1.091796
A66: =+A65+1 -> 2011 | B66: =PCE!D67 -> 98.1695 | C66: =+'CPI-U-RS'!D71 -> 330 | D66: =+'CPI-U'!B68 -> 224.93917 | E66: =+C$22/C66 -> 0.17 | F66: =+D$22/D66 -> 0.14848459 | G66: =+E66/F66 -> 1.1449 | H66: =+C$33/C66 -> 0.31636364 | I66: =+D$33/D66 -> 0.28985615 | J66: =+H66/I66 -> 1.0914505
A67: =+A66+1 -> 2012 | B67: =PCE!D68 -> 100 | C67: =+'CPI-U-RS'!D72 -> 336.9 | D67: =+'CPI-U'!B69 -> 229.59392 | E67: =+C$22/C67 -> 0.16651825 | F67: =+D$22/D67 -> 0.14547424 | G67: =+E67/F67 -> 1.144658 | H67: =+C$33/C67 -> 0.30988424 | I67: =+D$33/D67 -> 0.28397965 | J67: =+H67/I67 -> 1.0912199
A68: =+A67+1 -> 2013 | B68: =PCE!D69 -> 101.35425 | C68: =+'CPI-U-RS'!D73 -> 342 | D68: =+'CPI-U'!B70 -> 232.95708 | E68: =+C$22/C68 -> 0.16403509 | F68: =+D$22/D68 -> 0.14337405 | G68: =+E68/F68 -> 1.1441059 | H68: =+C$33/C68 -> 0.30526316 | I68: =+D$33/D68 -> 0.27987988 | J68: =+H68/I68 -> 1.0906935
A69: =+A68+1 -> 2014 | B69: =PCE!D70 -> 102.8865 | C69: =+'CPI-U-RS'!D74 -> 347.7 | D69: =+'CPI-U'!B71 -> 236.73617 | E69: =+C$22/C69 -> 0.16134599 | F69: =+D$22/D69 -> 0.14108533 | G69: =+E69/F69 -> 1.1436057 | H69: =+C$33/C69 -> 0.30025884 | I69: =+D$33/D69 -> 0.27541208 | J69: =+H69/I69 -> 1.0902167
A70: =+A69+1 -> 2015 | B70: =PCE!D71 -> 103.1155 | C70: =+'CPI-U-RS'!D75 -> 348.3 | D70: =+'CPI-U'!B72 -> 237.017 | E70: =+C$22/C70 -> 0.16106804 | F70: =+D$22/D70 -> 0.14091816 | G70: =+E70/F70 -> 1.14299 | H70: =+C$33/C70 -> 0.2997416 | I70: =+D$33/D70 -> 0.27508575 | J70: =+H70/I70 -> 1.0896297
A71: =+A70+1 -> 2016 | B71: =PCE!D72 -> 104.14825 | C71: =+'CPI-U-RS'!D76 -> 352.8 | D71: =+'CPI-U'!B73 -> 240.00717 | E71: =+C$22/C71 -> 0.15901361 | F71: =+D$22/D71 -> 0.13916251 | G71: =+E71/F71 -> 1.1426469 | H71: =+C$33/C71 -> 0.29591837 | I71: =+D$33/D71 -> 0.27165855 | J71: =+H71/I71 -> 1.0893026
A72: 2017 | B72: =PCE!D73 -> 106.05375 | C72: =+'CPI-U-RS'!D77 -> 360.3 | D72: =+'CPI-U'!B74 -> 245.12 | E72: =+C$22/C72 -> 0.15570358 | F72: =+D$22/D72 -> 0.13625979 | G72: =+E72/F72 -> 1.1426965 | H72: =+C$33/C72 -> 0.28975853 | I72: =+D$33/D72 -> 0.26599217 | J72: =+H72/I72 -> 1.0893499
A73: =+A72+1 -> 2018 | B73: =PCE!D74 -> 108.31675 | C73: =+'CPI-U-RS'!D78 -> 369.1 | D73: =+'CPI-U'!B75 -> 251.107 | E73: =+C$22/C73 -> 0.15199133 | F73: =+D$22/D73 -> 0.13301103 | G73: =+E73/F73 -> 1.1426972 | H73: =+C$33/C73 -> 0.28285018 | I73: =+D$33/D73 -> 0.25965027 | J73: =+H73/I73 -> 1.0893506
A74: =+A73+1 -> 2019 | B74: =PCE!D75 -> 109.933 | C74: =+'CPI-U-RS'!D79 -> 375.8 | D74: =+'CPI-U'!B76 -> 255.657 | E74: =+C$22/C74 -> 0.14928153 | F74: =+D$22/D74 -> 0.13064379 | G74: =+E74/F74 -> 1.1426607 | H74: =+C$33/C74 -> 0.27780734 | I74: =+D$33/D74 -> 0.2550292 | J74: =+H74/I74 -> 1.0893158
A75: =+A74+1 -> 2020 | B75: =PCE!D76 -> 111.1445 | C75: =+'CPI-U-RS'!D80 -> 380.8 | D75: =+'CPI-U'!B77 -> 258.811 | E75: =+C$22/C75 -> 0.14732143 | F75: =+D$22/D75 -> 0.1290517 | G75: =+E75/F75 -> 1.141569 | H75: =+C$33/C75 -> 0.27415966 | I75: =+D$33/D75 -> 0.25192129 | J75: =+H75/I75 -> 1.0882751
A76: =+A75+1 -> 2021 | B76: =PCE!D77 -> 115.62075 | C76: =+'CPI-U-RS'!D81 -> 399.2 | D76: =+'CPI-U'!B78 -> 270.96975 | E76: =+C$22/C76 -> 0.14053106 | F76: =+D$22/D76 -> 0.12326099 | G76: =+E76/F76 -> 1.1401098 | H76: =+C$33/C76 -> 0.26152305 | I76: =+D$33/D76 -> 0.24061726 | J76: =+H76/I76 -> 1.086884
A77: =+A76+1 -> 2022 | B77: =PCE!D78 -> 122.861 | C77: =+'CPI-U-RS'!D82 -> 431.5 | D77: =+'CPI-U'!B79 -> 292.655 | E77: =+C$22/C77 -> 0.13001159 | F77: =+D$22/D77 -> 0.11412756 | G77: =+E77/F77 -> 1.1391779 | H77: =+C$33/C77 -> 0.2419467 | I77: =+D$33/D77 -> 0.22278792 | J77: =+H77/I77 -> 1.0859956

Sheet cpi-u-rs-adj
C3: cpi-u-rs | D3: cpi-u-rs-adj .8% | E3: base=1980 | G3: check
B4: 1947 | C4: ='CPI-U-RS'!D7 -> 37.5 | D4: =+C4 -> 37.5 | E4: =+ROUND(D4/$D$37,3) -> 0.416 | K4: =+ROUND(C4/$C$62,3) -> 0.131 | L4: =+ROUND(D4/$D$62,3) -> 0.224
B5: 1948 | C5: ='CPI-U-RS'!D8 -> 40.5 | D5: =+D4+D4*((C5-C4)/C4-0.011) -> 40.0875 | E5: =+ROUND(D5/$D$37,3) -> 0.445 | G5: =+(C5-C4)/C4 -> 0.08 | H5: =+(D5-D4)/D4 -> 0.069 | I5: =+H5-G5 -> -0.011 | K5: =+ROUND(C5/$C$62,3) -> 0.141 | L5: =+ROUND(D5/$D$62,3) -> 0.24
B6: 1949 | C6: ='CPI-U-RS'!D9 -> 40 | D6: =+D5+D5*((C6-C5)/C5-0.011) -> 39.15163 | E6: =+ROUND(D6/$D$37,3) -> 0.434 | G6: =+(C6-C5)/C5 -> -0.012345679 | H6: =+(D6-D5)/D5 -> -0.023345679 | I6: =+H6-G6 -> -0.011 | K6: =+ROUND(C6/$C$62,3) -> 0.14 | L6: =+ROUND(D6/$D$62,3) -> 0.234
B7: 1950 | C7: ='CPI-U-RS'!D10 -> 40.5 | D7: =+D6+D6*((C7-C6)/C6-0.011) -> 39.210358 | E7: =+ROUND(D7/$D$37,3) -> 0.435 | G7: =+(C7-C6)/C6 -> 0.0125 | H7: =+(D7-D6)/D6 -> 0.0015 | I7: =+H7-G7 -> -0.011 | K7: =+ROUND(C7/$C$62,3) -> 0.141 | L7: =+ROUND(D7/$D$62,3) -> 0.234
B8: 1951 | C8: ='CPI-U-RS'!D11 -> 43.7 | D8: =+D7+D7*((C8-C7)/C7-0.011) -> 41.877146 | E8: =+ROUND(D8/$D$37,3) -> 0.465 | G8: =+(C8-C7)/C7 -> 0.079012346 | H8: =+(D8-D7)/D7 -> 0.068012346 | I8: =+H8-G8 -> -0.011 | K8: =+ROUND(C8/$C$62,3) -> 0.153 | L8: =+ROUND(D8/$D$62,3) -> 0.25
B9: 1952 | C9: ='CPI-U-RS'!D12 -> 44.5 | D9: =+D8+D8*((C9-C8)/C8-0.011) -> 42.183127 | E9: =+ROUND(D9/$D$37,3) -> 0.468 | G9: =+(C9-C8)/C8 -> 0.018306636 | H9: =+(D9-D8)/D8 -> 0.0073066362 | I9: =+H9-G9 -> -0.011 | K9: =+ROUND(C9/$C$62,3) -> 0.155 | L9: =+ROUND(D9/$D$62,3) -> 0.252
B10: 1953 | C10: ='CPI-U-RS'!D13 -> 44.8 | D10: =+D9+D9*((C10-C9)/C9-0.011) -> 42.003493 | E10: =+ROUND(D10/$D$37,3) -> 0.466 | G10: =+(C10-C9)/C9 -> 0.006741573 | H10: =+(D10-D9)/D9 -> -0.004258427 | I10: =+H10-G10 -> -0.011 | K10: =+ROUND(C10/$C$62,3) -> 0.156 | L10: =+ROUND(D10/$D$62,3) -> 0.251
B11: 1954 | C11: ='CPI-U-RS'!D14 -> 45.2 | D11: =+D10+D10*((C11-C10)/C10-0.011) -> 41.916486 | E11: =+ROUND(D11/$D$37,3) -> 0.465 | G11: =+(C11-C10)/C10 -> 0.0089285714 | H11: =+(D11-D10)/D10 -> -0.0020714286 | I11: =+H11-G11 -> -0.011 | K11: =+ROUND(C11/$C$62,3) -> 0.158 | L11: =+ROUND(D11/$D$62,3) -> 0.251
B12: 1955 | C12: ='CPI-U-RS'!D15 -> 45 | D12: =+D11+D11*((C12-C11)/C11-0.011) -> 41.269933 | E12: =+ROUND(D12/$D$37,3) -> 0.458 | G12: =+(C12-C11)/C11 -> -0.0044247788 | H12: =+(D12-D11)/D11 -> -0.015424779 | I12: =+H12-G12 -> -0.011 | K12: =+ROUND(C12/$C$62,3) -> 0.157 | L12: =+ROUND(D12/$D$62,3) -> 0.247
B13: 1956 | C13: ='CPI-U-RS'!D16 -> 45.7 | D13: =+D12+D12*((C13-C12)/C12-0.011) -> 41.457941 | E13: =+ROUND(D13/$D$37,3) -> 0.46 | G13: =+(C13-C12)/C12 -> 0.015555556 | H13: =+(D13-D12)/D12 -> 0.0045555556 | I13: =+H13-G13 -> -0.011 | K13: =+ROUND(C13/$C$62,3) -> 0.16 | L13: =+ROUND(D13/$D$62,3) -> 0.248
B14: 1957 | C14: ='CPI-U-RS'!D17 -> 47.2 | D14: =+D13+D13*((C14-C13)/C13-0.011) -> 42.362668 | E14: =+ROUND(D14/$D$37,3) -> 0.47 | G14: =+(C14-C13)/C13 -> 0.032822757 | H14: =+(D14-D13)/D13 -> 0.021822757 | I14: =+H14-G14 -> -0.011 | K14: =+ROUND(C14/$C$62,3) -> 0.165 | L14: =+ROUND(D14/$D$62,3) -> 0.253
B15: 1958 | C15: ='CPI-U-RS'!D18 -> 48.5 | D15: =+D14+D14*((C15-C14)/C14-0.011) -> 43.063447 | E15: =+ROUND(D15/$D$37,3) -> 0.478 | G15: =+(C15-C14)/C14 -> 0.027542373 | H15: =+(D15-D14)/D14 -> 0.016542373 | I15: =+H15-G15 -> -0.011 | K15: =+ROUND(C15/$C$62,3) -> 0.169 | L15: =+ROUND(D15/$D$62,3) -> 0.257
B16: 1959 | C16: ='CPI-U-RS'!D19 -> 48.9 | D16: =+D15+D15*((C16-C15)/C15-0.011) -> 42.944911 | E16: =+ROUND(D16/$D$37,3) -> 0.476 | G16: =+(C16-C15)/C15 -> 0.0082474227 | H16: =+(D16-D15)/D15 -> -0.0027525773 | I16: =+H16-G16 -> -0.011 | K16: =+ROUND(C16/$C$62,3) -> 0.171 | L16: =+ROUND(D16/$D$62,3) -> 0.257
... B33: 1976 | C33: ='CPI-U-RS'!D36 -> 91.9 | D33: =+D32+D32*((C33-C32)/C32-0.011) -> 67.332273 | E33: =+ROUND(D33/$D$37,3) -> 0.747 | G33: =+(C33-C32)/C32 -> 0.057537399 | H33: =+(D33-D32)/D32 -> 0.046537399 | I33: =+H33-G33 -> -0.011 | K33: =+ROUND(C33/$C$62,3) -> 0.321 | L33: =+ROUND(D33/$D$62,3) -> 0.403
A34: BEFORE 77 ADJ USING 1.1 | B34: 1977 | C34: ='CPI-U-RS'!D37 -> 97.7 | D34: =+D33+D33*((C34-C33)/C33-0.011) -> 70.841098 | E34: =+ROUND(D34/$D$37,3) -> 0.786 | G34: =+(C34-C33)/C33 -> 0.063112078 | H34: =+(D34-D33)/D33 -> 0.052112078 | I34: =+H34-G34 -> -0.011 | K34: =+ROUND(C34/$C$62,3) -> 0.341 | L34: =+ROUND(D34/$D$62,3) -> 0.424
B35: 1978 | C35: ='CPI-U-RS'!D38 -> 104.4 | D35: =+D34+D34*((C35-C34)/C34-0.008) -> 75.132458 | E35: =+ROUND(D35/$D$37,3) -> 0.833 | G35: =+(C35-C34)/C34 -> 0.068577277 | H35: =+(D35-D34)/D34 -> 0.060577277 | I35: =+H35-G35 -> -0.008 | K35: =+ROUND(C35/$C$62,3) -> 0.365 | L35: =+ROUND(D35/$D$62,3) -> 0.449
B36: 1979 | C36: ='CPI-U-RS'!D39 -> 114.3 | D36: =+D35+D35*((C36-C35)/C35-0.008) -> 81.656028 | E36: =+ROUND(D36/$D$37,3) -> 0.906 | G36: =+(C36-C35)/C35 -> 0.094827586 | H36: =+(D36-D35)/D35 -> 0.086827586 | I36: =+H36-G36 -> -0.008 | K36: =+ROUND(C36/$C$62,3) -> 0.399 | L36: =+ROUND(D36/$D$62,3) -> 0.488
B37: 1980 | C37: ='CPI-U-RS'!D40 -> 127.1 | D37: =+D36+D36*((C37-C36)/C36-0.008) -> 90.147112 | E37: =+ROUND(D37/$D$37,3) -> 1 | G37: =+(C37-C36)/C36 -> 0.111986 | H37: =+(D37-D36)/D36 -> 0.103986 | I37: =+H37-G37 -> -0.008 | K37: =+ROUND(C37/$C$62,3) -> 0.444 | L37: =+ROUND(D37/$D$62,3) -> 0.539
B38: 1981 | C38: ='CPI-U-RS'!D41 -> 139.1 | D38: =+D37+D37*((C38-C37)/C37-0.008) -> 97.937071 | E38: =+ROUND(D38/$D$37,3) -> 1.086 | G38: =+(C38-C37)/C37 -> 0.094413847 | H38: =+(D38-D37)/D37 -> 0.086413847 | I38: =+H38-G38 -> -0.008 | K38: =+ROUND(C38/$C$62,3) -> 0.486 | L38: =+ROUND(D38/$D$62,3) -> 0.586
B39: 1982 | C39: ='CPI-U-RS'!D42 -> 147.5 | D39: =+D38+D38*((C39-C38)/C38-0.008) -> 103.06782 | E39: =+ROUND(D39/$D$37,3) -> 1.143 | G39: =+(C39-C38)/C38 -> 0.06038821 | H39: =+(D39-D38)/D38 -> 0.05238821 | I39: =+H39-G39 -> -0.008 | K39: =+ROUND(C39/$C$62,3) -> 0.515 | L39: =+ROUND(D39/$D$62,3) -> 0.616
B40: 1983 | C40: ='CPI-U-RS'!D43 -> 153.8 | D40: =+D39+D39*((C40-C39)/C39-0.008) -> 106.6455 | E40: =+ROUND(D40/$D$37,3) -> 1.183 | G40: =+(C40-C39)/C39 -> 0.042711864 | H40: =+(D40-D39)/D39 -> 0.034711864 | I40: =+H40-G40 -> -0.008 | K40: =+ROUND(C40/$C$62,3) -> 0.537 | L40: =+ROUND(D40/$D$62,3) -> 0.638
B41: 1984 | C41: ='CPI-U-RS'!D44 -> 160.2 | D41: =+D40+D40*((C41-C40)/C40-0.008) -> 110.23012 | E41: =+ROUND(D41/$D$37,3) -> 1.223 | G41: =+(C41-C40)/C40 -> 0.041612484 | H41: =+(D41-D40)/D40 -> 0.033612484 | I41: =+H41-G41 -> -0.008 | K41: =+ROUND(C41/$C$62,3) -> 0.559 | L41: =+ROUND(D41/$D$62,3) -> 0.659
B42: 1985 | C42: ='CPI-U-RS'!D45 -> 165.6 | D42: =+D41+D41*((C42-C41)/C41-0.008) -> 113.0639 | E42: =+ROUND(D42/$D$37,3) -> 1.254 | G42: =+(C42-C41)/C41 -> 0.033707865 | H42: =+(D42-D41)/D41 -> 0.025707865 | I42: =+H42-G42 -> -0.008 | K42: =+ROUND(C42/$C$62,3) -> 0.578 | L42: =+ROUND(D42/$D$62,3) -> 0.676
B43: 1986 | C43: ='CPI-U-RS'!D46 -> 168.4 | D43: =+D42+D42*((C43-C42)/C42-0.008) -> 114.07109 | E43: =+ROUND(D43/$D$37,3) -> 1.265 | G43: =+(C43-C42)/C42 -> 0.016908213 | H43: =+(D43-D42)/D42 -> 0.0089082126 | I43: =+H43-G43 -> -0.008 | K43: =+ROUND(C43/$C$62,3) -> 0.588 | L43: =+ROUND(D43/$D$62,3) -> 0.682
B44: 1987 | C44: ='CPI-U-RS'!D47 -> 174.1 | D44: =+D43+D43*((C44-C43)/C43-0.008) -> 117.0196 | E44: =+ROUND(D44/$D$37,3) -> 1.298 | G44: =+(C44-C43)/C43 -> 0.033847981 | H44: =+(D44-D43)/D43 -> 0.025847981 | I44: =+H44-G44 -> -0.008 | K44: =+ROUND(C44/$C$62,3) -> 0.608 | L44: =+ROUND(D44/$D$62,3) -> 0.7
B45: 1988 | C45: ='CPI-U-RS'!D48 -> 180.5 | D45: =+D44+D44*((C45-C44)/C44-0.008) -> 120.38514 | E45: =+ROUND(D45/$D$37,3) -> 1.335 | G45: =+(C45-C44)/C44 -> 0.036760482 | H45: =+(D45-D44)/D44 -> 0.028760482 | I45: =+H45-G45 -> -0.008 | K45: =+ROUND(C45/$C$62,3) -> 0.63 | L45: =+ROUND(D45/$D$62,3) -> 0.72
B46: 1989 | C46: ='CPI-U-RS'!D49 -> 188.3 | D46: =+D45+D45*((C46-C45)/C45-0.008) -> 124.6243 | E46: =+ROUND(D46/$D$37,3) -> 1.382 | G46: =+(C46-C45)/C45 -> 0.043213296 | H46: =+(D46-D45)/D45 -> 0.035213296 | I46: =+H46-G46 -> -0.008 | K46: =+ROUND(C46/$C$62,3) -> 0.657 | L46: =+ROUND(D46/$D$62,3) -> 0.745
... B62: 2005 | C62: ='CPI-U-RS'!D65 -> 286.4 | D62: =+D61+D61*((C62-C61)/C61-0.008) -> 167.24758 | E62: =+ROUND(D62/$D$37,3) -> 1.855 | G62: =+(C62-C61)/C61 -> 0.033935018 | H62: =+(D62-D61)/D61 -> 0.025935018 | I62: =+H62-G62 -> -0.008 | K62: =+ROUND(C62/$C$62,3) -> 1 | L62: =+ROUND(D62/$D$62,3) -> 1
B63: =+B62+1 -> 2006 | C63: ='CPI-U-RS'!D66 -> 295.7 | D63: =+D62+D62*((C63-C62)/C62-0.008) -> 171.34048 | E63: =+ROUND(D63/$D$37,3) -> 1.901 | G63: =+(C63-C62)/C62 -> 0.032472067 | H63: =+(D63-D62)/D62 -> 0.024472067 | I63: =+H63-G63 -> -0.008 | K63: =+ROUND(C63/$C$62,3) -> 1.032 | L63: =+ROUND(D63/$D$62,3) -> 1.024
B64: =+B63+1 -> 2007 | C64: ='CPI-U-RS'!D67 -> 304.1 | D64: =+D63+D63*((C64-C63)/C63-0.008) -> 174.83705 | E64: =+ROUND(D64/$D$37,3) -> 1.939 | G64: =+(C64-C63)/C63 -> 0.028407169 | H64: =+(D64-D63)/D63 -> 0.020407169 | I64: =+H64-G64 -> -0.008 | K64: =+ROUND(C64/$C$62,3) -> 1.062 | L64: =+ROUND(D64/$D$62,3) -> 1.045
B65: =+B64+1 -> 2008 | C65: ='CPI-U-RS'!D68 -> 315.8 | D65: =+D64+D64*((C65-C64)/C64-0.008) -> 180.16507 | E65: =+ROUND(D65/$D$37,3) -> 1.999 | G65: =+(C65-C64)/C64 -> 0.038474186 | H65: =+(D65-D64)/D64 -> 0.030474186 | I65: =+H65-G65 -> -0.008 | K65: =+ROUND(C65/$C$62,3) -> 1.103 | L65: =+ROUND(D65/$D$62,3) -> 1.077
B66: =+B65+1 -> 2009 | C66: ='CPI-U-RS'!D69 -> 314.7 | D66: =+D65+D65*((C66-C65)/C65-0.008) -> 178.09619 | E66: =+ROUND(D66/$D$37,3) -> 1.976 | G66: =+(C66-C65)/C65 -> -0.0034832172 | H66: =+(D66-D65)/D65 -> -0.011483217 | I66: =+H66-G66 -> -0.008 | K66: =+ROUND(C66/$C$62,3) -> 1.099 | L66: =+ROUND(D66/$D$62,3) -> 1.065
B67: =+B66+1 -> 2010 | C67: ='CPI-U-RS'!D70 -> 319.8 | D67: =+D66+D66*((C67-C66)/C66-0.008) -> 179.55764 | E67: =+ROUND(D67/$D$37,3) -> 1.992 | G67: =+(C67-C66)/C66 -> 0.01620591 | H67: =+(D67-D66)/D66 -> 0.0082059104 | I67: =+H67-G67 -> -0.008 | K67: =+ROUND(C67/$C$62,3) -> 1.117 | L67: =+ROUND(D67/$D$62,3) -> 1.074
B68: =+B67+1 -> 2011 | C68: ='CPI-U-RS'!D71 -> 330 | D68: =+D67+D67*((C68-C67)/C67-0.008) -> 183.84815 | E68: =+ROUND(D68/$D$37,3) -> 2.039 | G68: =+(C68-C67)/C67 -> 0.031894934 | H68: =+(D68-D67)/D67 -> 0.023894934 | I68: =+H68-G68 -> -0.008 | K68: =+ROUND(C68/$C$62,3) -> 1.152 | L68: =+ROUND(D68/$D$62,3) -> 1.099
B69: =+B68+1 -> 2012 | C69: ='CPI-U-RS'!D72 -> 336.9 | D69: =+D68+D68*((C69-C68)/C68-0.008) -> 186.22147 | E69: =+ROUND(D69/$D$37,3) -> 2.066 | G69: =+(C69-C68)/C68 -> 0.020909091 | H69: =+(D69-D68)/D68 -> 0.012909091 | I69: =+H69-G69 -> -0.008 | K69: =+ROUND(C69/$C$62,3) -> 1.176 | L69: =+ROUND(D69/$D$62,3) -> 1.113
B70: =+B69+1 -> 2013 | C70: ='CPI-U-RS'!D73 -> 342 | D70: =+D69+D69*((C70-C69)/C69-0.008) -> 187.55072 | E70: =+ROUND(D70/$D$37,3) -> 2.08 | G70: =+(C70-C69)/C69 -> 0.015138023 | H70: =+(D70-D69)/D69 -> 0.0071380232 | I70: =+H70-G70 -> -0.008 | K70: =+ROUND(C70/$C$62,3) -> 1.194 | L70: =+ROUND(D70/$D$62,3) -> 1.121
B71: =+B70+1 -> 2014 | C71: ='CPI-U-RS'!D74 -> 347.7 | D71: =+D70+D70*((C71-C70)/C70-0.008) -> 189.17616 | E71: =+ROUND(D71/$D$37,3) -> 2.099 | G71: =+(C71-C70)/C70 -> 0.016666667 | H71: =+(D71-D70)/D70 -> 0.0086666667 | I71: =+H71-G71 -> -0.008 | K71: =+ROUND(C71/$C$62,3) -> 1.214 | L71: =+ROUND(D71/$D$62,3) -> 1.131
B72: =+B71+1 -> 2015 | C72: ='CPI-U-RS'!D75 -> 348.3 | D72: =+D71+D71*((C72-C71)/C71-0.008) -> 187.9892 | E72: =+ROUND(D72/$D$37,3) -> 2.085 | G72: =+(C72-C71)/C71 -> 0.0017256255 | H72: =+(D72-D71)/D71 -> -0.0062743745 | I72: =+H72-G72 -> -0.008 | K72: =+ROUND(C72/$C$62,3) -> 1.216 | L72: =+ROUND(D72/$D$62,3) -> 1.124
B73: =+B72+1 -> 2016 | C73: ='CPI-U-RS'!D76 -> 352.8 | D73: =+D72+D72*((C73-C72)/C72-0.008) -> 188.91408 | E73: =+ROUND(D73/$D$37,3) -> 2.096 | G73: =+(C73-C72)/C72 -> 0.012919897 | H73: =+(D73-D72)/D72 -> 0.0049198966 | I73: =+H73-G73 -> -0.008 | K73: =+ROUND(C73/$C$62,3) -> 1.232 | L73: =+ROUND(D73/$D$62,3) -> 1.13
B74: =+B73+1 -> 2017 | C74: ='CPI-U-RS'!D77 -> 360.3 | D74: =+D73+D73*((C74-C73)/C73-0.008) -> 191.4188 | E74: =+ROUND(D74/$D$37,3) -> 2.123 | G74: =+(C74-C73)/C73 -> 0.021258503 | H74: =+(D74-D73)/D73 -> 0.013258503 | I74: =+H74-G74 -> -0.008
B75: =+B74+1 -> 2018 | C75: ='CPI-U-RS'!D78 -> 369.1 | D75: =+D74+D74*((C75-C74)/C74-0.008) -> 194.56268 | E75: =+ROUND(D75/$D$37,3) -> 2.158 | G75: =+(C75-C74)/C74 -> 0.024424091 | H75: =+(D75-D74)/D74 -> 0.016424091 | I75: =+H75-G75 -> -0.008
B76: =+B75+1 -> 2019 | C76: ='CPI-U-RS'!D79 -> 375.8 | D76: =+D75+D75*((C76-C75)/C75-0.008) -> 196.53793 | E76: =+ROUND(D76/$D$37,3) -> 2.18 | G76: =+(C76-C75)/C75 -> 0.018152262 | H76: =+(D76-D75)/D75 -> 0.010152262 | I76: =+H76-G76 -> -0.008
B77: =+B76+1 -> 2020 | C77: ='CPI-U-RS'!D80 -> 380.8 | D77: =+D76+D76*((C77-C76)/C76-0.008) -> 197.58056 | E77: =+ROUND(D77/$D$37,3) -> 2.192 | G77: =+(C77-C76)/C76 -> 0.013304949 | H77: =+(D77-D76)/D76 -> 0.0053049494 | I77: =+H77-G77 -> -0.008
B78: =+B77+1 -> 2021 | C78: ='CPI-U-RS'!D81 -> 399.2 | D78: =+D77+D77*((C78-C77)/C77-0.008) -> 205.54687 | E78: =+ROUND(D78/$D$37,3) -> 2.28 | G78: =+(C78-C77)/C77 -> 0.048319328 | H78: =+(D78-D77)/D77 -> 0.040319328 | I78: =+H78-G78 -> -0.008
B79: =+B78+1 -> 2022 | C79: ='CPI-U-RS'!D82 -> 431.5 | D79: =+D78+D78*((C79-C78)/C78-0.008) -> 220.53367 | E79: =+ROUND(D79/$D$37,3) -> 2.446 | G79: =+(C79-C78)/C78 -> 0.080911824 | H79: =+(D79-D78)/D78 -> 0.072911824 | I79: =+H79-G79 -> -0.008

Sheet cpi-u-rs-adj-03
C3: cpi-u-rs | D3: cpi-u-rs-adj .5% | E3: base=1980 | G3: check
B4: 1947 | C4: ='CPI-U-RS'!D7 -> 37.5 | D4: =+C4 -> 37.5 | E4: =+ROUND(D4/$D$37,3) -> 0.413 | K4: =+ROUND(C4/$C$62,3) -> 0.131 | L4: =+ROUND(D4/$D$62,3) -> 0.207
B5: 1948 | C5: ='CPI-U-RS'!D8 -> 40.5 | D5: =+D4+D4*((C5-C4)/C4-0.011) -> 40.0875 | E5: =+ROUND(D5/$D$37,3) -> 0.441 | G5: =+(C5-C4)/C4 -> 0.08 | H5: =+(D5-D4)/D4 -> 0.069 | I5: =+H5-G5 -> -0.011 | K5: =+ROUND(C5/$C$62,3) -> 0.141 | L5: =+ROUND(D5/$D$62,3) -> 0.221
B6: 1949 | C6: ='CPI-U-RS'!D9 -> 40 | D6: =+D5+D5*((C6-C5)/C5-0.011) -> 39.15163 | E6: =+ROUND(D6/$D$37,3) -> 0.431 | G6: =+(C6-C5)/C5 -> -0.012345679 | H6: =+(D6-D5)/D5 -> -0.023345679 | I6: =+H6-G6 -> -0.011 | K6: =+ROUND(C6/$C$62,3) -> 0.14 | L6: =+ROUND(D6/$D$62,3) -> 0.216
B7: 1950 | C7: ='CPI-U-RS'!D10 -> 40.5 | D7: =+D6+D6*((C7-C6)/C6-0.011) -> 39.210358 | E7: =+ROUND(D7/$D$37,3) -> 0.431 | G7: =+(C7-C6)/C6 -> 0.0125 | H7: =+(D7-D6)/D6 -> 0.0015 | I7: =+H7-G7 -> -0.011 | K7: =+ROUND(C7/$C$62,3) -> 0.141 | L7: =+ROUND(D7/$D$62,3) -> 0.216
B8: 1951 | C8: ='CPI-U-RS'!D11 -> 43.7 | D8: =+D7+D7*((C8-C7)/C7-0.011) -> 41.877146 | E8: =+ROUND(D8/$D$37,3) -> 0.461 | G8: =+(C8-C7)/C7 -> 0.079012346 | H8: =+(D8-D7)/D7 -> 0.068012346 | I8: =+H8-G8 -> -0.011 | K8: =+ROUND(C8/$C$62,3) -> 0.153 | L8: =+ROUND(D8/$D$62,3) -> 0.231
B9: 1952 | C9: ='CPI-U-RS'!D12 -> 44.5 | D9: =+D8+D8*((C9-C8)/C8-0.011) -> 42.183127 | E9: =+ROUND(D9/$D$37,3) -> 0.464 | G9: =+(C9-C8)/C8 -> 0.018306636 | H9: =+(D9-D8)/D8 -> 0.0073066362 | I9: =+H9-G9 -> -0.011 | K9: =+ROUND(C9/$C$62,3) -> 0.155 | L9: =+ROUND(D9/$D$62,3) -> 0.233
B10: 1953 | C10: ='CPI-U-RS'!D13 -> 44.8 | D10: =+D9+D9*((C10-C9)/C9-0.011) -> 42.003493 | E10: =+ROUND(D10/$D$37,3) -> 0.462 | G10: =+(C10-C9)/C9 -> 0.006741573 | H10: =+(D10-D9)/D9 -> -0.004258427 | I10: =+H10-G10 -> -0.011 | K10: =+ROUND(C10/$C$62,3) -> 0.156 | L10: =+ROUND(D10/$D$62,3) -> 0.232
B11: 1954 | C11: ='CPI-U-RS'!D14 -> 45.2 | D11: =+D10+D10*((C11-C10)/C10-0.011) -> 41.916486 | E11: =+ROUND(D11/$D$37,3) -> 0.461 | G11: =+(C11-C10)/C10 -> 0.0089285714 | H11: =+(D11-D10)/D10 -> -0.0020714286 | I11: =+H11-G11 -> -0.011 | K11: =+ROUND(C11/$C$62,3) -> 0.158 | L11: =+ROUND(D11/$D$62,3) -> 0.231
B12: 1955 | C12: ='CPI-U-RS'!D15 -> 45 | D12: =+D11+D11*((C12-C11)/C11-0.011) -> 41.269933 | E12: =+ROUND(D12/$D$37,3) -> 0.454 | G12: =+(C12-C11)/C11 -> -0.0044247788 | H12: =+(D12-D11)/D11 -> -0.015424779 | I12: =+H12-G12 -> -0.011 | K12: =+ROUND(C12/$C$62,3) -> 0.157 | L12: =+ROUND(D12/$D$62,3) -> 0.227
B13: 1956 | C13: ='CPI-U-RS'!D16 -> 45.7 | D13: =+D12+D12*((C13-C12)/C12-0.011) -> 41.457941 | E13: =+ROUND(D13/$D$37,3) -> 0.456 | G13: =+(C13-C12)/C12 -> 0.015555556 | H13: =+(D13-D12)/D12 -> 0.0045555556 | I13: =+H13-G13 -> -0.011 | K13: =+ROUND(C13/$C$62,3) -> 0.16 | L13: =+ROUND(D13/$D$62,3) -> 0.229
B14: 1957 | C14: ='CPI-U-RS'!D17 -> 47.2 | D14: =+D13+D13*((C14-C13)/C13-0.011) -> 42.362668 | E14: =+ROUND(D14/$D$37,3) -> 0.466 | G14: =+(C14-C13)/C13 -> 0.032822757 | H14: =+(D14-D13)/D13 -> 0.021822757 | I14: =+H14-G14 -> -0.011 | K14: =+ROUND(C14/$C$62,3) -> 0.165 | L14: =+ROUND(D14/$D$62,3) -> 0.233
B15: 1958 | C15: ='CPI-U-RS'!D18 -> 48.5 | D15: =+D14+D14*((C15-C14)/C14-0.011) -> 43.063447 | E15: =+ROUND(D15/$D$37,3) -> 0.474 | G15: =+(C15-C14)/C14 -> 0.027542373 | H15: =+(D15-D14)/D14 -> 0.016542373 | I15: =+H15-G15 -> -0.011 | K15: =+ROUND(C15/$C$62,3) -> 0.169 | L15: =+ROUND(D15/$D$62,3) -> 0.237
B16: 1959 | C16: ='CPI-U-RS'!D19 -> 48.9 | D16: =+D15+D15*((C16-C15)/C15-0.011) -> 42.944911 | E16: =+ROUND(D16/$D$37,3) -> 0.472 | G16: =+(C16-C15)/C15 -> 0.0082474227 | H16: =+(D16-D15)/D15 -> -0.0027525773 | I16: =+H16-G16 -> -0.011 | K16: =+ROUND(C16/$C$62,3) -> 0.171 | L16: =+ROUND(D16/$D$62,3) -> 0.237
... B33: 1976 | C33: ='CPI-U-RS'!D36 -> 91.9 | D33: =+D32+D32*((C33-C32)/C32-0.011) -> 67.332273 | E33: =+ROUND(D33/$D$37,3) -> 0.741 | G33: =+(C33-C32)/C32 -> 0.057537399 | H33: =+(D33-D32)/D32 -> 0.046537399 | I33: =+H33-G33 -> -0.011 | K33: =+ROUND(C33/$C$62,3) -> 0.321 | L33: =+ROUND(D33/$D$62,3) -> 0.371
A34: BEFORE 77 ADJ USING 1.1 | B34: 1977 | C34: ='CPI-U-RS'!D37 -> 97.7 | D34: =+D33+D33*((C34-C33)/C33-0.011) -> 70.841098 | E34: =+ROUND(D34/$D$37,3) -> 0.779 | G34: =+(C34-C33)/C33 -> 0.063112078 | H34: =+(D34-D33)/D33 -> 0.052112078 | I34: =+H34-G34 -> -0.011 | K34: =+ROUND(C34/$C$62,3) -> 0.341 | L34: =+ROUND(D34/$D$62,3) -> 0.39
B35: 1978 | C35: ='CPI-U-RS'!D38 -> 104.4 | D35: =+D34+D34*((C35-C34)/C34-0.005) -> 75.344982 | E35: =+ROUND(D35/$D$37,3) -> 0.829 | G35: =+(C35-C34)/C34 -> 0.068577277 | H35: =+(D35-D34)/D34 -> 0.063577277 | I35: =+H35-G35 -> -0.005 | K35: =+ROUND(C35/$C$62,3) -> 0.365 | L35: =+ROUND(D35/$D$62,3) -> 0.415
B36: 1979 | C36: ='CPI-U-RS'!D39 -> 114.3 | D36: =+D35+D35*((C36-C35)/C35-0.005) -> 82.11304 | E36: =+ROUND(D36/$D$37,3) -> 0.903 | G36: =+(C36-C35)/C35 -> 0.094827586 | H36: =+(D36-D35)/D35 -> 0.089827586 | I36: =+H36-G36 -> -0.005 | K36: =+ROUND(C36/$C$62,3) -> 0.399 | L36: =+ROUND(D36/$D$62,3) -> 0.453
B37: 1980 | C37: ='CPI-U-RS'!D40 -> 127.1 | D37: =+D36+D36*((C37-C36)/C36-0.005) -> 90.897985 | E37: =+ROUND(D37/$D$37,3) -> 1 | G37: =+(C37-C36)/C36 -> 0.111986 | H37: =+(D37-D36)/D36 -> 0.106986 | I37: =+H37-G37 -> -0.005 | K37: =+ROUND(C37/$C$62,3) -> 0.444 | L37: =+ROUND(D37/$D$62,3) -> 0.501
B38: 1981 | C38: ='CPI-U-RS'!D41 -> 139.1 | D38: =+D37+D37*((C38-C37)/C37-0.005) -> 99.025524 | E38: =+ROUND(D38/$D$37,3) -> 1.089 | G38: =+(C38-C37)/C37 -> 0.094413847 | H38: =+(D38-D37)/D37 -> 0.089413847 | I38: =+H38-G38 -> -0.005 | K38: =+ROUND(C38/$C$62,3) -> 0.486 | L38: =+ROUND(D38/$D$62,3) -> 0.546
B39: 1982 | C39: ='CPI-U-RS'!D42 -> 147.5 | D39: =+D38+D38*((C39-C38)/C38-0.005) -> 104.51037 | E39: =+ROUND(D39/$D$37,3) -> 1.15 | G39: =+(C39-C38)/C38 -> 0.06038821 | H39: =+(D39-D38)/D38 -> 0.05538821 | I39: =+H39-G39 -> -0.005 | K39: =+ROUND(C39/$C$62,3) -> 0.515 | L39: =+ROUND(D39/$D$62,3) -> 0.576
B40: 1983 | C40: ='CPI-U-RS'!D43 -> 153.8 | D40: =+D39+D39*((C40-C39)/C39-0.005) -> 108.45165 | E40: =+ROUND(D40/$D$37,3) -> 1.193 | G40: =+(C40-C39)/C39 -> 0.042711864 | H40: =+(D40-D39)/D39 -> 0.037711864 | I40: =+H40-G40 -> -0.005 | K40: =+ROUND(C40/$C$62,3) -> 0.537 | L40: =+ROUND(D40/$D$62,3) -> 0.598
B41: 1984 | C41: ='CPI-U-RS'!D44 -> 160.2 | D41: =+D40+D40*((C41-C40)/C40-0.005) -> 112.42234 | E41: =+ROUND(D41/$D$37,3) -> 1.237 | G41: =+(C41-C40)/C40 -> 0.041612484 | H41: =+(D41-D40)/D40 -> 0.036612484 | I41: =+H41-G41 -> -0.005 | K41: =+ROUND(C41/$C$62,3) -> 0.559 | L41: =+ROUND(D41/$D$62,3) -> 0.62
B42: 1985 | C42: ='CPI-U-RS'!D45 -> 165.6 | D42: =+D41+D41*((C42-C41)/C41-0.005) -> 115.64974 | E42: =+ROUND(D42/$D$37,3) -> 1.272 | G42: =+(C42-C41)/C41 -> 0.033707865 | H42: =+(D42-D41)/D41 -> 0.028707865 | I42: =+H42-G42 -> -0.005 | K42: =+ROUND(C42/$C$62,3) -> 0.578 | L42: =+ROUND(D42/$D$62,3) -> 0.637
B43: 1986 | C43: ='CPI-U-RS'!D46 -> 168.4 | D43: =+D42+D42*((C43-C42)/C42-0.005) -> 117.02692 | E43: =+ROUND(D43/$D$37,3) -> 1.287 | G43: =+(C43-C42)/C42 -> 0.016908213 | H43: =+(D43-D42)/D42 -> 0.011908213 | I43: =+H43-G43 -> -0.005 | K43: =+ROUND(C43/$C$62,3) -> 0.588 | L43: =+ROUND(D43/$D$62,3) -> 0.645
B44: 1987 | C44: ='CPI-U-RS'!D47 -> 174.1 | D44: =+D43+D43*((C44-C43)/C43-0.005) -> 120.40291 | E44: =+ROUND(D44/$D$37,3) -> 1.325 | G44: =+(C44-C43)/C43 -> 0.033847981 | H44: =+(D44-D43)/D43 -> 0.028847981 | I44: =+H44-G44 -> -0.005 | K44: =+ROUND(C44/$C$62,3) -> 0.608 | L44: =+ROUND(D44/$D$62,3) -> 0.664
B45: 1988 | C45: ='CPI-U-RS'!D48 -> 180.5 | D45: =+D44+D44*((C45-C44)/C44-0.005) -> 124.22697 | E45: =+ROUND(D45/$D$37,3) -> 1.367 | G45: =+(C45-C44)/C44 -> 0.036760482 | H45: =+(D45-D44)/D44 -> 0.031760482 | I45: =+H45-G45 -> -0.005 | K45: =+ROUND(C45/$C$62,3) -> 0.63 | L45: =+ROUND(D45/$D$62,3) -> 0.685
B46: 1989 | C46: ='CPI-U-RS'!D49 -> 188.3 | D46: =+D45+D45*((C46-C45)/C45-0.005) -> 128.97409 | E46: =+ROUND(D46/$D$37,3) -> 1.419 | G46: =+(C46-C45)/C45 -> 0.043213296 | H46: =+(D46-D45)/D45 -> 0.038213296 | I46: =+H46-G46 -> -0.005 | K46: =+ROUND(C46/$C$62,3) -> 0.657 | L46: =+ROUND(D46/$D$62,3) -> 0.711
... B62: 2005 | C62: ='CPI-U-RS'!D65 -> 286.4 | D62: =+D61+D61*((C62-C61)/C61-0.005) -> 181.42476 | E62: =+ROUND(D62/$D$37,3) -> 1.996 | G62: =+(C62-C61)/C61 -> 0.033935018 | H62: =+(D62-D61)/D61 -> 0.028935018 | I62: =+H62-G62 -> -0.005 | K62: =+ROUND(C62/$C$62,3) -> 1 | L62: =+ROUND(D62/$D$62,3) -> 1
B63: =+B62+1 -> 2006 | C63: ='CPI-U-RS'!D66 -> 295.7 | D63: =+D62+D62*((C63-C62)/C62-0.005) -> 186.40888 | E63: =+ROUND(D63/$D$37,3) -> 2.051 | G63: =+(C63-C62)/C62 -> 0.032472067 | H63: =+(D63-D62)/D62 -> 0.027472067 | I63: =+H63-G63 -> -0.005 | K63: =+ROUND(C63/$C$62,3) -> 1.032 | L63: =+ROUND(D63/$D$62,3) -> 1.027
B64: =+B63+1 -> 2007 | C64: ='CPI-U-RS'!D67 -> 304.1 | D64: =+D63+D63*((C64-C63)/C63-0.005) -> 190.77218 | E64: =+ROUND(D64/$D$37,3) -> 2.099 | G64: =+(C64-C63)/C63 -> 0.028407169 | H64: =+(D64-D63)/D63 -> 0.023407169 | I64: =+H64-G64 -> -0.005 | K64: =+ROUND(C64/$C$62,3) -> 1.062 | L64: =+ROUND(D64/$D$62,3) -> 1.052
B65: =+B64+1 -> 2008 | C65: ='CPI-U-RS'!D68 -> 315.8 | D65: =+D64+D64*((C65-C64)/C64-0.005) -> 197.15812 | E65: =+ROUND(D65/$D$37,3) -> 2.169 | G65: =+(C65-C64)/C64 -> 0.038474186 | H65: =+(D65-D64)/D64 -> 0.033474186 | I65: =+H65-G65 -> -0.005 | K65: =+ROUND(C65/$C$62,3) -> 1.103 | L65: =+ROUND(D65/$D$62,3) -> 1.087
B66: =+B65+1 -> 2009 | C66: ='CPI-U-RS'!D69 -> 314.7 | D66: =+D65+D65*((C66-C65)/C65-0.005) -> 195.48559 | E66: =+ROUND(D66/$D$37,3) -> 2.151 | G66: =+(C66-C65)/C65 -> -0.0034832172 | H66: =+(D66-D65)/D65 -> -0.0084832172 | I66: =+H66-G66 -> -0.005 | K66: =+ROUND(C66/$C$62,3) -> 1.099 | L66: =+ROUND(D66/$D$62,3) -> 1.078
B67: =+B66+1 -> 2010 | C67: ='CPI-U-RS'!D70 -> 319.8 | D67: =+D66+D66*((C67-C66)/C66-0.005) -> 197.67618 | E67: =+ROUND(D67/$D$37,3) -> 2.175 | G67: =+(C67-C66)/C66 -> 0.01620591 | H67: =+(D67-D66)/D66 -> 0.01120591 | I67: =+H67-G67 -> -0.005 | K67: =+ROUND(C67/$C$62,3) -> 1.117 | L67: =+ROUND(D67/$D$62,3) -> 1.09
B68: =+B67+1 -> 2011 | C68: ='CPI-U-RS'!D71 -> 330 | D68: =+D67+D67*((C68-C67)/C67-0.005) -> 202.99267 | E68: =+ROUND(D68/$D$37,3) -> 2.233 | G68: =+(C68-C67)/C67 -> 0.031894934 | H68: =+(D68-D67)/D67 -> 0.026894934 | I68: =+H68-G68 -> -0.005 | K68: =+ROUND(C68/$C$62,3) -> 1.152 | L68: =+ROUND(D68/$D$62,3) -> 1.119
B69: =+B68+1 -> 2012 | C69: ='CPI-U-RS'!D72 -> 336.9 | D69: =+D68+D68*((C69-C68)/C68-0.005) -> 206.2221 | E69: =+ROUND(D69/$D$37,3) -> 2.269 | G69: =+(C69-C68)/C68 -> 0.020909091 | H69: =+(D69-D68)/D68 -> 0.015909091 | I69: =+H69-G69 -> -0.005 | K69: =+ROUND(C69/$C$62,3) -> 1.176 | L69: =+ROUND(D69/$D$62,3) -> 1.137
B70: =+B69+1 -> 2013 | C70: ='CPI-U-RS'!D73 -> 342 | D70: =+D69+D69*((C70-C69)/C69-0.005) -> 208.31278 | E70: =+ROUND(D70/$D$37,3) -> 2.292 | G70: =+(C70-C69)/C69 -> 0.015138023 | H70: =+(D70-D69)/D69 -> 0.010138023 | I70: =+H70-G70 -> -0.005 | K70: =+ROUND(C70/$C$62,3) -> 1.194 | L70: =+ROUND(D70/$D$62,3) -> 1.148
B71: =+B70+1 -> 2014 | C71: ='CPI-U-RS'!D74 -> 347.7 | D71: =+D70+D70*((C71-C70)/C70-0.005) -> 210.7431 | E71: =+ROUND(D71/$D$37,3) -> 2.318 | G71: =+(C71-C70)/C70 -> 0.016666667 | H71: =+(D71-D70)/D70 -> 0.011666667 | I71: =+H71-G71 -> -0.005 | K71: =+ROUND(C71/$C$62,3) -> 1.214 | L71: =+ROUND(D71/$D$62,3) -> 1.162
B72: =+B71+1 -> 2015 | C72: ='CPI-U-RS'!D75 -> 348.3 | D72: =+D71+D71*((C72-C71)/C71-0.005) -> 210.05305 | E72: =+ROUND(D72/$D$37,3) -> 2.311 | G72: =+(C72-C71)/C71 -> 0.0017256255 | H72: =+(D72-D71)/D71 -> -0.0032743745 | I72: =+H72-G72 -> -0.005 | K72: =+ROUND(C72/$C$62,3) -> 1.216 | L72: =+ROUND(D72/$D$62,3) -> 1.158
B73: =+B72+1 -> 2016 | C73: ='CPI-U-RS'!D76 -> 352.8 | D73: =+D72+D72*((C73-C72)/C72-0.005) -> 211.71665 | E73: =+ROUND(D73/$D$37,3) -> 2.329 | G73: =+(C73-C72)/C72 -> 0.012919897 | H73: =+(D73-D72)/D72 -> 0.0079198966 | I73: =+H73-G73 -> -0.005 | K73: =+ROUND(C73/$C$62,3) -> 1.232 | L73: =+ROUND(D73/$D$62,3) -> 1.167
B74: =+B73+1 -> 2017 | C74: ='CPI-U-RS'!D77 -> 360.3 | D74: =+D73+D73*((C74-C73)/C73-0.005) -> 215.15884 | E74: =+ROUND(D74/$D$37,3) -> 2.367
B75: =+B74+1 -> 2018 | C75: ='CPI-U-RS'!D78 -> 369.1 | D75: =+D74+D74*((C75-C74)/C74-0.005) -> 219.33811 | E75: =+ROUND(D75/$D$37,3) -> 2.413
B76: =+B75+1 -> 2019 | C76: ='CPI-U-RS'!D79 -> 375.8 | D76: =+D75+D75*((C76-C75)/C75-0.005) -> 222.2229 | E76: =+ROUND(D76/$D$37,3) -> 2.445
B77: =+B76+1 -> 2020 | C77: ='CPI-U-RS'!D80 -> 380.8 | D77: =+D76+D76*((C77-C76)/C76-0.005) -> 224.06845 | E77: =+ROUND(D77/$D$37,3) -> 2.465
B78: =+B77+1 -> 2021 | C78: ='CPI-U-RS'!D81 -> 399.2 | D78: =+D77+D77*((C78-C77)/C77-0.005) -> 233.77494 | E78: =+ROUND(D78/$D$37,3) -> 2.572

Sheet dat_file 1980
B1: Year | C1: pce | D1: cpi-u-rs | E1: cpiu | F1: cpiu-rs67 | G1: cpiu67 | H1: cpi-u-rs adj | I1: N_cpi-u-rs adj | J1: cpi-u-rs adj03
B2: =+Sheet3!A2 -> 1947 | C2: =+ROUND(Sheet3!B2/Sheet3!B$35,4) -> 0.3033 | D2: =+ROUND(Sheet3!C2/Sheet3!C$35,4) -> 0.295 | E2: =+ROUND(Sheet3!D2/Sheet3!D$35,4) -> 0.2706 | F2: =+ROUND(Sheet3!E2,4) -> 1.496 | G2: =+ROUND(Sheet3!F2,4) -> 1.4978 | H2: =+ROUND('cpi-u-rs-adj'!D4/'cpi-u-rs-adj'!D$37,4) -> 0.416 | I2: =1/H2 -> 2.4038462 | J2: ='cpi-u-rs-adj-03'!E4 -> 0.413
B3: =+Sheet3!A3 -> 1948 | C3: =+ROUND(Sheet3!B3/Sheet3!B$35,4) -> 0.3205 | D3: =+ROUND(Sheet3!C3/Sheet3!C$35,4) -> 0.3186 | E3: =+ROUND(Sheet3!D3/Sheet3!D$35,4) -> 0.2925 | F3: =+ROUND(Sheet3!E3,4) -> 1.3852 | G3: =+ROUND(Sheet3!F3,4) -> 1.3859 | H3: =+ROUND('cpi-u-rs-adj'!D5/'cpi-u-rs-adj'!D$37,4) -> 0.4447 | I3: =1/H3 -> 2.248707 | J3: ='cpi-u-rs-adj-03'!E5 -> 0.441
B4: =+Sheet3!A4 -> 1949 | C4: =+ROUND(Sheet3!B4/Sheet3!B$35,4) -> 0.318 | D4: =+ROUND(Sheet3!C4/Sheet3!C$35,4) -> 0.3147 | E4: =+ROUND(Sheet3!D4/Sheet3!D$35,4) -> 0.2888 | F4: =+ROUND(Sheet3!E4,4) -> 1.4025 | G4: =+ROUND(Sheet3!F4,4) -> 1.4034 | H4: =+ROUND('cpi-u-rs-adj'!D6/'cpi-u-rs-adj'!D$37,4) -> 0.4343 | I4: =1/H4 -> 2.3025558 | J4: ='cpi-u-rs-adj-03'!E6 -> 0.431
B5: =+Sheet3!A5 -> 1950 | C5: =+ROUND(Sheet3!B5/Sheet3!B$35,4) -> 0.3218 | D5: =+ROUND(Sheet3!C5/Sheet3!C$35,4) -> 0.3186 | E5: =+ROUND(Sheet3!D5/Sheet3!D$35,4) -> 0.2925 | F5: =+ROUND(Sheet3!E5,4) -> 1.3852 | G5: =+ROUND(Sheet3!F5,4) -> 1.3859 | H5: =+ROUND('cpi-u-rs-adj'!D7/'cpi-u-rs-adj'!D$37,4) -> 0.435 | I5: =1/H5 -> 2.2988506 | J5: ='cpi-u-rs-adj-03'!E7 -> 0.431
B6: =+Sheet3!A6 -> 1951 | C6: =+ROUND(Sheet3!B6/Sheet3!B$35,4) -> 0.3437 | D6: =+ROUND(Sheet3!C6/Sheet3!C$35,4) -> 0.3438 | E6: =+ROUND(Sheet3!D6/Sheet3!D$35,4) -> 0.3155 | F6: =+ROUND(Sheet3!E6,4) -> 1.2838 | G6: =+ROUND(Sheet3!F6,4) -> 1.2846 | H6: =+ROUND('cpi-u-rs-adj'!D8/'cpi-u-rs-adj'!D$37,4) -> 0.4645 | I6: =1/H6 -> 2.1528525 | J6: ='cpi-u-rs-adj-03'!E8 -> 0.461
B7: =+Sheet3!A7 -> 1952 | C7: =+ROUND(Sheet3!B7/Sheet3!B$35,4) -> 0.3508 | D7: =+ROUND(Sheet3!C7/Sheet3!C$35,4) -> 0.3501 | E7: =+ROUND(Sheet3!D7/Sheet3!D$35,4) -> 0.3216 | F7: =+ROUND(Sheet3!E7,4) -> 1.2607 | G7: =+ROUND(Sheet3!F7,4) -> 1.2604 | H7: =+ROUND('cpi-u-rs-adj'!D9/'cpi-u-rs-adj'!D$37,4) -> 0.4679 | I7: =1/H7 -> 2.1372088 | J7: ='cpi-u-rs-adj-03'!E9 -> 0.464
B8: =+Sheet3!A8 -> 1953 | C8: =+ROUND(Sheet3!B8/Sheet3!B$35,4) -> 0.3554 | D8: =+ROUND(Sheet3!C8/Sheet3!C$35,4) -> 0.3525 | E8: =+ROUND(Sheet3!D8/Sheet3!D$35,4) -> 0.324 | F8: =+ROUND(Sheet3!E8,4) -> 1.2522 | G8: =+ROUND(Sheet3!F8,4) -> 1.2509 | H8: =+ROUND('cpi-u-rs-adj'!D10/'cpi-u-rs-adj'!D$37,4) -> 0.4659 | I8: =1/H8 -> 2.1463833 | J8: ='cpi-u-rs-adj-03'!E10 -> 0.462
B9: =+Sheet3!A9 -> 1954 | C9: =+ROUND(Sheet3!B9/Sheet3!B$35,4) -> 0.3584 | D9: =+ROUND(Sheet3!C9/Sheet3!C$35,4) -> 0.3556 | E9: =+ROUND(Sheet3!D9/Sheet3!D$35,4) -> 0.3265 | F9: =+ROUND(Sheet3!E9,4) -> 1.2412 | G9: =+ROUND(Sheet3!F9,4) -> 1.2416 | H9: =+ROUND('cpi-u-rs-adj'!D11/'cpi-u-rs-adj'!D$37,4) -> 0.465 | I9: =1/H9 -> 2.1505376 | J9: ='cpi-u-rs-adj-03'!E11 -> 0.461
B10: =+Sheet3!A10 -> 1955 | C10: =+ROUND(Sheet3!B10/Sheet3!B$35,4) -> 0.3598 | D10: =+ROUND(Sheet3!C10/Sheet3!C$35,4) -> 0.3541 | E10: =+ROUND(Sheet3!D10/Sheet3!D$35,4) -> 0.3252 | F10: =+ROUND(Sheet3!E10,4) -> 1.2467 | G10: =+ROUND(Sheet3!F10,4) -> 1.2463 | H10: =+ROUND('cpi-u-rs-adj'!D12/'cpi-u-rs-adj'!D$37,4) -> 0.4578 | I10: =1/H10 -> 2.18436 | J10: ='cpi-u-rs-adj-03'!E12 -> 0.454
B11: =+Sheet3!A11 -> 1956 | C11: =+ROUND(Sheet3!B11/Sheet3!B$35,4) -> 0.3669 | D11: =+ROUND(Sheet3!C11/Sheet3!C$35,4) -> 0.3596 | E11: =+ROUND(Sheet3!D11/Sheet3!D$35,4) -> 0.3301 | F11: =+ROUND(Sheet3!E11,4) -> 1.2276 | G11: =+ROUND(Sheet3!F11,4) -> 1.2279 | H11: =+ROUND('cpi-u-rs-adj'!D13/'cpi-u-rs-adj'!D$37,4) -> 0.4599 | I11: =1/H11 -> 2.1743857 | J11: ='cpi-u-rs-adj-03'!E13 -> 0.456
B12: =+Sheet3!A12 -> 1957 | C12: =+ROUND(Sheet3!B12/Sheet3!B$35,4) -> 0.3781 | D12: =+ROUND(Sheet3!C12/Sheet3!C$35,4) -> 0.3714 | E12: =+ROUND(Sheet3!D12/Sheet3!D$35,4) -> 0.341 | F12: =+ROUND(Sheet3!E12,4) -> 1.1886 | G12: =+ROUND(Sheet3!F12,4) -> 1.1886 | H12: =+ROUND('cpi-u-rs-adj'!D14/'cpi-u-rs-adj'!D$37,4) -> 0.4699 | I12: =1/H12 -> 2.1281124 | J12: ='cpi-u-rs-adj-03'!E14 -> 0.466
B13: =+Sheet3!A13 -> 1958 | C13: =+ROUND(Sheet3!B13/Sheet3!B$35,4) -> 0.387 | D13: =+ROUND(Sheet3!C13/Sheet3!C$35,4) -> 0.3816 | E13: =+ROUND(Sheet3!D13/Sheet3!D$35,4) -> 0.3507 | F13: =+ROUND(Sheet3!E13,4) -> 1.1567 | G13: =+ROUND(Sheet3!F13,4) -> 1.1557 | H13: =+ROUND('cpi-u-rs-adj'!D15/'cpi-u-rs-adj'!D$37,4) -> 0.4777 | I13: =1/H13 -> 2.093364 | J13: ='cpi-u-rs-adj-03'!E15 -> 0.474
... B77: =+Sheet3!A77 -> 2022 | C77: =+ROUND(Sheet3!B77/Sheet3!B$35,4) -> 2.9834 | D77: =+ROUND(Sheet3!C77/Sheet3!C$35,4) -> 3.395 | E77: =+ROUND(Sheet3!D77/Sheet3!D$35,4) -> 3.5516 | F77: =+ROUND(Sheet3!E77,4) -> 0.13 | G77: =+ROUND(Sheet3!F77,4) -> 0.1141 | H77: =+ROUND('cpi-u-rs-adj'!D79/'cpi-u-rs-adj'!D$37,4) -> 2.4464 | I77: =1/H77 -> 0.4087639 | J77: ='cpi-u-rs-adj-03'!E79 -> 0

Sheet dat_file 2000
B1: Year | C1: pce | D1: cpi-u-rs | E1: cpiu | F1: cpiu-rs67 | G1: cpiu67 | H1: cpi-u-rs adj | I1: N_cpi-u-rs adj
B2: =+Sheet3!A2 -> 1947 | C2: =ROUND('dat_file 1980'!C2/'dat_file 1980'!C$55,4) -> 0.1599 | D2: =ROUND('dat_file 1980'!D2/'dat_file 1980'!D$55,4) -> 0.1485 | E2: =ROUND('dat_file 1980'!E2/'dat_file 1980'!E$55,4) -> 0.1295 | F2: ='dat_file 1980'!F2 -> 1.496 | G2: ='dat_file 1980'!G2 -> 1.4978 | H2: =ROUND('dat_file 1980'!H2/'dat_file 1980'!H$55,4) -> 0.2446 | I2: =1/H2 -> 4.0883074
B3: =+Sheet3!A3 -> 1948 | C3: =ROUND('dat_file 1980'!C3/'dat_file 1980'!C$55,4) -> 0.169 | D3: =ROUND('dat_file 1980'!D3/'dat_file 1980'!D$55,4) -> 0.1604 | E3: =ROUND('dat_file 1980'!E3/'dat_file 1980'!E$55,4) -> 0.14 | F3: ='dat_file 1980'!F3 -> 1.3852 | G3: ='dat_file 1980'!G3 -> 1.3859 | H3: =ROUND('dat_file 1980'!H3/'dat_file 1980'!H$55,4) -> 0.2614 | I3: =1/H3 -> 3.8255547
B4: =+Sheet3!A4 -> 1949 | C4: =ROUND('dat_file 1980'!C4/'dat_file 1980'!C$55,4) -> 0.1677 | D4: =ROUND('dat_file 1980'!D4/'dat_file 1980'!D$55,4) -> 0.1584 | E4: =ROUND('dat_file 1980'!E4/'dat_file 1980'!E$55,4) -> 0.1382 | F4: ='dat_file 1980'!F4 -> 1.4025 | G4: ='dat_file 1980'!G4 -> 1.4034 | H4: =ROUND('dat_file 1980'!H4/'dat_file 1980'!H$55,4) -> 0.2553 | I4: =1/H4 -> 3.9169604
B5: =+Sheet3!A5 -> 1950 | C5: =ROUND('dat_file 1980'!C5/'dat_file 1980'!C$55,4) -> 0.1697 | D5: =ROUND('dat_file 1980'!D5/'dat_file 1980'!D$55,4) -> 0.1604 | E5: =ROUND('dat_file 1980'!E5/'dat_file 1980'!E$55,4) -> 0.14 | F5: ='dat_file 1980'!F5 -> 1.3852 | G5: ='dat_file 1980'!G5 -> 1.3859 | H5: =ROUND('dat_file 1980'!H5/'dat_file 1980'!H$55,4) -> 0.2557 | I5: =1/H5 -> 3.910833
B6: =+Sheet3!A6 -> 1951 | C6: =ROUND('dat_file 1980'!C6/'dat_file 1980'!C$55,4) -> 0.1812 | D6: =ROUND('dat_file 1980'!D6/'dat_file 1980'!D$55,4) -> 0.1731 | E6: =ROUND('dat_file 1980'!E6/'dat_file 1980'!E$55,4) -> 0.151 | F6: ='dat_file 1980'!F6 -> 1.2838 | G6: ='dat_file 1980'!G6 -> 1.2846 | H6: =ROUND('dat_file 1980'!H6/'dat_file 1980'!H$55,4) -> 0.2731 | I6: =1/H6 -> 3.6616624
B7: =+Sheet3!A7 -> 1952 | C7: =ROUND('dat_file 1980'!C7/'dat_file 1980'!C$55,4) -> 0.185 | D7: =ROUND('dat_file 1980'!D7/'dat_file 1980'!D$55,4) -> 0.1762 | E7: =ROUND('dat_file 1980'!E7/'dat_file 1980'!E$55,4) -> 0.1539 | F7: ='dat_file 1980'!F7 -> 1.2607 | G7: ='dat_file 1980'!G7 -> 1.2604 | H7: =ROUND('dat_file 1980'!H7/'dat_file 1980'!H$55,4) -> 0.2751 | I7: =1/H7 -> 3.6350418
B8: =+Sheet3!A8 -> 1953 | C8: =ROUND('dat_file 1980'!C8/'dat_file 1980'!C$55,4) -> 0.1874 | D8: =ROUND('dat_file 1980'!D8/'dat_file 1980'!D$55,4) -> 0.1774 | E8: =ROUND('dat_file 1980'!E8/'dat_file 1980'!E$55,4) -> 0.155 | F8: ='dat_file 1980'!F8 -> 1.2522 | G8: ='dat_file 1980'!G8 -> 1.2509 | H8: =ROUND('dat_file 1980'!H8/'dat_file 1980'!H$55,4) -> 0.2739 | I8: =1/H8 -> 3.6509675
B9: =+Sheet3!A9 -> 1954 | C9: =ROUND('dat_file 1980'!C9/'dat_file 1980'!C$55,4) -> 0.189 | D9: =ROUND('dat_file 1980'!D9/'dat_file 1980'!D$55,4) -> 0.179 | E9: =ROUND('dat_file 1980'!E9/'dat_file 1980'!E$55,4) -> 0.1562 | F9: ='dat_file 1980'!F9 -> 1.2412 | G9: ='dat_file 1980'!G9 -> 1.2416 | H9: =ROUND('dat_file 1980'!H9/'dat_file 1980'!H$55,4) -> 0.2734 | I9: =1/H9 -> 3.6576445
B10: =+Sheet3!A10 -> 1955 | C10: =ROUND('dat_file 1980'!C10/'dat_file 1980'!C$55,4) -> 0.1897 | D10: =ROUND('dat_file 1980'!D10/'dat_file 1980'!D$55,4) -> 0.1782 | E10: =ROUND('dat_file 1980'!E10/'dat_file 1980'!E$55,4) -> 0.1556 | F10: ='dat_file 1980'!F10 -> 1.2467 | G10: ='dat_file 1980'!G10 -> 1.2463 | H10: =ROUND('dat_file 1980'!H10/'dat_file 1980'!H$55,4) -> 0.2691 | I10: =1/H10 -> 3.7160907
B11: =+Sheet3!A11 -> 1956 | C11: =ROUND('dat_file 1980'!C11/'dat_file 1980'!C$55,4) -> 0.1935 | D11: =ROUND('dat_file 1980'!D11/'dat_file 1980'!D$55,4) -> 0.181 | E11: =ROUND('dat_file 1980'!E11/'dat_file 1980'!E$55,4) -> 0.158 | F11: ='dat_file 1980'!F11 -> 1.2276 | G11: ='dat_file 1980'!G11 -> 1.2279 | H11: =ROUND('dat_file 1980'!H11/'dat_file 1980'!H$55,4) -> 0.2704 | I11: =1/H11 -> 3.6982249
B12: =+Sheet3!A12 -> 1957 | C12: =ROUND('dat_file 1980'!C12/'dat_file 1980'!C$55,4) -> 0.1994 | D12: =ROUND('dat_file 1980'!D12/'dat_file 1980'!D$55,4) -> 0.187 | E12: =ROUND('dat_file 1980'!E12/'dat_file 1980'!E$55,4) -> 0.1632 | F12: ='dat_file 1980'!F12 -> 1.1886 | G12: ='dat_file 1980'!G12 -> 1.1886 | H12: =ROUND('dat_file 1980'!H12/'dat_file 1980'!H$55,4) -> 0.2762 | I12: =1/H12 -> 3.6205648
B13: =+Sheet3!A13 -> 1958 | C13: =ROUND('dat_file 1980'!C13/'dat_file 1980'!C$55,4) -> 0.2041 | D13: =ROUND('dat_file 1980'!D13/'dat_file 1980'!D$55,4) -> 0.1921 | E13: =ROUND('dat_file 1980'!E13/'dat_file 1980'!E$55,4) -> 0.1678 | F13: ='dat_file 1980'!F13 -> 1.1567 | G13: ='dat_file 1980'!G13 -> 1.1557 | H13: =ROUND('dat_file 1980'!H13/'dat_file 1980'!H$55,4) -> 0.2808 | I13: =1/H13 -> 3.5612536
... B76: =+Sheet3!A76 -> 2021 | C76: =ROUND('dat_file 1980'!C76/'dat_file 1980'!C$55,4) -> 1.4806 | D76: =ROUND('dat_file 1980'!D76/'dat_file 1980'!D$55,4) -> 1.581 | E76: =ROUND('dat_file 1980'!E76/'dat_file 1980'!E$55,4) -> 1.5736 | F76: ='dat_file 1980'!F76 -> 0.1405 | G76: ='dat_file 1980'!G76 -> 0.1233 | H76: =ROUND('dat_file 1980'!H76/'dat_file 1980'!H$55,4) -> 1.3404 | I76: =1/H76 -> 0.74604596

Sheet dat_file 2012
B1: Year | C1: pce | D1: cpi-u-rs | E1: cpiu | F1: cpiu-rs67 | G1: cpiu67 | H1: cpi-u-rs adj
B2: =+Sheet3!A2 -> 1947 | C2: =ROUND('dat_file 1980'!C2/'dat_file 1980'!C$67,4) -> 0.1249 | D2: =ROUND('dat_file 1980'!D2/'dat_file 1980'!D$67,4) -> 0.1113 | E2: =ROUND('dat_file 1980'!E2/'dat_file 1980'!E$67,4) -> 0.0971 | F2: ='dat_file 1980'!F2 -> 1.496 | G2: ='dat_file 1980'!G2 -> 1.4978 | H2: =ROUND('dat_file 1980'!H2/'dat_file 1980'!H$67,4) -> 0.2014
B3: =+Sheet3!A3 -> 1948 | C3: =ROUND('dat_file 1980'!C3/'dat_file 1980'!C$67,4) -> 0.132 | D3: =ROUND('dat_file 1980'!D3/'dat_file 1980'!D$67,4) -> 0.1202 | E3: =ROUND('dat_file 1980'!E3/'dat_file 1980'!E$67,4) -> 0.105 | F3: ='dat_file 1980'!F3 -> 1.3852 | G3: ='dat_file 1980'!G3 -> 1.3859 | H3: =ROUND('dat_file 1980'!H3/'dat_file 1980'!H$67,4) -> 0.2153
B4: =+Sheet3!A4 -> 1949 | C4: =ROUND('dat_file 1980'!C4/'dat_file 1980'!C$67,4) -> 0.131 | D4: =ROUND('dat_file 1980'!D4/'dat_file 1980'!D$67,4) -> 0.1187 | E4: =ROUND('dat_file 1980'!E4/'dat_file 1980'!E$67,4) -> 0.1037 | F4: ='dat_file 1980'!F4 -> 1.4025 | G4: ='dat_file 1980'!G4 -> 1.4034 | H4: =ROUND('dat_file 1980'!H4/'dat_file 1980'!H$67,4) -> 0.2102
B5: =+Sheet3!A5 -> 1950 | C5: =ROUND('dat_file 1980'!C5/'dat_file 1980'!C$67,4) -> 0.1325 | D5: =ROUND('dat_file 1980'!D5/'dat_file 1980'!D$67,4) -> 0.1202 | E5: =ROUND('dat_file 1980'!E5/'dat_file 1980'!E$67,4) -> 0.105 | F5: ='dat_file 1980'!F5 -> 1.3852 | G5: ='dat_file 1980'!G5 -> 1.3859 | H5: =ROUND('dat_file 1980'!H5/'dat_file 1980'!H$67,4) -> 0.2106
B6: =+Sheet3!A6 -> 1951 | C6: =ROUND('dat_file 1980'!C6/'dat_file 1980'!C$67,4) -> 0.1415 | D6: =ROUND('dat_file 1980'!D6/'dat_file 1980'!D$67,4) -> 0.1297 | E6: =ROUND('dat_file 1980'!E6/'dat_file 1980'!E$67,4) -> 0.1132 | F6: ='dat_file 1980'!F6 -> 1.2838 | G6: ='dat_file 1980'!G6 -> 1.2846 | H6: =ROUND('dat_file 1980'!H6/'dat_file 1980'!H$67,4) -> 0.2249
B7: =+Sheet3!A7 -> 1952 | C7: =ROUND('dat_file 1980'!C7/'dat_file 1980'!C$67,4) -> 0.1445 | D7: =ROUND('dat_file 1980'!D7/'dat_file 1980'!D$67,4) -> 0.1321 | E7: =ROUND('dat_file 1980'!E7/'dat_file 1980'!E$67,4) -> 0.1154 | F7: ='dat_file 1980'!F7 -> 1.2607 | G7: ='dat_file 1980'!G7 -> 1.2604 | H7: =ROUND('dat_file 1980'!H7/'dat_file 1980'!H$67,4) -> 0.2265
B8: =+Sheet3!A8 -> 1953 | C8: =ROUND('dat_file 1980'!C8/'dat_file 1980'!C$67,4) -> 0.1464 | D8: =ROUND('dat_file 1980'!D8/'dat_file 1980'!D$67,4) -> 0.133 | E8: =ROUND('dat_file 1980'!E8/'dat_file 1980'!E$67,4) -> 0.1163 | F8: ='dat_file 1980'!F8 -> 1.2522 | G8: ='dat_file 1980'!G8 -> 1.2509 | H8: =ROUND('dat_file 1980'!H8/'dat_file 1980'!H$67,4) -> 0.2255
B9: =+Sheet3!A9 -> 1954 | C9: =ROUND('dat_file 1980'!C9/'dat_file 1980'!C$67,4) -> 0.1476 | D9: =ROUND('dat_file 1980'!D9/'dat_file 1980'!D$67,4) -> 0.1342 | E9: =ROUND('dat_file 1980'!E9/'dat_file 1980'!E$67,4) -> 0.1172 | F9: ='dat_file 1980'!F9 -> 1.2412 | G9: ='dat_file 1980'!G9 -> 1.2416 | H9: =ROUND('dat_file 1980'!H9/'dat_file 1980'!H$67,4) -> 0.2251
B10: =+Sheet3!A10 -> 1955 | C10: =ROUND('dat_file 1980'!C10/'dat_file 1980'!C$67,4) -> 0.1482 | D10: =ROUND('dat_file 1980'!D10/'dat_file 1980'!D$67,4) -> 0.1336 | E10: =ROUND('dat_file 1980'!E10/'dat_file 1980'!E$67,4) -> 0.1167 | F10: ='dat_file 1980'!F10 -> 1.2467 | G10: ='dat_file 1980'!G10 -> 1.2463 | H10: =ROUND('dat_file 1980'!H10/'dat_file 1980'!H$67,4) -> 0.2216
B11: =+Sheet3!A11 -> 1956 | C11: =ROUND('dat_file 1980'!C11/'dat_file 1980'!C$67,4) -> 0.1511 | D11: =ROUND('dat_file 1980'!D11/'dat_file 1980'!D$67,4) -> 0.1357 | E11: =ROUND('dat_file 1980'!E11/'dat_file 1980'!E$67,4) -> 0.1185 | F11: ='dat_file 1980'!F11 -> 1.2276 | G11: ='dat_file 1980'!G11 -> 1.2279 | H11: =ROUND('dat_file 1980'!H11/'dat_file 1980'!H$67,4) -> 0.2226
B12: =+Sheet3!A12 -> 1957 | C12: =ROUND('dat_file 1980'!C12/'dat_file 1980'!C$67,4) -> 0.1557 | D12: =ROUND('dat_file 1980'!D12/'dat_file 1980'!D$67,4) -> 0.1401 | E12: =ROUND('dat_file 1980'!E12/'dat_file 1980'!E$67,4) -> 0.1224 | F12: ='dat_file 1980'!F12 -> 1.1886 | G12: ='dat_file 1980'!G12 -> 1.1886 | H12: =ROUND('dat_file 1980'!H12/'dat_file 1980'!H$67,4) -> 0.2275
B13: =+Sheet3!A13 -> 1958 | C13: =ROUND('dat_file 1980'!C13/'dat_file 1980'!C$67,4) -> 0.1594 | D13: =ROUND('dat_file 1980'!D13/'dat_file 1980'!D$67,4) -> 0.144 | E13: =ROUND('dat_file 1980'!E13/'dat_file 1980'!E$67,4) -> 0.1259 | F13: ='dat_file 1980'!F13 -> 1.1567 | G13: ='dat_file 1980'!G13 -> 1.1557 | H13: =ROUND('dat_file 1980'!H13/'dat_file 1980'!H$67,4) -> 0.2312
... B76: =+Sheet3!A76 -> 2021 | C76: =ROUND('dat_file 1980'!C76/'dat_file 1980'!C$67,4) -> 1.1562 | D76: =ROUND('dat_file 1980'!D76/'dat_file 1980'!D$67,4) -> 1.1849 | E76: =ROUND('dat_file 1980'!E76/'dat_file 1980'!E$67,4) -> 1.1802 | F76: ='dat_file 1980'!F76 -> 0.1405 | G76: ='dat_file 1980'!G76 -> 0.1233 | H76: =ROUND('dat_file 1980'!H76/'dat_file 1980'!H$67,4) -> 1.1037

Sheet dat_file 2015
B1: Year | C1: pce | D1: cpi-u-rs | E1: cpiu | F1: cpiu-rs67 | G1: cpiu67 | H1: cpi-u-rs adj
B2: =+Sheet3!A2 -> 1947 | C2: =ROUND('dat_file 1980'!C2/'dat_file 1980'!C$70,4) -> 0.1211 | D2: =ROUND('dat_file 1980'!D2/'dat_file 1980'!D$70,4) -> 0.1076 | E2: =ROUND('dat_file 1980'!E2/'dat_file 1980'!E$70,4) -> 0.0941 | F2: ='dat_file 1980'!F2 -> 1.496 | G2: ='dat_file 1980'!G2 -> 1.4978 | H2: =ROUND('dat_file 1980'!H2/'dat_file 1980'!H$70,4) -> 0.1995
B3: =+Sheet3!A3 -> 1948 | C3: =ROUND('dat_file 1980'!C3/'dat_file 1980'!C$70,4) -> 0.128 | D3: =ROUND('dat_file 1980'!D3/'dat_file 1980'!D$70,4) -> 0.1163 | E3: =ROUND('dat_file 1980'!E3/'dat_file 1980'!E$70,4) -> 0.1017 | F3: ='dat_file 1980'!F3 -> 1.3852 | G3: ='dat_file 1980'!G3 -> 1.3859 | H3: =ROUND('dat_file 1980'!H3/'dat_file 1980'!H$70,4) -> 0.2132
B4: =+Sheet3!A4 -> 1949 | C4: =ROUND('dat_file 1980'!C4/'dat_file 1980'!C$70,4) -> 0.127 | D4: =ROUND('dat_file 1980'!D4/'dat_file 1980'!D$70,4) -> 0.1148 | E4: =ROUND('dat_file 1980'!E4/'dat_file 1980'!E$70,4) -> 0.1004 | F4: ='dat_file 1980'!F4 -> 1.4025 | G4: ='dat_file 1980'!G4 -> 1.4034 | H4: =ROUND('dat_file 1980'!H4/'dat_file 1980'!H$70,4) -> 0.2083
B5: =+Sheet3!A5 -> 1950 | C5: =ROUND('dat_file 1980'!C5/'dat_file 1980'!C$70,4) -> 0.1285 | D5: =ROUND('dat_file 1980'!D5/'dat_file 1980'!D$70,4) -> 0.1163 | E5: =ROUND('dat_file 1980'!E5/'dat_file 1980'!E$70,4) -> 0.1017 | F5: ='dat_file 1980'!F5 -> 1.3852 | G5: ='dat_file 1980'!G5 -> 1.3859 | H5: =ROUND('dat_file 1980'!H5/'dat_file 1980'!H$70,4) -> 0.2086
B6: =+Sheet3!A6 -> 1951 | C6: =ROUND('dat_file 1980'!C6/'dat_file 1980'!C$70,4) -> 0.1373 | D6: =ROUND('dat_file 1980'!D6/'dat_file 1980'!D$70,4) -> 0.1255 | E6: =ROUND('dat_file 1980'!E6/'dat_file 1980'!E$70,4) -> 0.1097 | F6: ='dat_file 1980'!F6 -> 1.2838 | G6: ='dat_file 1980'!G6 -> 1.2846 | H6: =ROUND('dat_file 1980'!H6/'dat_file 1980'!H$70,4) -> 0.2227
B7: =+Sheet3!A7 -> 1952 | C7: =ROUND('dat_file 1980'!C7/'dat_file 1980'!C$70,4) -> 0.1401 | D7: =ROUND('dat_file 1980'!D7/'dat_file 1980'!D$70,4) -> 0.1278 | E7: =ROUND('dat_file 1980'!E7/'dat_file 1980'!E$70,4) -> 0.1118 | F7: ='dat_file 1980'!F7 -> 1.2607 | G7: ='dat_file 1980'!G7 -> 1.2604 | H7: =ROUND('dat_file 1980'!H7/'dat_file 1980'!H$70,4) -> 0.2244
B8: =+Sheet3!A8 -> 1953 | C8: =ROUND('dat_file 1980'!C8/'dat_file 1980'!C$70,4) -> 0.1419 | D8: =ROUND('dat_file 1980'!D8/'dat_file 1980'!D$70,4) -> 0.1286 | E8: =ROUND('dat_file 1980'!E8/'dat_file 1980'!E$70,4) -> 0.1126 | F8: ='dat_file 1980'!F8 -> 1.2522 | G8: ='dat_file 1980'!G8 -> 1.2509 | H8: =ROUND('dat_file 1980'!H8/'dat_file 1980'!H$70,4) -> 0.2234
B9: =+Sheet3!A9 -> 1954 | C9: =ROUND('dat_file 1980'!C9/'dat_file 1980'!C$70,4) -> 0.1431 | D9: =ROUND('dat_file 1980'!D9/'dat_file 1980'!D$70,4) -> 0.1298 | E9: =ROUND('dat_file 1980'!E9/'dat_file 1980'!E$70,4) -> 0.1135 | F9: ='dat_file 1980'!F9 -> 1.2412 | G9: ='dat_file 1980'!G9 -> 1.2416 | H9: =ROUND('dat_file 1980'!H9/'dat_file 1980'!H$70,4) -> 0.223
B10: =+Sheet3!A10 -> 1955 | C10: =ROUND('dat_file 1980'!C10/'dat_file 1980'!C$70,4) -> 0.1437 | D10: =ROUND('dat_file 1980'!D10/'dat_file 1980'!D$70,4) -> 0.1292 | E10: =ROUND('dat_file 1980'!E10/'dat_file 1980'!E$70,4) -> 0.1131 | F10: ='dat_file 1980'!F10 -> 1.2467 | G10: ='dat_file 1980'!G10 -> 1.2463 | H10: =ROUND('dat_file 1980'!H10/'dat_file 1980'!H$70,4) -> 0.2195
B11: =+Sheet3!A11 -> 1956 | C11: =ROUND('dat_file 1980'!C11/'dat_file 1980'!C$70,4) -> 0.1465 | D11: =ROUND('dat_file 1980'!D11/'dat_file 1980'!D$70,4) -> 0.1312 | E11: =ROUND('dat_file 1980'!E11/'dat_file 1980'!E$70,4) -> 0.1148 | F11: ='dat_file 1980'!F11 -> 1.2276 | G11: ='dat_file 1980'!G11 -> 1.2279 | H11: =ROUND('dat_file 1980'!H11/'dat_file 1980'!H$70,4) -> 0.2205
B12: =+Sheet3!A12 -> 1957 | C12: =ROUND('dat_file 1980'!C12/'dat_file 1980'!C$70,4) -> 0.151 | D12: =ROUND('dat_file 1980'!D12/'dat_file 1980'!D$70,4) -> 0.1355 | E12: =ROUND('dat_file 1980'!E12/'dat_file 1980'!E$70,4) -> 0.1186 | F12: ='dat_file 1980'!F12 -> 1.1886 | G12: ='dat_file 1980'!G12 -> 1.1886 | H12: =ROUND('dat_file 1980'!H12/'dat_file 1980'!H$70,4) -> 0.2253
B13: =+Sheet3!A13 -> 1958 | C13: =ROUND('dat_file 1980'!C13/'dat_file 1980'!C$70,4) -> 0.1546 | D13: =ROUND('dat_file 1980'!D13/'dat_file 1980'!D$70,4) -> 0.1392 | E13: =ROUND('dat_file 1980'!E13/'dat_file 1980'!E$70,4) -> 0.1219 | F13: ='dat_file 1980'!F13 -> 1.1567 | G13: ='dat_file 1980'!G13 -> 1.1557 | H13: =ROUND('dat_file 1980'!H13/'dat_file 1980'!H$70,4) -> 0.2291
... B77: =+Sheet3!A77 -> 2022 | C77: =ROUND('dat_file 1980'!C77/'dat_file 1980'!C$70,4) -> 1.1915 | D77: =ROUND('dat_file 1980'!D77/'dat_file 1980'!D$70,4) -> 1.2389 | E77: =ROUND('dat_file 1980'!E77/'dat_file 1980'!E$70,4) -> 1.2347 | F77: ='dat_file 1980'!F77 -> 0.13 | G77: ='dat_file 1980'!G77 -> 0.1141 | H77: =ROUND('dat_file 1980'!H77/'dat_file 1980'!H$70,4) -> 1.1731

Sheet dat_file 2020
B1: Year | C1: pce | D1: cpi-u-rs | E1: cpiu | F1: cpiu-rs67 | G1: cpiu67 | H1: cpi-u-rs adj | I1: cpi-u-rs adj03
B2: =+Sheet3!A2 -> 1947 | C2: =ROUND('dat_file 1980'!C2/'dat_file 1980'!C$75,4) -> 0.1124 | D2: =ROUND('dat_file 1980'!D2/'dat_file 1980'!D$75,4) -> 0.0985 | E2: =ROUND('dat_file 1980'!E2/'dat_file 1980'!E$75,4) -> 0.0862 | F2: ='dat_file 1980'!F2 -> 1.496 | G2: ='dat_file 1980'!G2 -> 1.4978 | H2: =ROUND('dat_file 1980'!H2/'dat_file 1980'!H$75,4) -> 0.1898 | I2: =ROUND('dat_file 1980'!J2/'dat_file 1980'!J$75,4) -> 0.1675
B3: =+Sheet3!A3 -> 1948 | C3: =ROUND('dat_file 1980'!C3/'dat_file 1980'!C$75,4) -> 0.1188 | D3: =ROUND('dat_file 1980'!D3/'dat_file 1980'!D$75,4) -> 0.1063 | E3: =ROUND('dat_file 1980'!E3/'dat_file 1980'!E$75,4) -> 0.0931 | F3: ='dat_file 1980'!F3 -> 1.3852 | G3: ='dat_file 1980'!G3 -> 1.3859 | H3: =ROUND('dat_file 1980'!H3/'dat_file 1980'!H$75,4) -> 0.2029 | I3: =ROUND('dat_file 1980'!J3/'dat_file 1980'!J$75,4) -> 0.1789
B4: =+Sheet3!A4 -> 1949 | C4: =ROUND('dat_file 1980'!C4/'dat_file 1980'!C$75,4) -> 0.1178 | D4: =ROUND('dat_file 1980'!D4/'dat_file 1980'!D$75,4) -> 0.105 | E4: =ROUND('dat_file 1980'!E4/'dat_file 1980'!E$75,4) -> 0.0919 | F4: ='dat_file 1980'!F4 -> 1.4025 | G4: ='dat_file 1980'!G4 -> 1.4034 | H4: =ROUND('dat_file 1980'!H4/'dat_file 1980'!H$75,4) -> 0.1981 | I4: =ROUND('dat_file 1980'!J4/'dat_file 1980'!J$75,4) -> 0.1748
B5: =+Sheet3!A5 -> 1950 | C5: =ROUND('dat_file 1980'!C5/'dat_file 1980'!C$75,4) -> 0.1192 | D5: =ROUND('dat_file 1980'!D5/'dat_file 1980'!D$75,4) -> 0.1063 | E5: =ROUND('dat_file 1980'!E5/'dat_file 1980'!E$75,4) -> 0.0931 | F5: ='dat_file 1980'!F5 -> 1.3852 | G5: ='dat_file 1980'!G5 -> 1.3859 | H5: =ROUND('dat_file 1980'!H5/'dat_file 1980'!H$75,4) -> 0.1985 | I5: =ROUND('dat_file 1980'!J5/'dat_file 1980'!J$75,4) -> 0.1748
B6: =+Sheet3!A6 -> 1951 | C6: =ROUND('dat_file 1980'!C6/'dat_file 1980'!C$75,4) -> 0.1273 | D6: =ROUND('dat_file 1980'!D6/'dat_file 1980'!D$75,4) -> 0.1147 | E6: =ROUND('dat_file 1980'!E6/'dat_file 1980'!E$75,4) -> 0.1004 | F6: ='dat_file 1980'!F6 -> 1.2838 | G6: ='dat_file 1980'!G6 -> 1.2846 | H6: =ROUND('dat_file 1980'!H6/'dat_file 1980'!H$75,4) -> 0.2119 | I6: =ROUND('dat_file 1980'!J6/'dat_file 1980'!J$75,4) -> 0.187
B7: =+Sheet3!A7 -> 1952 | C7: =ROUND('dat_file 1980'!C7/'dat_file 1980'!C$75,4) -> 0.13 | D7: =ROUND('dat_file 1980'!D7/'dat_file 1980'!D$75,4) -> 0.1169 | E7: =ROUND('dat_file 1980'!E7/'dat_file 1980'!E$75,4) -> 0.1024 | F7: ='dat_file 1980'!F7 -> 1.2607 | G7: ='dat_file 1980'!G7 -> 1.2604 | H7: =ROUND('dat_file 1980'!H7/'dat_file 1980'!H$75,4) -> 0.2135 | I7: =ROUND('dat_file 1980'!J7/'dat_file 1980'!J$75,4) -> 0.1882
B8: =+Sheet3!A8 -> 1953 | C8: =ROUND('dat_file 1980'!C8/'dat_file 1980'!C$75,4) -> 0.1317 | D8: =ROUND('dat_file 1980'!D8/'dat_file 1980'!D$75,4) -> 0.1177 | E8: =ROUND('dat_file 1980'!E8/'dat_file 1980'!E$75,4) -> 0.1032 | F8: ='dat_file 1980'!F8 -> 1.2522 | G8: ='dat_file 1980'!G8 -> 1.2509 | H8: =ROUND('dat_file 1980'!H8/'dat_file 1980'!H$75,4) -> 0.2126 | I8: =ROUND('dat_file 1980'!J8/'dat_file 1980'!J$75,4) -> 0.1874
B9: =+Sheet3!A9 -> 1954 | C9: =ROUND('dat_file 1980'!C9/'dat_file 1980'!C$75,4) -> 0.1328 | D9: =ROUND('dat_file 1980'!D9/'dat_file 1980'!D$75,4) -> 0.1187 | E9: =ROUND('dat_file 1980'!E9/'dat_file 1980'!E$75,4) -> 0.104 | F9: ='dat_file 1980'!F9 -> 1.2412 | G9: ='dat_file 1980'!G9 -> 1.2416 | H9: =ROUND('dat_file 1980'!H9/'dat_file 1980'!H$75,4) -> 0.2122 | I9: =ROUND('dat_file 1980'!J9/'dat_file 1980'!J$75,4) -> 0.187
B10: =+Sheet3!A10 -> 1955 | C10: =ROUND('dat_file 1980'!C10/'dat_file 1980'!C$75,4) -> 0.1333 | D10: =ROUND('dat_file 1980'!D10/'dat_file 1980'!D$75,4) -> 0.1182 | E10: =ROUND('dat_file 1980'!E10/'dat_file 1980'!E$75,4) -> 0.1035 | F10: ='dat_file 1980'!F10 -> 1.2467 | G10: ='dat_file 1980'!G10 -> 1.2463 | H10: =ROUND('dat_file 1980'!H10/'dat_file 1980'!H$75,4) -> 0.2089 | I10: =ROUND('dat_file 1980'!J10/'dat_file 1980'!J$75,4) -> 0.1842
B11: =+Sheet3!A11 -> 1956 | C11: =ROUND('dat_file 1980'!C11/'dat_file 1980'!C$75,4) -> 0.1359 | D11: =ROUND('dat_file 1980'!D11/'dat_file 1980'!D$75,4) -> 0.12 | E11: =ROUND('dat_file 1980'!E11/'dat_file 1980'!E$75,4) -> 0.1051 | F11: ='dat_file 1980'!F11 -> 1.2276 | G11: ='dat_file 1980'!G11 -> 1.2279 | H11: =ROUND('dat_file 1980'!H11/'dat_file 1980'!H$75,4) -> 0.2098 | I11: =ROUND('dat_file 1980'!J11/'dat_file 1980'!J$75,4) -> 0.185
B12: =+Sheet3!A12 -> 1957 | C12: =ROUND('dat_file 1980'!C12/'dat_file 1980'!C$75,4) -> 0.1401 | D12: =ROUND('dat_file 1980'!D12/'dat_file 1980'!D$75,4) -> 0.124 | E12: =ROUND('dat_file 1980'!E12/'dat_file 1980'!E$75,4) -> 0.1086 | F12: ='dat_file 1980'!F12 -> 1.1886 | G12: ='dat_file 1980'!G12 -> 1.1886 | H12: =ROUND('dat_file 1980'!H12/'dat_file 1980'!H$75,4) -> 0.2144 | I12: =ROUND('dat_file 1980'!J12/'dat_file 1980'!J$75,4) -> 0.189
B13: =+Sheet3!A13 -> 1958 | C13: =ROUND('dat_file 1980'!C13/'dat_file 1980'!C$75,4) -> 0.1434 | D13: =ROUND('dat_file 1980'!D13/'dat_file 1980'!D$75,4) -> 0.1274 | E13: =ROUND('dat_file 1980'!E13/'dat_file 1980'!E$75,4) -> 0.1117 | F13: ='dat_file 1980'!F13 -> 1.1567 | G13: ='dat_file 1980'!G13 -> 1.1557 | H13: =ROUND('dat_file 1980'!H13/'dat_file 1980'!H$75,4) -> 0.2179 | I13: =ROUND('dat_file 1980'!J13/'dat_file 1980'!J$75,4) -> 0.1923
B14: =+Sheet3!A14 -> 1959 | C14: =ROUND('dat_file 1980'!C14/'dat_file 1980'!C$75,4) -> 0.1455 | D14: =ROUND('dat_file 1980'!D14/'dat_file 1980'!D$75,4) -> 0.1284 | E14: =ROUND('dat_file 1980'!E14/'dat_file 1980'!E$75,4) -> 0.1125 | F14: ='dat_file 1980'!F14 -> 1.1472 | G14: ='dat_file 1980'!G14 -> 1.1478 | H14: =ROUND('dat_file 1980'!H14/'dat_file 1980'!H$75,4) -> 0.2174 | I14: =ROUND('dat_file 1980'!J14/'dat_file 1980'!J$75,4) -> 0.1915
B15: =+Sheet3!A15 -> 1960 | C15: =ROUND('dat_file 1980'!C15/'dat_file 1980'!C$75,4) -> 0.1479 | D15: =ROUND('dat_file 1980'!D15/'dat_file 1980'!D$75,4) -> 0.1305 | E15: =ROUND('dat_file 1980'!E15/'dat_file 1980'!E$75,4) -> 0.1144 | F15: ='dat_file 1980'!F15 -> 1.1288 | G15: ='dat_file 1980'!G15 -> 1.1284 | H15: =ROUND('dat_file 1980'!H15/'dat_file 1980'!H$75,4) -> 0.2185 | I15: =ROUND('dat_file 1980'!J15/'dat_file 1980'!J$75,4) -> 0.1927 | K15: ="IF ref_year="&'dat_file 1980'!B15&" THEN cpi_u_rs_18="&ROUND('dat_file 1980'!$D$73/'dat_file 1980'!D15,3)&";" -> IF ref_year=1960 THEN cpi_u_rs_18=7.427; | O15: ="IF ref_year="&'dat_file 1980'!B15&" THEN cpi_u_rs_adj_18="&ROUND('dat_file 1980'!$H$73/'dat_file 1980'!H15,3)&";" -> IF ref_year=1960 THEN cpi_u_rs_adj_18=4.507;
B16: =+Sheet3!A16 -> 1961 | C16: =ROUND('dat_file 1980'!C16/'dat_file 1980'!C$75,4) -> 0.1495 | D16: =ROUND('dat_file 1980'!D16/'dat_file 1980'!D$75,4) -> 0.1318 | E16: =ROUND('dat_file 1980'!E16/'dat_file 1980'!E$75,4) -> 0.1155 | F16: ='dat_file 1980'!F16 -> 1.1175 | G16: ='dat_file 1980'!G16 -> 1.1171 | H16: =ROUND('dat_file 1980'!H16/'dat_file 1980'!H$75,4) -> 0.2183 | I16: =ROUND('dat_file 1980'!J16/'dat_file 1980'!J$75,4) -> 0.1927 | K16: ="ELSE IF ref_year="&'dat_file 1980'!B16&" THEN cpi_u_rs_18="&ROUND('dat_file 1980'!$D$73/'dat_file 1980'!D16,3)&";" -> ELSE IF ref_year=1961 THEN cpi_u_rs_18=7.352; | O16: ="ELSE IF ref_year="&'dat_file 1980'!B16&" THEN cpi_u_rs_adj_18="&ROUND('dat_file 1980'!$H$73/'dat_file 1980'!H16,3)&";" -> ELSE IF ref_year=1961 THEN cpi_u_rs_adj_18=4.511;
B17: =+Sheet3!A17 -> 1962 | C17: =ROUND('dat_file 1980'!C17/'dat_file 1980'!C$75,4) -> 0.1512 | D17: =ROUND('dat_file 1980'!D17/'dat_file 1980'!D$75,4) -> 0.1331 | E17: =ROUND('dat_file 1980'!E17/'dat_file 1980'!E$75,4) -> 0.1167 | F17: ='dat_file 1980'!F17 -> 1.1065 | G17: ='dat_file 1980'!G17 -> 1.106 | H17: =ROUND('dat_file 1980'!H17/'dat_file 1980'!H$75,4) -> 0.2181 | I17: =ROUND('dat_file 1980'!J17/'dat_file 1980'!J$75,4) -> 0.1923 | K17: ="ELSE IF ref_year="&'dat_file 1980'!B17&" THEN cpi_u_rs_18="&ROUND('dat_file 1980'!$D$73/'dat_file 1980'!D17,3)&";" -> ELSE IF ref_year=1962 THEN cpi_u_rs_18=7.28; | O17: ="ELSE IF ref_year="&'dat_file 1980'!B17&" THEN cpi_u_rs_adj_18="&ROUND('dat_file 1980'!$H$73/'dat_file 1980'!H17,3)&";" -> ELSE IF ref_year=1962 THEN cpi_u_rs_adj_18=4.515;
B18: =+Sheet3!A18 -> 1963 | C18: =ROUND('dat_file 1980'!C18/'dat_file 1980'!C$75,4) -> 0.153 | D18: =ROUND('dat_file 1980'!D18/'dat_file 1980'!D$75,4) -> 0.135 | E18: =ROUND('dat_file 1980'!E18/'dat_file 1980'!E$75,4) -> 0.1182 | F18: ='dat_file 1980'!F18 -> 1.0914 | G18: ='dat_file 1980'!G18 -> 1.0915 | H18: =ROUND('dat_file 1980'!H18/'dat_file 1980'!H$75,4) -> 0.2187 | I18: =ROUND('dat_file 1980'!J18/'dat_file 1980'!J$75,4) -> 0.1927 | K18: ="ELSE IF ref_year="&'dat_file 1980'!B18&" THEN cpi_u_rs_18="&ROUND('dat_file 1980'!$D$73/'dat_file 1980'!D18,3)&";" -> ELSE IF ref_year=1963 THEN cpi_u_rs_18=7.181; | O18: ="ELSE IF ref_year="&'dat_file 1980'!B18&" THEN cpi_u_rs_adj_18="&ROUND('dat_file 1980'!$H$73/'dat_file 1980'!H18,3)&";" -> ELSE IF ref_year=1963 THEN cpi_u_rs_adj_18=4.503;
B19: =+Sheet3!A19 -> 1964 | C19: =ROUND('dat_file 1980'!C19/'dat_file 1980'!C$75,4) -> 0.1552 | D19: =ROUND('dat_file 1980'!D19/'dat_file 1980'!D$75,4) -> 0.1368 | E19: =ROUND('dat_file 1980'!E19/'dat_file 1980'!E$75,4) -> 0.1198 | F19: ='dat_file 1980'!F19 -> 1.0768 | G19: ='dat_file 1980'!G19 -> 1.0774 | H19: =ROUND('dat_file 1980'!H19/'dat_file 1980'!H$75,4) -> 0.2193 | I19: =ROUND('dat_file 1980'!J19/'dat_file 1980'!J$75,4) -> 0.1935 | K19: ="ELSE IF ref_year="&'dat_file 1980'!B19&" THEN cpi_u_rs_18="&ROUND('dat_file 1980'!$D$73/'dat_file 1980'!D19,3)&";" -> ELSE IF ref_year=1964 THEN cpi_u_rs_18=7.085; | O19: ="ELSE IF ref_year="&'dat_file 1980'!B19&" THEN cpi_u_rs_adj_18="&ROUND('dat_file 1980'!$H$73/'dat_file 1980'!H19,3)&";" -> ELSE IF ref_year=1964 THEN cpi_u_rs_adj_18=4.491;
B20: =+Sheet3!A20 -> 1965 | C20: =ROUND('dat_file 1980'!C20/'dat_file 1980'!C$75,4) -> 0.1575 | D20: =ROUND('dat_file 1980'!D20/'dat_file 1980'!D$75,4) -> 0.1389 | E20: =ROUND('dat_file 1980'!E20/'dat_file 1980'!E$75,4) -> 0.1217 | F20: ='dat_file 1980'!F20 -> 1.0605 | G20: ='dat_file 1980'!G20 -> 1.0603 | H20: =ROUND('dat_file 1980'!H20/'dat_file 1980'!H$75,4) -> 0.2202 | I20: =ROUND('dat_file 1980'!J20/'dat_file 1980'!J$75,4) -> 0.1943 | K20: ="ELSE IF ref_year="&'dat_file 1980'!B20&" THEN cpi_u_rs_18="&ROUND('dat_file 1980'!$D$73/'dat_file 1980'!D20,3)&";" -> ELSE IF ref_year=1965 THEN cpi_u_rs_18=6.977; | O20: ="ELSE IF ref_year="&'dat_file 1980'!B20&" THEN cpi_u_rs_adj_18="&ROUND('dat_file 1980'!$H$73/'dat_file 1980'!H20,3)&";" -> ELSE IF ref_year=1965 THEN cpi_u_rs_adj_18=4.471;
B21: =+Sheet3!A21 -> 1966 | C21: =ROUND('dat_file 1980'!C21/'dat_file 1980'!C$75,4) -> 0.1614 | D21: =ROUND('dat_file 1980'!D21/'dat_file 1980'!D$75,4) -> 0.1429 | E21: =ROUND('dat_file 1980'!E21/'dat_file 1980'!E$75,4) -> 0.1252 | F21: ='dat_file 1980'!F21 -> 1.0313 | G21: ='dat_file 1980'!G21 -> 1.0309 | H21: =ROUND('dat_file 1980'!H21/'dat_file 1980'!H$75,4) -> 0.2241 | I21: =ROUND('dat_file 1980'!J21/'dat_file 1980'!J$75,4) -> 0.1976 | K21: ="ELSE IF ref_year="&'dat_file 1980'!B21&" THEN cpi_u_rs_18="&ROUND('dat_file 1980'!$D$73/'dat_file 1980'!D21,3)&";" -> ELSE IF ref_year=1966 THEN cpi_u_rs_18=6.785; | O21: ="ELSE IF ref_year="&'dat_file 1980'!B21&" THEN cpi_u_rs_adj_18="&ROUND('dat_file 1980'!$H$73/'dat_file 1980'!H21,3)&";" -> ELSE IF ref_year=1966 THEN cpi_u_rs_adj_18=4.395;
B22: =+Sheet3!A22 -> 1967 | C22: =ROUND('dat_file 1980'!C22/'dat_file 1980'!C$75,4) -> 0.1655 | D22: =ROUND('dat_file 1980'!D22/'dat_file 1980'!D$75,4) -> 0.1473 | E22: =ROUND('dat_file 1980'!E22/'dat_file 1980'!E$75,4) -> 0.129 | F22: ='dat_file 1980'!F22 -> 1 | G22: ='dat_file 1980'!G22 -> 1 | H22: =ROUND('dat_file 1980'!H22/'dat_file 1980'!H$75,4) -> 0.2286 | I22: =ROUND('dat_file 1980'!J22/'dat_file 1980'!J$75,4) -> 0.2016 | K22: ="ELSE IF ref_year="&'dat_file 1980'!B22&" THEN cpi_u_rs_18="&ROUND('dat_file 1980'!$D$73/'dat_file 1980'!D22,3)&";" -> ELSE IF ref_year=1967 THEN cpi_u_rs_18=6.579; | O22: ="ELSE IF ref_year="&'dat_file 1980'!B22&" THEN cpi_u_rs_adj_18="&ROUND('dat_file 1980'!$H$73/'dat_file 1980'!H22,3)&";" -> ELSE IF ref_year=1967 THEN cpi_u_rs_adj_18=4.308;
B23: =+Sheet3!A23 -> 1968 | C23: =ROUND('dat_file 1980'!C23/'dat_file 1980'!C$75,4) -> 0.172 | D23: =ROUND('dat_file 1980'!D23/'dat_file 1980'!D$75,4) -> 0.1531 | E23: =ROUND('dat_file 1980'!E23/'dat_file 1980'!E$75,4) -> 0.1345 | F23: ='dat_file 1980'!F23 -> 0.9623 | G23: ='dat_file 1980'!G23 -> 0.9598 | H23: =ROUND('dat_file 1980'!H23/'dat_file 1980'!H$75,4) -> 0.235 | I23: =ROUND('dat_file 1980'!J23/'dat_file 1980'!J$75,4) -> 0.2073 | K23: ="ELSE IF ref_year="&'dat_file 1980'!B23&" THEN cpi_u_rs_18="&ROUND('dat_file 1980'!$D$73/'dat_file 1980'!D23,3)&";" -> ELSE IF ref_year=1968 THEN cpi_u_rs_18=6.331; | O23: ="ELSE IF ref_year="&'dat_file 1980'!B23&" THEN cpi_u_rs_adj_18="&ROUND('dat_file 1980'!$H$73/'dat_file 1980'!H23,3)&";" -> ELSE IF ref_year=1968 THEN cpi_u_rs_adj_18=4.19;
B24: =+Sheet3!A24 -> 1969 | C24: =ROUND('dat_file 1980'!C24/'dat_file 1980'!C$75,4) -> 0.1797 | D24: =ROUND('dat_file 1980'!D24/'dat_file 1980'!D$75,4) -> 0.1599 | E24: =ROUND('dat_file 1980'!E24/'dat_file 1980'!E$75,4) -> 0.1418 | F24: ='dat_file 1980'!F24 -> 0.9212 | G24: ='dat_file 1980'!G24 -> 0.9101 | H24: =ROUND('dat_file 1980'!H24/'dat_file 1980'!H$75,4) -> 0.2429 | I24: =ROUND('dat_file 1980'!J24/'dat_file 1980'!J$75,4) -> 0.2142 | K24: ="ELSE IF ref_year="&'dat_file 1980'!B24&" THEN cpi_u_rs_18="&ROUND('dat_file 1980'!$D$73/'dat_file 1980'!D24,3)&";" -> ELSE IF ref_year=1969 THEN cpi_u_rs_18=6.06; | O24: ="ELSE IF ref_year="&'dat_file 1980'!B24&" THEN cpi_u_rs_adj_18="&ROUND('dat_file 1980'!$H$73/'dat_file 1980'!H24,3)&";" -> ELSE IF ref_year=1969 THEN cpi_u_rs_adj_18=4.054;
B25: =+Sheet3!A25 -> 1970 | C25: =ROUND('dat_file 1980'!C25/'dat_file 1980'!C$75,4) -> 0.1882 | D25: =ROUND('dat_file 1980'!D25/'dat_file 1980'!D$75,4) -> 0.1678 | E25: =ROUND('dat_file 1980'!E25/'dat_file 1980'!E$75,4) -> 0.1499 | F25: ='dat_file 1980'!F25 -> 0.8779 | G25: ='dat_file 1980'!G25 -> 0.8608 | H25: =ROUND('dat_file 1980'!H25/'dat_file 1980'!H$75,4) -> 0.2522 | I25: =ROUND('dat_file 1980'!J25/'dat_file 1980'!J$75,4) -> 0.2223 | K25: ="ELSE IF ref_year="&'dat_file 1980'!B25&" THEN cpi_u_rs_18="&ROUND('dat_file 1980'!$D$73/'dat_file 1980'!D25,3)&";" -> ELSE IF ref_year=1970 THEN cpi_u_rs_18=5.776; | O25: ="ELSE IF ref_year="&'dat_file 1980'!B25&" THEN cpi_u_rs_adj_18="&ROUND('dat_file 1980'!$H$73/'dat_file 1980'!H25,3)&";" -> ELSE IF ref_year=1970 THEN cpi_u_rs_adj_18=3.904;
B26: =+Sheet3!A26 -> 1971 | C26: =ROUND('dat_file 1980'!C26/'dat_file 1980'!C$75,4) -> 0.1961 | D26: =ROUND('dat_file 1980'!D26/'dat_file 1980'!D$75,4) -> 0.1752 | E26: =ROUND('dat_file 1980'!E26/'dat_file 1980'!E$75,4) -> 0.1565 | F26: ='dat_file 1980'!F26 -> 0.8411 | G26: ='dat_file 1980'!G26 -> 0.8247 | H26: =ROUND('dat_file 1980'!H26/'dat_file 1980'!H$75,4) -> 0.2605 | I26: =ROUND('dat_file 1980'!J26/'dat_file 1980'!J$75,4) -> 0.2296 | K26: ="ELSE IF ref_year="&'dat_file 1980'!B26&" THEN cpi_u_rs_18="&ROUND('dat_file 1980'!$D$73/'dat_file 1980'!D26,3)&";" -> ELSE IF ref_year=1971 THEN cpi_u_rs_18=5.534; | O26: ="ELSE IF ref_year="&'dat_file 1980'!B26&" THEN cpi_u_rs_adj_18="&ROUND('dat_file 1980'!$H$73/'dat_file 1980'!H26,3)&";" -> ELSE IF ref_year=1971 THEN cpi_u_rs_adj_18=3.78;
B27: =+Sheet3!A27 -> 1972 | C27: =ROUND('dat_file 1980'!C27/'dat_file 1980'!C$75,4) -> 0.2028 | D27: =ROUND('dat_file 1980'!D27/'dat_file 1980'!D$75,4) -> 0.1804 | E27: =ROUND('dat_file 1980'!E27/'dat_file 1980'!E$75,4) -> 0.1615 | F27: ='dat_file 1980'!F27 -> 0.8166 | G27: ='dat_file 1980'!G27 -> 0.799 | H27: =ROUND('dat_file 1980'!H27/'dat_file 1980'!H$75,4) -> 0.2654 | I27: =ROUND('dat_file 1980'!J27/'dat_file 1980'!J$75,4) -> 0.2341 | K27: ="ELSE IF ref_year="&'dat_file 1980'!B27&" THEN cpi_u_rs_18="&ROUND('dat_file 1980'!$D$73/'dat_file 1980'!D27,3)&";" -> ELSE IF ref_year=1972 THEN cpi_u_rs_18=5.373; | O27: ="ELSE IF ref_year="&'dat_file 1980'!B27&" THEN cpi_u_rs_adj_18="&ROUND('dat_file 1980'!$H$73/'dat_file 1980'!H27,3)&";" -> ELSE IF ref_year=1972 THEN cpi_u_rs_adj_18=3.71;
... B73: =+Sheet3!A73 -> 2018 | C73: =ROUND('dat_file 1980'!C73/'dat_file 1980'!C$75,4) -> 0.9745 | D73: =ROUND('dat_file 1980'!D73/'dat_file 1980'!D$75,4) -> 0.9693 | E73: =ROUND('dat_file 1980'!E73/'dat_file 1980'!E$75,4) -> 0.9702 | F73: ='dat_file 1980'!F73 -> 0.152 | G73: ='dat_file 1980'!G73 -> 0.133 | H73: =ROUND('dat_file 1980'!H73/'dat_file 1980'!H$75,4) -> 0.9847 | I73: =ROUND('dat_file 1980'!J73/'dat_file 1980'!J$75,4) -> 0.9789 | K73: ="ELSE IF ref_year="&'dat_file 1980'!B73&" THEN cpi_u_rs_18="&ROUND('dat_file 1980'!$D$73/'dat_file 1980'!D73,3)&";" -> ELSE IF ref_year=2018 THEN cpi_u_rs_18=1; | O73: ="ELSE IF ref_year="&'dat_file 1980'!B73&" THEN cpi_u_rs_adj_18="&ROUND('dat_file 1980'!$H$73/'dat_file 1980'!H73,3)&";" -> ELSE IF ref_year=2018 THEN cpi_u_rs_adj_18=1;
B74: =+Sheet3!A74 -> 2019 | C74: =ROUND('dat_file 1980'!C74/'dat_file 1980'!C$75,4) -> 0.9891 | D74: =ROUND('dat_file 1980'!D74/'dat_file 1980'!D$75,4) -> 0.9868 | E74: =ROUND('dat_file 1980'!E74/'dat_file 1980'!E$75,4) -> 0.9878 | F74: ='dat_file 1980'!F74 -> 0.1493 | G74: ='dat_file 1980'!G74 -> 0.1306 | H74: =ROUND('dat_file 1980'!H74/'dat_file 1980'!H$75,4) -> 0.9947 | I74: =ROUND('dat_file 1980'!J74/'dat_file 1980'!J$75,4) -> 0.9919
B75: =+Sheet3!A75 -> 2020 | C75: =ROUND('dat_file 1980'!C75/'dat_file 1980'!C$75,4) -> 1 | D75: =ROUND('dat_file 1980'!D75/'dat_file 1980'!D$75,4) -> 1 | E75: =ROUND('dat_file 1980'!E75/'dat_file 1980'!E$75,4) -> 1 | F75: ='dat_file 1980'!F75 -> 0.1473 | G75: ='dat_file 1980'!G75 -> 0.1291 | H75: =ROUND('dat_file 1980'!H75/'dat_file 1980'!H$75,4) -> 1 | I75: =ROUND('dat_file 1980'!J75/'dat_file 1980'!J$75,4) -> 1
B76: =+Sheet3!A76 -> 2021 | C76: =ROUND('dat_file 1980'!C76/'dat_file 1980'!C$75,4) -> 1.0403 | D76: =ROUND('dat_file 1980'!D76/'dat_file 1980'!D$75,4) -> 1.0483 | E76: =ROUND('dat_file 1980'!E76/'dat_file 1980'!E$75,4) -> 1.047 | F76: ='dat_file 1980'!F76 -> 0.1405 | G76: ='dat_file 1980'!G76 -> 0.1233 | H76: =ROUND('dat_file 1980'!H76/'dat_file 1980'!H$75,4) -> 1.0403 | I76: =ROUND('dat_file 1980'!J76/'dat_file 1980'!J$75,4) -> 1.0434

Sheet dat_file 2021
B1: Year | C1: pce | D1: cpi-u-rs | E1: cpiu | F1: cpiu-rs67 | G1: cpiu67 | H1: cpi-u-rs adj | I1: cpi-u-rs adj03
B2: =+Sheet3!A2 -> 1947 | C2: =ROUND('dat_file 1980'!C2/'dat_file 1980'!C$76,4) -> 0.108 | D2: =ROUND('dat_file 1980'!D2/'dat_file 1980'!D$76,4) -> 0.0939 | E2: =ROUND('dat_file 1980'!E2/'dat_file 1980'!E$76,4) -> 0.0823 | F2: ='dat_file 1980'!F2 -> 1.496 | G2: ='dat_file 1980'!G2 -> 1.4978 | H2: =ROUND('dat_file 1980'!H2/'dat_file 1980'!H$76,4) -> 0.1824 | I2: =ROUND('dat_file 1980'!I2/'dat_file 1980'!I$76,4) -> 5.481
B3: =+Sheet3!A3 -> 1948 | C3: =ROUND('dat_file 1980'!C3/'dat_file 1980'!C$76,4) -> 0.1142 | D3: =ROUND('dat_file 1980'!D3/'dat_file 1980'!D$76,4) -> 0.1014 | E3: =ROUND('dat_file 1980'!E3/'dat_file 1980'!E$76,4) -> 0.0889 | F3: ='dat_file 1980'!F3 -> 1.3852 | G3: ='dat_file 1980'!G3 -> 1.3859 | H3: =ROUND('dat_file 1980'!H3/'dat_file 1980'!H$76,4) -> 0.195 | I3: =ROUND('dat_file 1980'!I3/'dat_file 1980'!I$76,4) -> 5.1273
B4: =+Sheet3!A4 -> 1949 | C4: =ROUND('dat_file 1980'!C4/'dat_file 1980'!C$76,4) -> 0.1133 | D4: =ROUND('dat_file 1980'!D4/'dat_file 1980'!D$76,4) -> 0.1002 | E4: =ROUND('dat_file 1980'!E4/'dat_file 1980'!E$76,4) -> 0.0878 | F4: ='dat_file 1980'!F4 -> 1.4025 | G4: ='dat_file 1980'!G4 -> 1.4034 | H4: =ROUND('dat_file 1980'!H4/'dat_file 1980'!H$76,4) -> 0.1905 | I4: =ROUND('dat_file 1980'!I4/'dat_file 1980'!I$76,4) -> 5.2501
B5: =+Sheet3!A5 -> 1950 | C5: =ROUND('dat_file 1980'!C5/'dat_file 1980'!C$76,4) -> 0.1146 | D5: =ROUND('dat_file 1980'!D5/'dat_file 1980'!D$76,4) -> 0.1014 | E5: =ROUND('dat_file 1980'!E5/'dat_file 1980'!E$76,4) -> 0.0889 | F5: ='dat_file 1980'!F5 -> 1.3852 | G5: ='dat_file 1980'!G5 -> 1.3859 | H5: =ROUND('dat_file 1980'!H5/'dat_file 1980'!H$76,4) -> 0.1908 | I5: =ROUND('dat_file 1980'!I5/'dat_file 1980'!I$76,4) -> 5.2416
B6: =+Sheet3!A6 -> 1951 | C6: =ROUND('dat_file 1980'!C6/'dat_file 1980'!C$76,4) -> 0.1224 | D6: =ROUND('dat_file 1980'!D6/'dat_file 1980'!D$76,4) -> 0.1095 | E6: =ROUND('dat_file 1980'!E6/'dat_file 1980'!E$76,4) -> 0.0959 | F6: ='dat_file 1980'!F6 -> 1.2838 | G6: ='dat_file 1980'!G6 -> 1.2846 | H6: =ROUND('dat_file 1980'!H6/'dat_file 1980'!H$76,4) -> 0.2037 | I6: =ROUND('dat_file 1980'!I6/'dat_file 1980'!I$76,4) -> 4.9087
B7: =+Sheet3!A7 -> 1952 | C7: =ROUND('dat_file 1980'!C7/'dat_file 1980'!C$76,4) -> 0.1249 | D7: =ROUND('dat_file 1980'!D7/'dat_file 1980'!D$76,4) -> 0.1115 | E7: =ROUND('dat_file 1980'!E7/'dat_file 1980'!E$76,4) -> 0.0978 | F7: ='dat_file 1980'!F7 -> 1.2607 | G7: ='dat_file 1980'!G7 -> 1.2604 | H7: =ROUND('dat_file 1980'!H7/'dat_file 1980'!H$76,4) -> 0.2052 | I7: =ROUND('dat_file 1980'!I7/'dat_file 1980'!I$76,4) -> 4.873
B8: =+Sheet3!A8 -> 1953 | C8: =ROUND('dat_file 1980'!C8/'dat_file 1980'!C$76,4) -> 0.1266 | D8: =ROUND('dat_file 1980'!D8/'dat_file 1980'!D$76,4) -> 0.1122 | E8: =ROUND('dat_file 1980'!E8/'dat_file 1980'!E$76,4) -> 0.0985 | F8: ='dat_file 1980'!F8 -> 1.2522 | G8: ='dat_file 1980'!G8 -> 1.2509 | H8: =ROUND('dat_file 1980'!H8/'dat_file 1980'!H$76,4) -> 0.2043 | I8: =ROUND('dat_file 1980'!I8/'dat_file 1980'!I$76,4) -> 4.894
B9: =+Sheet3!A9 -> 1954 | C9: =ROUND('dat_file 1980'!C9/'dat_file 1980'!C$76,4) -> 0.1277 | D9: =ROUND('dat_file 1980'!D9/'dat_file 1980'!D$76,4) -> 0.1132 | E9: =ROUND('dat_file 1980'!E9/'dat_file 1980'!E$76,4) -> 0.0993 | F9: ='dat_file 1980'!F9 -> 1.2412 | G9: ='dat_file 1980'!G9 -> 1.2416 | H9: =ROUND('dat_file 1980'!H9/'dat_file 1980'!H$76,4) -> 0.2039 | I9: =ROUND('dat_file 1980'!I9/'dat_file 1980'!I$76,4) -> 4.9034
B10: =+Sheet3!A10 -> 1955 | C10: =ROUND('dat_file 1980'!C10/'dat_file 1980'!C$76,4) -> 0.1282 | D10: =ROUND('dat_file 1980'!D10/'dat_file 1980'!D$76,4) -> 0.1127 | E10: =ROUND('dat_file 1980'!E10/'dat_file 1980'!E$76,4) -> 0.0989 | F10: ='dat_file 1980'!F10 -> 1.2467 | G10: ='dat_file 1980'!G10 -> 1.2463 | H10: =ROUND('dat_file 1980'!H10/'dat_file 1980'!H$76,4) -> 0.2008 | I10: =ROUND('dat_file 1980'!I10/'dat_file 1980'!I$76,4) -> 4.9806
B11: =+Sheet3!A11 -> 1956 | C11: =ROUND('dat_file 1980'!C11/'dat_file 1980'!C$76,4) -> 0.1307 | D11: =ROUND('dat_file 1980'!D11/'dat_file 1980'!D$76,4) -> 0.1145 | E11: =ROUND('dat_file 1980'!E11/'dat_file 1980'!E$76,4) -> 0.1004 | F11: ='dat_file 1980'!F11 -> 1.2276 | G11: ='dat_file 1980'!G11 -> 1.2279 | H11: =ROUND('dat_file 1980'!H11/'dat_file 1980'!H$76,4) -> 0.2017 | I11: =ROUND('dat_file 1980'!I11/'dat_file 1980'!I$76,4) -> 4.9578
B12: =+Sheet3!A12 -> 1957 | C12: =ROUND('dat_file 1980'!C12/'dat_file 1980'!C$76,4) -> 0.1347 | D12: =ROUND('dat_file 1980'!D12/'dat_file 1980'!D$76,4) -> 0.1183 | E12: =ROUND('dat_file 1980'!E12/'dat_file 1980'!E$76,4) -> 0.1037 | F12: ='dat_file 1980'!F12 -> 1.1886 | G12: ='dat_file 1980'!G12 -> 1.1886 | H12: =ROUND('dat_file 1980'!H12/'dat_file 1980'!H$76,4) -> 0.2061 | I12: =ROUND('dat_file 1980'!I12/'dat_file 1980'!I$76,4) -> 4.8523
B13: =+Sheet3!A13 -> 1958 | C13: =ROUND('dat_file 1980'!C13/'dat_file 1980'!C$76,4) -> 0.1378 | D13: =ROUND('dat_file 1980'!D13/'dat_file 1980'!D$76,4) -> 0.1215 | E13: =ROUND('dat_file 1980'!E13/'dat_file 1980'!E$76,4) -> 0.1066 | F13: ='dat_file 1980'!F13 -> 1.1567 | G13: ='dat_file 1980'!G13 -> 1.1557 | H13: =ROUND('dat_file 1980'!H13/'dat_file 1980'!H$76,4) -> 0.2095 | I13: =ROUND('dat_file 1980'!I13/'dat_file 1980'!I$76,4) -> 4.7731
B14: =+Sheet3!A14 -> 1959 | C14: =ROUND('dat_file 1980'!C14/'dat_file 1980'!C$76,4) -> 0.1399 | D14: =ROUND('dat_file 1980'!D14/'dat_file 1980'!D$76,4) -> 0.1225 | E14: =ROUND('dat_file 1980'!E14/'dat_file 1980'!E$76,4) -> 0.1074 | F14: ='dat_file 1980'!F14 -> 1.1472 | G14: ='dat_file 1980'!G14 -> 1.1478 | H14: =ROUND('dat_file 1980'!H14/'dat_file 1980'!H$76,4) -> 0.2089 | I14: =ROUND('dat_file 1980'!I14/'dat_file 1980'!I$76,4) -> 4.7861
B15: =+Sheet3!A15 -> 1960 | C15: =ROUND('dat_file 1980'!C15/'dat_file 1980'!C$76,4) -> 0.1422 | D15: =ROUND('dat_file 1980'!D15/'dat_file 1980'!D$76,4) -> 0.1245 | E15: =ROUND('dat_file 1980'!E15/'dat_file 1980'!E$76,4) -> 0.1092 | F15: ='dat_file 1980'!F15 -> 1.1288 | G15: ='dat_file 1980'!G15 -> 1.1284 | H15: =ROUND('dat_file 1980'!H15/'dat_file 1980'!H$76,4) -> 0.21 | I15: =ROUND('dat_file 1980'!I15/'dat_file 1980'!I$76,4) -> 4.7611 | K15: ="IF ref_year="&'dat_file 1980'!B15&" THEN cpi_u_rs_18="&ROUND('dat_file 1980'!$D$73/'dat_file 1980'!D15,3)&";" -> IF ref_year=1960 THEN cpi_u_rs_18=7.427; | O15: ="IF ref_year="&'dat_file 1980'!B15&" THEN cpi_u_rs_adj_18="&ROUND('dat_file 1980'!$H$73/'dat_file 1980'!H15,3)&";" -> IF ref_year=1960 THEN cpi_u_rs_adj_18=4.507;
B16: =+Sheet3!A16 -> 1961 | C16: =ROUND('dat_file 1980'!C16/'dat_file 1980'!C$76,4) -> 0.1437 | D16: =ROUND('dat_file 1980'!D16/'dat_file 1980'!D$76,4) -> 0.1258 | E16: =ROUND('dat_file 1980'!E16/'dat_file 1980'!E$76,4) -> 0.1104 | F16: ='dat_file 1980'!F16 -> 1.1175 | G16: ='dat_file 1980'!G16 -> 1.1171 | H16: =ROUND('dat_file 1980'!H16/'dat_file 1980'!H$76,4) -> 0.2099 | I16: =ROUND('dat_file 1980'!I16/'dat_file 1980'!I$76,4) -> 4.7651 | K16: ="ELSE IF ref_year="&'dat_file 1980'!B16&" THEN cpi_u_rs_18="&ROUND('dat_file 1980'!$D$73/'dat_file 1980'!D16,3)&";" -> ELSE IF ref_year=1961 THEN cpi_u_rs_18=7.352; | O16: ="ELSE IF ref_year="&'dat_file 1980'!B16&" THEN cpi_u_rs_adj_18="&ROUND('dat_file 1980'!$H$73/'dat_file 1980'!H16,3)&";" -> ELSE IF ref_year=1961 THEN cpi_u_rs_adj_18=4.511;
B17: =+Sheet3!A17 -> 1962 | C17: =ROUND('dat_file 1980'!C17/'dat_file 1980'!C$76,4) -> 0.1454 | D17: =ROUND('dat_file 1980'!D17/'dat_file 1980'!D$76,4) -> 0.127 | E17: =ROUND('dat_file 1980'!E17/'dat_file 1980'!E$76,4) -> 0.1114 | F17: ='dat_file 1980'!F17 -> 1.1065 | G17: ='dat_file 1980'!G17 -> 1.106 | H17: =ROUND('dat_file 1980'!H17/'dat_file 1980'!H$76,4) -> 0.2096 | I17: =ROUND('dat_file 1980'!I17/'dat_file 1980'!I$76,4) -> 4.7701 | K17: ="ELSE IF ref_year="&'dat_file 1980'!B17&" THEN cpi_u_rs_18="&ROUND('dat_file 1980'!$D$73/'dat_file 1980'!D17,3)&";" -> ELSE IF ref_year=1962 THEN cpi_u_rs_18=7.28; | O17: ="ELSE IF ref_year="&'dat_file 1980'!B17&" THEN cpi_u_rs_adj_18="&ROUND('dat_file 1980'!$H$73/'dat_file 1980'!H17,3)&";" -> ELSE IF ref_year=1962 THEN cpi_u_rs_adj_18=4.515;
B18: =+Sheet3!A18 -> 1963 | C18: =ROUND('dat_file 1980'!C18/'dat_file 1980'!C$76,4) -> 0.1471 | D18: =ROUND('dat_file 1980'!D18/'dat_file 1980'!D$76,4) -> 0.1288 | E18: =ROUND('dat_file 1980'!E18/'dat_file 1980'!E$76,4) -> 0.1129 | F18: ='dat_file 1980'!F18 -> 1.0914 | G18: ='dat_file 1980'!G18 -> 1.0915 | H18: =ROUND('dat_file 1980'!H18/'dat_file 1980'!H$76,4) -> 0.2102 | I18: =ROUND('dat_file 1980'!I18/'dat_file 1980'!I$76,4) -> 4.7571 | K18: ="ELSE IF ref_year="&'dat_file 1980'!B18&" THEN cpi_u_rs_18="&ROUND('dat_file 1980'!$D$73/'dat_file 1980'!D18,3)&";" -> ELSE IF ref_year=1963 THEN cpi_u_rs_18=7.181; | O18: ="ELSE IF ref_year="&'dat_file 1980'!B18&" THEN cpi_u_rs_adj_18="&ROUND('dat_file 1980'!$H$73/'dat_file 1980'!H18,3)&";" -> ELSE IF ref_year=1963 THEN cpi_u_rs_adj_18=4.503;
B19: =+Sheet3!A19 -> 1964 | C19: =ROUND('dat_file 1980'!C19/'dat_file 1980'!C$76,4) -> 0.1492 | D19: =ROUND('dat_file 1980'!D19/'dat_file 1980'!D$76,4) -> 0.1305 | E19: =ROUND('dat_file 1980'!E19/'dat_file 1980'!E$76,4) -> 0.1144 | F19: ='dat_file 1980'!F19 -> 1.0768 | G19: ='dat_file 1980'!G19 -> 1.0774 | H19: =ROUND('dat_file 1980'!H19/'dat_file 1980'!H$76,4) -> 0.2108 | I19: =ROUND('dat_file 1980'!I19/'dat_file 1980'!I$76,4) -> 4.7443 | K19: ="ELSE IF ref_year="&'dat_file 1980'!B19&" THEN cpi_u_rs_18="&ROUND('dat_file 1980'!$D$73/'dat_file 1980'!D19,3)&";" -> ELSE IF ref_year=1964 THEN cpi_u_rs_18=7.085; | O19: ="ELSE IF ref_year="&'dat_file 1980'!B19&" THEN cpi_u_rs_adj_18="&ROUND('dat_file 1980'!$H$73/'dat_file 1980'!H19,3)&";" -> ELSE IF ref_year=1964 THEN cpi_u_rs_adj_18=4.491;
B20: =+Sheet3!A20 -> 1965 | C20: =ROUND('dat_file 1980'!C20/'dat_file 1980'!C$76,4) -> 0.1514 | D20: =ROUND('dat_file 1980'!D20/'dat_file 1980'!D$76,4) -> 0.1325 | E20: =ROUND('dat_file 1980'!E20/'dat_file 1980'!E$76,4) -> 0.1163 | F20: ='dat_file 1980'!F20 -> 1.0605 | G20: ='dat_file 1980'!G20 -> 1.0603 | H20: =ROUND('dat_file 1980'!H20/'dat_file 1980'!H$76,4) -> 0.2117 | I20: =ROUND('dat_file 1980'!I20/'dat_file 1980'!I$76,4) -> 4.7236 | K20: ="ELSE IF ref_year="&'dat_file 1980'!B20&" THEN cpi_u_rs_18="&ROUND('dat_file 1980'!$D$73/'dat_file 1980'!D20,3)&";" -> ELSE IF ref_year=1965 THEN cpi_u_rs_18=6.977; | O20: ="ELSE IF ref_year="&'dat_file 1980'!B20&" THEN cpi_u_rs_adj_18="&ROUND('dat_file 1980'!$H$73/'dat_file 1980'!H20,3)&";" -> ELSE IF ref_year=1965 THEN cpi_u_rs_adj_18=4.471;
B21: =+Sheet3!A21 -> 1966 | C21: =ROUND('dat_file 1980'!C21/'dat_file 1980'!C$76,4) -> 0.1552 | D21: =ROUND('dat_file 1980'!D21/'dat_file 1980'!D$76,4) -> 0.1363 | E21: =ROUND('dat_file 1980'!E21/'dat_file 1980'!E$76,4) -> 0.1196 | F21: ='dat_file 1980'!F21 -> 1.0313 | G21: ='dat_file 1980'!G21 -> 1.0309 | H21: =ROUND('dat_file 1980'!H21/'dat_file 1980'!H$76,4) -> 0.2154 | I21: =ROUND('dat_file 1980'!I21/'dat_file 1980'!I$76,4) -> 4.6428 | K21: ="ELSE IF ref_year="&'dat_file 1980'!B21&" THEN cpi_u_rs_18="&ROUND('dat_file 1980'!$D$73/'dat_file 1980'!D21,3)&";" -> ELSE IF ref_year=1966 THEN cpi_u_rs_18=6.785; | O21: ="ELSE IF ref_year="&'dat_file 1980'!B21&" THEN cpi_u_rs_adj_18="&ROUND('dat_file 1980'!$H$73/'dat_file 1980'!H21,3)&";" -> ELSE IF ref_year=1966 THEN cpi_u_rs_adj_18=4.395;
B22: =+Sheet3!A22 -> 1967 | C22: =ROUND('dat_file 1980'!C22/'dat_file 1980'!C$76,4) -> 0.1591 | D22: =ROUND('dat_file 1980'!D22/'dat_file 1980'!D$76,4) -> 0.1405 | E22: =ROUND('dat_file 1980'!E22/'dat_file 1980'!E$76,4) -> 0.1232 | F22: ='dat_file 1980'!F22 -> 1 | G22: ='dat_file 1980'!G22 -> 1 | H22: =ROUND('dat_file 1980'!H22/'dat_file 1980'!H$76,4) -> 0.2197 | I22: =ROUND('dat_file 1980'!I22/'dat_file 1980'!I$76,4) -> 4.5511 | K22: ="ELSE IF ref_year="&'dat_file 1980'!B22&" THEN cpi_u_rs_18="&ROUND('dat_file 1980'!$D$73/'dat_file 1980'!D22,3)&";" -> ELSE IF ref_year=1967 THEN cpi_u_rs_18=6.579; | O22: ="ELSE IF ref_year="&'dat_file 1980'!B22&" THEN cpi_u_rs_adj_18="&ROUND('dat_file 1980'!$H$73/'dat_file 1980'!H22,3)&";" -> ELSE IF ref_year=1967 THEN cpi_u_rs_adj_18=4.308;
B23: =+Sheet3!A23 -> 1968 | C23: =ROUND('dat_file 1980'!C23/'dat_file 1980'!C$76,4) -> 0.1653 | D23: =ROUND('dat_file 1980'!D23/'dat_file 1980'!D$76,4) -> 0.146 | E23: =ROUND('dat_file 1980'!E23/'dat_file 1980'!E$76,4) -> 0.1284 | F23: ='dat_file 1980'!F23 -> 0.9623 | G23: ='dat_file 1980'!G23 -> 0.9598 | H23: =ROUND('dat_file 1980'!H23/'dat_file 1980'!H$76,4) -> 0.2259 | I23: =ROUND('dat_file 1980'!I23/'dat_file 1980'!I$76,4) -> 4.4265 | K23: ="ELSE IF ref_year="&'dat_file 1980'!B23&" THEN cpi_u_rs_18="&ROUND('dat_file 1980'!$D$73/'dat_file 1980'!D23,3)&";" -> ELSE IF ref_year=1968 THEN cpi_u_rs_18=6.331; | O23: ="ELSE IF ref_year="&'dat_file 1980'!B23&" THEN cpi_u_rs_adj_18="&ROUND('dat_file 1980'!$H$73/'dat_file 1980'!H23,3)&";" -> ELSE IF ref_year=1968 THEN cpi_u_rs_adj_18=4.19;
B24: =+Sheet3!A24 -> 1969 | C24: =ROUND('dat_file 1980'!C24/'dat_file 1980'!C$76,4) -> 0.1728 | D24: =ROUND('dat_file 1980'!D24/'dat_file 1980'!D$76,4) -> 0.1526 | E24: =ROUND('dat_file 1980'!E24/'dat_file 1980'!E$76,4) -> 0.1354 | F24: ='dat_file 1980'!F24 -> 0.9212 | G24: ='dat_file 1980'!G24 -> 0.9101 | H24: =ROUND('dat_file 1980'!H24/'dat_file 1980'!H$76,4) -> 0.2335 | I24: =ROUND('dat_file 1980'!I24/'dat_file 1980'!I$76,4) -> 4.2827 | K24: ="ELSE IF ref_year="&'dat_file 1980'!B24&" THEN cpi_u_rs_18="&ROUND('dat_file 1980'!$D$73/'dat_file 1980'!D24,3)&";" -> ELSE IF ref_year=1969 THEN cpi_u_rs_18=6.06; | O24: ="ELSE IF ref_year="&'dat_file 1980'!B24&" THEN cpi_u_rs_adj_18="&ROUND('dat_file 1980'!$H$73/'dat_file 1980'!H24,3)&";" -> ELSE IF ref_year=1969 THEN cpi_u_rs_adj_18=4.054;
B25: =+Sheet3!A25 -> 1970 | C25: =ROUND('dat_file 1980'!C25/'dat_file 1980'!C$76,4) -> 0.1809 | D25: =ROUND('dat_file 1980'!D25/'dat_file 1980'!D$76,4) -> 0.1601 | E25: =ROUND('dat_file 1980'!E25/'dat_file 1980'!E$76,4) -> 0.1432 | F25: ='dat_file 1980'!F25 -> 0.8779 | G25: ='dat_file 1980'!G25 -> 0.8608 | H25: =ROUND('dat_file 1980'!H25/'dat_file 1980'!H$76,4) -> 0.2424 | I25: =ROUND('dat_file 1980'!I25/'dat_file 1980'!I$76,4) -> 4.1246 | K25: ="ELSE IF ref_year="&'dat_file 1980'!B25&" THEN cpi_u_rs_18="&ROUND('dat_file 1980'!$D$73/'dat_file 1980'!D25,3)&";" -> ELSE IF ref_year=1970 THEN cpi_u_rs_18=5.776; | O25: ="ELSE IF ref_year="&'dat_file 1980'!B25&" THEN cpi_u_rs_adj_18="&ROUND('dat_file 1980'!$H$73/'dat_file 1980'!H25,3)&";" -> ELSE IF ref_year=1970 THEN cpi_u_rs_adj_18=3.904;
B26: =+Sheet3!A26 -> 1971 | C26: =ROUND('dat_file 1980'!C26/'dat_file 1980'!C$76,4) -> 0.1885 | D26: =ROUND('dat_file 1980'!D26/'dat_file 1980'!D$76,4) -> 0.1671 | E26: =ROUND('dat_file 1980'!E26/'dat_file 1980'!E$76,4) -> 0.1495 | F26: ='dat_file 1980'!F26 -> 0.8411 | G26: ='dat_file 1980'!G26 -> 0.8247 | H26: =ROUND('dat_file 1980'!H26/'dat_file 1980'!H$76,4) -> 0.2504 | I26: =ROUND('dat_file 1980'!I26/'dat_file 1980'!I$76,4) -> 3.9932 | K26: ="ELSE IF ref_year="&'dat_file 1980'!B26&" THEN cpi_u_rs_18="&ROUND('dat_file 1980'!$D$73/'dat_file 1980'!D26,3)&";" -> ELSE IF ref_year=1971 THEN cpi_u_rs_18=5.534; | O26: ="ELSE IF ref_year="&'dat_file 1980'!B26&" THEN cpi_u_rs_adj_18="&ROUND('dat_file 1980'!$H$73/'dat_file 1980'!H26,3)&";" -> ELSE IF ref_year=1971 THEN cpi_u_rs_adj_18=3.78;
B27: =+Sheet3!A27 -> 1972 | C27: =ROUND('dat_file 1980'!C27/'dat_file 1980'!C$76,4) -> 0.195 | D27: =ROUND('dat_file 1980'!D27/'dat_file 1980'!D$76,4) -> 0.1721 | E27: =ROUND('dat_file 1980'!E27/'dat_file 1980'!E$76,4) -> 0.1543 | F27: ='dat_file 1980'!F27 -> 0.8166 | G27: ='dat_file 1980'!G27 -> 0.799 | H27: =ROUND('dat_file 1980'!H27/'dat_file 1980'!H$76,4) -> 0.2552 | I27: =ROUND('dat_file 1980'!I27/'dat_file 1980'!I$76,4) -> 3.919 | K27: ="ELSE IF ref_year="&'dat_file 1980'!B27&" THEN cpi_u_rs_18="&ROUND('dat_file 1980'!$D$73/'dat_file 1980'!D27,3)&";" -> ELSE IF ref_year=1972 THEN cpi_u_rs_18=5.373; | O27: ="ELSE IF ref_year="&'dat_file 1980'!B27&" THEN cpi_u_rs_adj_18="&ROUND('dat_file 1980'!$H$73/'dat_file 1980'!H27,3)&";" -> ELSE IF ref_year=1972 THEN cpi_u_rs_adj_18=3.71;
... B73: =+Sheet3!A73 -> 2018 | C73: =ROUND('dat_file 1980'!C73/'dat_file 1980'!C$76,4) -> 0.9368 | D73: =ROUND('dat_file 1980'!D73/'dat_file 1980'!D$76,4) -> 0.9246 | E73: =ROUND('dat_file 1980'!E73/'dat_file 1980'!E$76,4) -> 0.9267 | F73: ='dat_file 1980'!F73 -> 0.152 | G73: ='dat_file 1980'!G73 -> 0.133 | H73: =ROUND('dat_file 1980'!H73/'dat_file 1980'!H$76,4) -> 0.9466 | I73: =ROUND('dat_file 1980'!I73/'dat_file 1980'!I$76,4) -> 1.0564 | K73: ="ELSE IF ref_year="&'dat_file 1980'!B73&" THEN cpi_u_rs_18="&ROUND('dat_file 1980'!$D$73/'dat_file 1980'!D73,3)&";" -> ELSE IF ref_year=2018 THEN cpi_u_rs_18=1; | O73: ="ELSE IF ref_year="&'dat_file 1980'!B73&" THEN cpi_u_rs_adj_18="&ROUND('dat_file 1980'!$H$73/'dat_file 1980'!H73,3)&";" -> ELSE IF ref_year=2018 THEN cpi_u_rs_adj_18=1;
B74: =+Sheet3!A74 -> 2019 | C74: =ROUND('dat_file 1980'!C74/'dat_file 1980'!C$76,4) -> 0.9508 | D74: =ROUND('dat_file 1980'!D74/'dat_file 1980'!D$76,4) -> 0.9414 | E74: =ROUND('dat_file 1980'!E74/'dat_file 1980'!E$76,4) -> 0.9435 | F74: ='dat_file 1980'!F74 -> 0.1493 | G74: ='dat_file 1980'!G74 -> 0.1306 | H74: =ROUND('dat_file 1980'!H74/'dat_file 1980'!H$76,4) -> 0.9562 | I74: =ROUND('dat_file 1980'!I74/'dat_file 1980'!I$76,4) -> 1.0458
B75: =+Sheet3!A75 -> 2020 | C75: =ROUND('dat_file 1980'!C75/'dat_file 1980'!C$76,4) -> 0.9613 | D75: =ROUND('dat_file 1980'!D75/'dat_file 1980'!D$76,4) -> 0.9539 | E75: =ROUND('dat_file 1980'!E75/'dat_file 1980'!E$76,4) -> 0.9551 | F75: ='dat_file 1980'!F75 -> 0.1473 | G75: ='dat_file 1980'!G75 -> 0.1291 | H75: =ROUND('dat_file 1980'!H75/'dat_file 1980'!H$76,4) -> 0.9613 | I75: =ROUND('dat_file 1980'!I75/'dat_file 1980'!I$76,4) -> 1.0403
B76: =+Sheet3!A76 -> 2021 | C76: =ROUND('dat_file 1980'!C76/'dat_file 1980'!C$76,4) -> 1 | D76: =ROUND('dat_file 1980'!D76/'dat_file 1980'!D$76,4) -> 1 | E76: =ROUND('dat_file 1980'!E76/'dat_file 1980'!E$76,4) -> 1 | F76: ='dat_file 1980'!F76 -> 0.1405 | G76: ='dat_file 1980'!G76 -> 0.1233 | H76: =ROUND('dat_file 1980'!H76/'dat_file 1980'!H$76,4) -> 1 | I76: =ROUND('dat_file 1980'!I76/'dat_file 1980'!I$76,4) -> 1

Sheet compare cpi-u to cpi-u-rs
F6: cpi-u-rs | G6: % chg | I6: cpiu | J6: % chg
E7: 1947 | F7: ='CPI-U-RS'!D7 -> 37.5 | I7: 22.3
E8: 1948 | F8: ='CPI-U-RS'!D8 -> 40.5 | G8: =+F8/F7-1 -> 0.08 | I8: 24.1 | J8: =+I8/I7-1 -> 0.080717489
E9: 1949 | F9: ='CPI-U-RS'!D9 -> 40 | G9: =+F9/F8-1 -> -0.012345679 | I9: 23.8 | J9: =+I9/I8-1 -> -0.012448133
E10: 1950 | F10: ='CPI-U-RS'!D10 -> 40.5 | G10: =+F10/F9-1 -> 0.0125 | I10: 24.1 | J10: =+I10/I9-1 -> 0.012605042
E11: 1951 | F11: ='CPI-U-RS'!D11 -> 43.7 | G11: =+F11/F10-1 -> 0.079012346 | I11: 26 | J11: =+I11/I10-1 -> 0.078838174
E12: 1952 | F12: ='CPI-U-RS'!D12 -> 44.5 | G12: =+F12/F11-1 -> 0.018306636 | I12: 26.5 | J12: =+I12/I11-1 -> 0.019230769
E13: 1953 | F13: ='CPI-U-RS'!D13 -> 44.8 | G13: =+F13/F12-1 -> 0.006741573 | I13: 26.7 | J13: =+I13/I12-1 -> 0.0075471698
E14: 1954 | F14: ='CPI-U-RS'!D14 -> 45.2 | G14: =+F14/F13-1 -> 0.0089285714 | I14: 26.9 | J14: =+I14/I13-1 -> 0.0074906367
E15: 1955 | F15: ='CPI-U-RS'!D15 -> 45 | G15: =+F15/F14-1 -> -0.0044247788 | I15: 26.8 | J15: =+I15/I14-1 -> -0.0037174721
E16: 1956 | F16: ='CPI-U-RS'!D16 -> 45.7 | G16: =+F16/F15-1 -> 0.015555556 | I16: 27.2 | J16: =+I16/I15-1 -> 0.014925373
E17: 1957 | F17: ='CPI-U-RS'!D17 -> 47.2 | G17: =+F17/F16-1 -> 0.032822757 | I17: 28.1 | J17: =+I17/I16-1 -> 0.033088235
E18: 1958 | F18: ='CPI-U-RS'!D18 -> 48.5 | G18: =+F18/F17-1 -> 0.027542373 | I18: 28.9 | J18: =+I18/I17-1 -> 0.028469751
E19: 1959 | F19: ='CPI-U-RS'!D19 -> 48.9 | G19: =+F19/F18-1 -> 0.0082474227 | I19: 29.1 | J19: =+I19/I18-1 -> 0.0069204152
E20: 1960 | F20: ='CPI-U-RS'!D20 -> 49.7 | G20: =+F20/F19-1 -> 0.016359918 | I20: 29.6 | J20: =+I20/I19-1 -> 0.017182131 | L20: =+G20-J20 -> -0.00082221238
E21: 1961 | F21: ='CPI-U-RS'!D21 -> 50.2 | G21: =+F21/F20-1 -> 0.010060362 | I21: 29.9 | J21: =+I21/I20-1 -> 0.010135135 | L21: =+G21-J21 -> -7.4772962e-05
E22: 1962 | F22: ='CPI-U-RS'!D22 -> 50.7 | G22: =+F22/F21-1 -> 0.0099601594 | I22: 30.2 | J22: =+I22/I21-1 -> 0.010033445 | L22: =+G22-J22 -> -7.3285454e-05
E23: 1963 | F23: ='CPI-U-RS'!D23 -> 51.4 | G23: =+F23/F22-1 -> 0.013806706 | I23: 30.6 | J23: =+I23/I22-1 -> 0.013245033 | L23: =+G23-J23 -> 0.000561673
E24: 1964 | F24: ='CPI-U-RS'!D24 -> 52.1 | G24: =+F24/F23-1 -> 0.013618677 | I24: 31 | J24: =+I24/I23-1 -> 0.013071895 | L24: =+G24-J24 -> 0.00054678162
E25: 1965 | F25: ='CPI-U-RS'!D25 -> 52.9 | G25: =+F25/F24-1 -> 0.015355086 | I25: 31.5 | J25: =+I25/I24-1 -> 0.016129032 | L25: =+G25-J25 -> -0.00077394589
E26: 1966 | F26: ='CPI-U-RS'!D26 -> 54.4 | G26: =+F26/F25-1 -> 0.028355388 | I26: 32.4 | J26: =+I26/I25-1 -> 0.028571429 | L26: =+G26-J26 -> -0.00021604105
E27: 1967 | F27: ='CPI-U-RS'!D27 -> 56.1 | G27: =+F27/F26-1 -> 0.03125 | I27: 33.4 | J27: =+I27/I26-1 -> 0.030864198 | L27: =+G27-J27 -> 0.00038580247
E28: 1968 | F28: ='CPI-U-RS'!D28 -> 58.3 | G28: =+F28/F27-1 -> 0.039215686 | I28: 34.8 | J28: =+I28/I27-1 -> 0.041916168 | L28: =+G28-J28 -> -0.0027004814
E29: 1969 | F29: ='CPI-U-RS'!D29 -> 60.9 | G29: =+F29/F28-1 -> 0.044596913 | I29: 36.7 | J29: =+I29/I28-1 -> 0.054597701 | L29: =+G29-J29 -> -0.010000789
E30: 1970 | F30: ='CPI-U-RS'!D30 -> 63.9 | G30: =+F30/F29-1 -> 0.049261084 | H30: =AVERAGE(G20:G29) -> 0.02225789 | I30: 38.8 | J30: =+I30/I29-1 -> 0.057220708 | K30: =AVERAGE(J20:J29) -> 0.023574617 | L30: =+H30-K30 -> -0.0013167271
E31: 1971 | F31: ='CPI-U-RS'!D31 -> 66.7 | G31: =+F31/F30-1 -> 0.043818466 | I31: 40.5 | J31: =+I31/I30-1 -> 0.043814433 | L31: =+G31-J31 -> 4.033364e-06
E32: 1972 | F32: ='CPI-U-RS'!D32 -> 68.7 | G32: =+F32/F31-1 -> 0.029985007 | I32: 41.8 | J32: =+I32/I31-1 -> 0.032098765 | L32: =+G32-J32 -> -0.0021137579
E33: 1973 | F33: ='CPI-U-RS'!D33 -> 73 | G33: =+F33/F32-1 -> 0.062590975 | I33: 44.4 | J33: =+I33/I32-1 -> 0.062200957 | L33: =+G33-J33 -> 0.00039001832
E34: 1974 | F34: ='CPI-U-RS'!D34 -> 80.3 | G34: =+F34/F33-1 -> 0.1 | I34: 49.3 | J34: =+I34/I33-1 -> 0.11036036 | L34: =+G34-J34 -> -0.01036036
E35: 1975 | F35: ='CPI-U-RS'!D35 -> 86.9 | G35: =+F35/F34-1 -> 0.082191781 | I35: 53.8 | J35: =+I35/I34-1 -> 0.09127789 | L35: =+G35-J35 -> -0.0090861096
E36: 1976 | F36: ='CPI-U-RS'!D36 -> 91.9 | G36: =+F36/F35-1 -> 0.057537399 | I36: 56.9 | J36: =+I36/I35-1 -> 0.057620818 | L36: =+G36-J36 -> -8.3418534e-05
E37: 1977 | F37: ='CPI-U-RS'!D37 -> 97.7 | G37: =+F37/F36-1 -> 0.063112078 | I37: 60.6 | J37: =+I37/I36-1 -> 0.065026362 | L37: =+G37-J37 -> -0.0019142837 | M37: =AVERAGE(L30:L33) -> -0.00075910833
E38: 1978 | F38: ='CPI-U-RS'!D38 -> 104.4 | G38: =+F38/F37-1 -> 0.068577277 | I38: 65.2 | J38: =+I38/I37-1 -> 0.075907591 | L38: =+G38-J38 -> -0.0073303134
E39: 1979 | F39: ='CPI-U-RS'!D39 -> 114.3 | G39: =+F39/F38-1 -> 0.094827586 | I39: 72.6 | J39: =+I39/I38-1 -> 0.11349693 | L39: =+G39-J39 -> -0.018669346
E40: 1980 | F40: ='CPI-U-RS'!D40 -> 127.1 | G40: =+F40/F39-1 -> 0.111986 | H40: =AVERAGE(G30:G39) -> 0.065190165 | I40: 82.4 | J40: =+I40/I39-1 -> 0.13498623 | K40: =AVERAGE(J30:J39) -> 0.070902482 | L40: =+H40-K40 -> -0.0057123163
E41: 1981 | F41: ='CPI-U-RS'!D41 -> 139.1 | G41: =+F41/F40-1 -> 0.094413847 | I41: 90.9 | J41: =+I41/I40-1 -> 0.10315534
E42: 1982 | F42: ='CPI-U-RS'!D42 -> 147.5 | G42: =+F42/F41-1 -> 0.06038821 | I42: 96.5 | J42: =+I42/I41-1 -> 0.061606161
E43: 1983 | F43: ='CPI-U-RS'!D43 -> 153.8 | G43: =+F43/F42-1 -> 0.042711864 | I43: 99.6 | J43: =+I43/I42-1 -> 0.032124352
E44: 1984 | F44: ='CPI-U-RS'!D44 -> 160.2 | G44: =+F44/F43-1 -> 0.041612484 | I44: 103.9 | J44: =+I44/I43-1 -> 0.043172691
E45: 1985 | F45: ='CPI-U-RS'!D45 -> 165.6 | G45: =+F45/F44-1 -> 0.033707865 | I45: 107.6 | J45: =+I45/I44-1 -> 0.035611165
E46: 1986 | F46: ='CPI-U-RS'!D46 -> 168.4 | G46: =+F46/F45-1 -> 0.016908213 | I46: 109.6 | J46: =+I46/I45-1 -> 0.018587361
E47: 1987 | F47: ='CPI-U-RS'!D47 -> 174.1 | G47: =+F47/F46-1 -> 0.033847981 | I47: 113.6 | J47: =+I47/I46-1 -> 0.03649635
E48: 1988 | F48: ='CPI-U-RS'!D48 -> 180.5 | G48: =+F48/F47-1 -> 0.036760482 | I48: 118.3 | J48: =+I48/I47-1 -> 0.041373239
E49: 1989 | F49: ='CPI-U-RS'!D49 -> 188.3 | G49: =+F49/F48-1 -> 0.043213296 | I49: 124 | J49: =+I49/I48-1 -> 0.048182587
E50: 1990 | F50: ='CPI-U-RS'!D50 -> 197.6 | G50: =+F50/F49-1 -> 0.049389272 | H50: =AVERAGE(G40:G49) -> 0.051555024 | I50: 130.7 | J50: =+I50/I49-1 -> 0.054032258 | K50: =AVERAGE(J40:J49) -> 0.055529547 | L50: =+H50-K50 -> -0.0039745226
E51: 1991 | F51: ='CPI-U-RS'!D51 -> 204.8 | G51: =+F51/F50-1 -> 0.036437247 | I51: 136.2 | J51: =+I51/I50-1 -> 0.042081102
E52: 1992 | F52: ='CPI-U-RS'!D52 -> 209.9 | G52: =+F52/F51-1 -> 0.024902344 | I52: 140.3 | J52: =+I52/I51-1 -> 0.03010279
E53: 1993 | F53: ='CPI-U-RS'!D53 -> 215.2 | G53: =+F53/F52-1 -> 0.025250119 | I53: 144.5 | J53: =+I53/I52-1 -> 0.029935852
E54: 1994 | F54: ='CPI-U-RS'!D54 -> 219.7 | G54: =+F54/F53-1 -> 0.020910781 | I54: 148.2 | J54: =+I54/I53-1 -> 0.025605536
E55: 1995 | F55: ='CPI-U-RS'!D55 -> 225 | G55: =+F55/F54-1 -> 0.024123805 | I55: 152.4 | J55: =+I55/I54-1 -> 0.028340081
E56: 1996 | F56: ='CPI-U-RS'!D56 -> 231 | G56: =+F56/F55-1 -> 0.026666667 | I56: 156.9 | J56: =+I56/I55-1 -> 0.029527559
E57: 1997 | F57: ='CPI-U-RS'!D57 -> 236 | G57: =+F57/F56-1 -> 0.021645022 | I57: 160.5 | J57: =+I57/I56-1 -> 0.022944551 | N57: =+G57-J57 -> -0.001299529
E58: 1998 | F58: ='CPI-U-RS'!D58 -> 239.2 | G58: =+F58/F57-1 -> 0.013559322 | I58: 163 | J58: =+I58/I57-1 -> 0.015576324 | N58: =+G58-J58 -> -0.002017002
E59: 1999 | F59: ='CPI-U-RS'!D59 -> 244.2 | G59: =+F59/F58-1 -> 0.02090301 | I59: 166.6 | J59: =+I59/I58-1 -> 0.02208589 | N59: =+G59-J59 -> -0.0011828795
E60: 2000 | F60: ='CPI-U-RS'!D60 -> 252.5 | G60: =+F60/F59-1 -> 0.033988534 | H60: =AVERAGE(G50:G59) -> 0.026378759 | I60: 172.2 | J60: =+I60/I59-1 -> 0.033613445 | K60: =AVERAGE(J50:J59) -> 0.030023194 | L60: =+H60-K60 -> -0.0036444354 | N60: =+G60-J60 -> 0.00037508861
E61: 2001 | F61: ='CPI-U-RS'!D61 -> 259.7 | G61: =+F61/F60-1 -> 0.028514851 | I61: 177.1 | J61: =+I61/I60-1 -> 0.028455285 | N61: =+G61-J61 -> 5.9566932e-05
E62: 2002 | F62: ='CPI-U-RS'!D62 -> 263.8 | G62: =+F62/F61-1 -> 0.015787447 | I62: 179.9 | J62: =+I62/I61-1 -> 0.015810277 | N62: =+G62-J62 -> -2.2829626e-05
E63: 2003 | F63: ='CPI-U-RS'!D63 -> 269.8 | G63: =+F63/F62-1 -> 0.022744503 | I63: 184 | J63: =+I63/I62-1 -> 0.022790439 | N63: =+G63-J63 -> -4.5935721e-05
E64: 2004 | F64: ='CPI-U-RS'!D64 -> 277 | G64: =+F64/F63-1 -> 0.026686434 | I64: 188.9 | J64: =+I64/I63-1 -> 0.026630435 | N64: =+G64-J64 -> 5.5999613e-05
E65: 2005 | F65: ='CPI-U-RS'!D65 -> 286.4 | G65: =+F65/F64-1 -> 0.033935018 | I65: 195.3 | J65: =+I65/I64-1 -> 0.03388036 | N65: =+G65-J65 -> 5.4658072e-05
H66: =AVERAGE(G60:G65) -> 0.026942798 | K66: =AVERAGE(J60:J65) -> 0.026863373 | L66: =+H66-K66 -> 7.9424647e-05
E67: =COUNT(E30:E65) -> 36 | G67: =AVERAGE(G20:G65) -> 0.039466852 | J67: =AVERAGE(J20:J65) -> 0.04264084
E68: =2005-1960 -> 45 | H68: =2005-1960 -> 45 | J68: =+G67-J67 -> -0.0031739884
F69: =(LN(F65)-LN(F20))/E68 -> 0.038919656 | I69: =(LN(I65)-LN(I20))/H68 -> 0.041928055 | J69: =+F69-I69 -> -0.0030083994

Sheet dat_file 1994
B1: Year | C1: pce | D1: cpi-u-rs | E1: cpiu | F1: cpiu-rs67 | G1: cpiu67 | H1: cpi-u-rs adj | I1: N_cpi-u-rs adj | J1: cpi-u-rs adj03
B2: =+Sheet3!A2 -> 1947 | C2: =ROUND('dat_file 1980'!C2/'dat_file 1980'!C$49,4) -> 0.1779 | D2: =ROUND('dat_file 1980'!D2/'dat_file 1980'!D$49,4) -> 0.1707 | E2: =ROUND('dat_file 1980'!E2/'dat_file 1980'!E$49,4) -> 0.1505 | F2: ='dat_file 1980'!F2 -> 1.496 | G2: ='dat_file 1980'!G2 -> 1.4978 | H2: =ROUND('dat_file 1980'!H2/'dat_file 1980'!H$49,4) -> 0.2681 | I2: =1/H2 -> 3.7299515 | J2: =ROUND('dat_file 1980'!J2/'dat_file 1980'!J$49,4) -> 0.2556
B3: =+Sheet3!A3 -> 1948 | C3: =ROUND('dat_file 1980'!C3/'dat_file 1980'!C$49,4) -> 0.188 | D3: =ROUND('dat_file 1980'!D3/'dat_file 1980'!D$49,4) -> 0.1843 | E3: =ROUND('dat_file 1980'!E3/'dat_file 1980'!E$49,4) -> 0.1626 | F3: ='dat_file 1980'!F3 -> 1.3852 | G3: ='dat_file 1980'!G3 -> 1.3859 | H3: =ROUND('dat_file 1980'!H3/'dat_file 1980'!H$49,4) -> 0.2866 | I3: =1/H3 -> 3.4891835 | J3: =ROUND('dat_file 1980'!J3/'dat_file 1980'!J$49,4) -> 0.2729
B4: =+Sheet3!A4 -> 1949 | C4: =ROUND('dat_file 1980'!C4/'dat_file 1980'!C$49,4) -> 0.1866 | D4: =ROUND('dat_file 1980'!D4/'dat_file 1980'!D$49,4) -> 0.1821 | E4: =ROUND('dat_file 1980'!E4/'dat_file 1980'!E$49,4) -> 0.1606 | F4: ='dat_file 1980'!F4 -> 1.4025 | G4: ='dat_file 1980'!G4 -> 1.4034 | H4: =ROUND('dat_file 1980'!H4/'dat_file 1980'!H$49,4) -> 0.2799 | I4: =1/H4 -> 3.5727045 | J4: =ROUND('dat_file 1980'!J4/'dat_file 1980'!J$49,4) -> 0.2667
B5: =+Sheet3!A5 -> 1950 | C5: =ROUND('dat_file 1980'!C5/'dat_file 1980'!C$49,4) -> 0.1888 | D5: =ROUND('dat_file 1980'!D5/'dat_file 1980'!D$49,4) -> 0.1843 | E5: =ROUND('dat_file 1980'!E5/'dat_file 1980'!E$49,4) -> 0.1626 | F5: ='dat_file 1980'!F5 -> 1.3852 | G5: ='dat_file 1980'!G5 -> 1.3859 | H5: =ROUND('dat_file 1980'!H5/'dat_file 1980'!H$49,4) -> 0.2804 | I5: =1/H5 -> 3.5663338 | J5: =ROUND('dat_file 1980'!J5/'dat_file 1980'!J$49,4) -> 0.2667
B6: =+Sheet3!A6 -> 1951 | C6: =ROUND('dat_file 1980'!C6/'dat_file 1980'!C$49,4) -> 0.2016 | D6: =ROUND('dat_file 1980'!D6/'dat_file 1980'!D$49,4) -> 0.1989 | E6: =ROUND('dat_file 1980'!E6/'dat_file 1980'!E$49,4) -> 0.1754 | F6: ='dat_file 1980'!F6 -> 1.2838 | G6: ='dat_file 1980'!G6 -> 1.2846 | H6: =ROUND('dat_file 1980'!H6/'dat_file 1980'!H$49,4) -> 0.2994 | I6: =1/H6 -> 3.3400134 | J6: =ROUND('dat_file 1980'!J6/'dat_file 1980'!J$49,4) -> 0.2853
B7: =+Sheet3!A7 -> 1952 | C7: =ROUND('dat_file 1980'!C7/'dat_file 1980'!C$49,4) -> 0.2058 | D7: =ROUND('dat_file 1980'!D7/'dat_file 1980'!D$49,4) -> 0.2025 | E7: =ROUND('dat_file 1980'!E7/'dat_file 1980'!E$49,4) -> 0.1788 | F7: ='dat_file 1980'!F7 -> 1.2607 | G7: ='dat_file 1980'!G7 -> 1.2604 | H7: =ROUND('dat_file 1980'!H7/'dat_file 1980'!H$49,4) -> 0.3016 | I7: =1/H7 -> 3.3156499 | J7: =ROUND('dat_file 1980'!J7/'dat_file 1980'!J$49,4) -> 0.2871
B8: =+Sheet3!A8 -> 1953 | C8: =ROUND('dat_file 1980'!C8/'dat_file 1980'!C$49,4) -> 0.2085 | D8: =ROUND('dat_file 1980'!D8/'dat_file 1980'!D$49,4) -> 0.2039 | E8: =ROUND('dat_file 1980'!E8/'dat_file 1980'!E$49,4) -> 0.1802 | F8: ='dat_file 1980'!F8 -> 1.2522 | G8: ='dat_file 1980'!G8 -> 1.2509 | H8: =ROUND('dat_file 1980'!H8/'dat_file 1980'!H$49,4) -> 0.3003 | I8: =1/H8 -> 3.3300033 | J8: =ROUND('dat_file 1980'!J8/'dat_file 1980'!J$49,4) -> 0.2859
B9: =+Sheet3!A9 -> 1954 | C9: =ROUND('dat_file 1980'!C9/'dat_file 1980'!C$49,4) -> 0.2103 | D9: =ROUND('dat_file 1980'!D9/'dat_file 1980'!D$49,4) -> 0.2057 | E9: =ROUND('dat_file 1980'!E9/'dat_file 1980'!E$49,4) -> 0.1815 | F9: ='dat_file 1980'!F9 -> 1.2412 | G9: ='dat_file 1980'!G9 -> 1.2416 | H9: =ROUND('dat_file 1980'!H9/'dat_file 1980'!H$49,4) -> 0.2997 | I9: =1/H9 -> 3.33667 | J9: =ROUND('dat_file 1980'!J9/'dat_file 1980'!J$49,4) -> 0.2853
B10: =+Sheet3!A10 -> 1955 | C10: =ROUND('dat_file 1980'!C10/'dat_file 1980'!C$49,4) -> 0.2111 | D10: =ROUND('dat_file 1980'!D10/'dat_file 1980'!D$49,4) -> 0.2048 | E10: =ROUND('dat_file 1980'!E10/'dat_file 1980'!E$49,4) -> 0.1808 | F10: ='dat_file 1980'!F10 -> 1.2467 | G10: ='dat_file 1980'!G10 -> 1.2463 | H10: =ROUND('dat_file 1980'!H10/'dat_file 1980'!H$49,4) -> 0.2951 | I10: =1/H10 -> 3.3886818 | J10: =ROUND('dat_file 1980'!J10/'dat_file 1980'!J$49,4) -> 0.2809
B11: =+Sheet3!A11 -> 1956 | C11: =ROUND('dat_file 1980'!C11/'dat_file 1980'!C$49,4) -> 0.2153 | D11: =ROUND('dat_file 1980'!D11/'dat_file 1980'!D$49,4) -> 0.208 | E11: =ROUND('dat_file 1980'!E11/'dat_file 1980'!E$49,4) -> 0.1835 | F11: ='dat_file 1980'!F11 -> 1.2276 | G11: ='dat_file 1980'!G11 -> 1.2279 | H11: =ROUND('dat_file 1980'!H11/'dat_file 1980'!H$49,4) -> 0.2964 | I11: =1/H11 -> 3.3738192 | J11: =ROUND('dat_file 1980'!J11/'dat_file 1980'!J$49,4) -> 0.2822
B12: =+Sheet3!A12 -> 1957 | C12: =ROUND('dat_file 1980'!C12/'dat_file 1980'!C$49,4) -> 0.2218 | D12: =ROUND('dat_file 1980'!D12/'dat_file 1980'!D$49,4) -> 0.2149 | E12: =ROUND('dat_file 1980'!E12/'dat_file 1980'!E$49,4) -> 0.1896 | F12: ='dat_file 1980'!F12 -> 1.1886 | G12: ='dat_file 1980'!G12 -> 1.1886 | H12: =ROUND('dat_file 1980'!H12/'dat_file 1980'!H$49,4) -> 0.3029 | I12: =1/H12 -> 3.3014196 | J12: =ROUND('dat_file 1980'!J12/'dat_file 1980'!J$49,4) -> 0.2884
B13: =+Sheet3!A13 -> 1958 | C13: =ROUND('dat_file 1980'!C13/'dat_file 1980'!C$49,4) -> 0.227 | D13: =ROUND('dat_file 1980'!D13/'dat_file 1980'!D$49,4) -> 0.2208 | E13: =ROUND('dat_file 1980'!E13/'dat_file 1980'!E$49,4) -> 0.195 | F13: ='dat_file 1980'!F13 -> 1.1567 | G13: ='dat_file 1980'!G13 -> 1.1557 | H13: =ROUND('dat_file 1980'!H13/'dat_file 1980'!H$49,4) -> 0.3079 | I13: =1/H13 -> 3.2478077 | J13: =ROUND('dat_file 1980'!J13/'dat_file 1980'!J$49,4) -> 0.2933
... B75: =+Sheet3!A75 -> 2020 | C75: =ROUND('dat_file 1980'!C75/'dat_file 1980'!C$49,4) -> 1.5834 | D75: =ROUND('dat_file 1980'!D75/'dat_file 1980'!D$49,4) -> 1.7333 | E75: =ROUND('dat_file 1980'!E75/'dat_file 1980'!E$49,4) -> 1.7464 | F75: ='dat_file 1980'!F75 -> 0.1473 | G75: ='dat_file 1980'!G75 -> 0.1291 | H75: =ROUND('dat_file 1980'!H75/'dat_file 1980'!H$49,4) -> 1.4128 | I75: =1/H75 -> 0.70781427 | J75: =ROUND('dat_file 1980'!J75/'dat_file 1980'!J$49,4) -> 1.5254

Sheet dat_file 2005
B1: Year | C1: pce | D1: cpi-u-rs | E1: cpiu | F1: cpiu-rs67 | G1: cpiu67 | H1: cpi-u-rs adj
B2: =+Sheet3!A2 -> 1947 | C2: =ROUND('dat_file 1980'!C2/'dat_file 1980'!C$60,4) -> 0.1438 | D2: =ROUND('dat_file 1980'!D2/'dat_file 1980'!D$60,4) -> 0.1309 | E2: =ROUND('dat_file 1980'!E2/'dat_file 1980'!E$60,4) -> 0.1142 | F2: ='dat_file 1980'!F2 -> 1.496 | G2: ='dat_file 1980'!G2 -> 1.4978 | H2: =ROUND('dat_file 1980'!H2/'dat_file 1980'!H$60,4) -> 0.2242
B3: =+Sheet3!A3 -> 1948 | C3: =ROUND('dat_file 1980'!C3/'dat_file 1980'!C$60,4) -> 0.1519 | D3: =ROUND('dat_file 1980'!D3/'dat_file 1980'!D$60,4) -> 0.1414 | E3: =ROUND('dat_file 1980'!E3/'dat_file 1980'!E$60,4) -> 0.1234 | F3: ='dat_file 1980'!F3 -> 1.3852 | G3: ='dat_file 1980'!G3 -> 1.3859 | H3: =ROUND('dat_file 1980'!H3/'dat_file 1980'!H$60,4) -> 0.2397
B4: =+Sheet3!A4 -> 1949 | C4: =ROUND('dat_file 1980'!C4/'dat_file 1980'!C$60,4) -> 0.1507 | D4: =ROUND('dat_file 1980'!D4/'dat_file 1980'!D$60,4) -> 0.1397 | E4: =ROUND('dat_file 1980'!E4/'dat_file 1980'!E$60,4) -> 0.1219 | F4: ='dat_file 1980'!F4 -> 1.4025 | G4: ='dat_file 1980'!G4 -> 1.4034 | H4: =ROUND('dat_file 1980'!H4/'dat_file 1980'!H$60,4) -> 0.2341
B5: =+Sheet3!A5 -> 1950 | C5: =ROUND('dat_file 1980'!C5/'dat_file 1980'!C$60,4) -> 0.1525 | D5: =ROUND('dat_file 1980'!D5/'dat_file 1980'!D$60,4) -> 0.1414 | E5: =ROUND('dat_file 1980'!E5/'dat_file 1980'!E$60,4) -> 0.1234 | F5: ='dat_file 1980'!F5 -> 1.3852 | G5: ='dat_file 1980'!G5 -> 1.3859 | H5: =ROUND('dat_file 1980'!H5/'dat_file 1980'!H$60,4) -> 0.2345
B6: =+Sheet3!A6 -> 1951 | C6: =ROUND('dat_file 1980'!C6/'dat_file 1980'!C$60,4) -> 0.1629 | D6: =ROUND('dat_file 1980'!D6/'dat_file 1980'!D$60,4) -> 0.1526 | E6: =ROUND('dat_file 1980'!E6/'dat_file 1980'!E$60,4) -> 0.1331 | F6: ='dat_file 1980'!F6 -> 1.2838 | G6: ='dat_file 1980'!G6 -> 1.2846 | H6: =ROUND('dat_file 1980'!H6/'dat_file 1980'!H$60,4) -> 0.2504
B7: =+Sheet3!A7 -> 1952 | C7: =ROUND('dat_file 1980'!C7/'dat_file 1980'!C$60,4) -> 0.1663 | D7: =ROUND('dat_file 1980'!D7/'dat_file 1980'!D$60,4) -> 0.1554 | E7: =ROUND('dat_file 1980'!E7/'dat_file 1980'!E$60,4) -> 0.1357 | F7: ='dat_file 1980'!F7 -> 1.2607 | G7: ='dat_file 1980'!G7 -> 1.2604 | H7: =ROUND('dat_file 1980'!H7/'dat_file 1980'!H$60,4) -> 0.2522
B8: =+Sheet3!A8 -> 1953 | C8: =ROUND('dat_file 1980'!C8/'dat_file 1980'!C$60,4) -> 0.1685 | D8: =ROUND('dat_file 1980'!D8/'dat_file 1980'!D$60,4) -> 0.1564 | E8: =ROUND('dat_file 1980'!E8/'dat_file 1980'!E$60,4) -> 0.1367 | F8: ='dat_file 1980'!F8 -> 1.2522 | G8: ='dat_file 1980'!G8 -> 1.2509 | H8: =ROUND('dat_file 1980'!H8/'dat_file 1980'!H$60,4) -> 0.2511
B9: =+Sheet3!A9 -> 1954 | C9: =ROUND('dat_file 1980'!C9/'dat_file 1980'!C$60,4) -> 0.1699 | D9: =ROUND('dat_file 1980'!D9/'dat_file 1980'!D$60,4) -> 0.1578 | E9: =ROUND('dat_file 1980'!E9/'dat_file 1980'!E$60,4) -> 0.1378 | F9: ='dat_file 1980'!F9 -> 1.2412 | G9: ='dat_file 1980'!G9 -> 1.2416 | H9: =ROUND('dat_file 1980'!H9/'dat_file 1980'!H$60,4) -> 0.2506
B10: =+Sheet3!A10 -> 1955 | C10: =ROUND('dat_file 1980'!C10/'dat_file 1980'!C$60,4) -> 0.1706 | D10: =ROUND('dat_file 1980'!D10/'dat_file 1980'!D$60,4) -> 0.1571 | E10: =ROUND('dat_file 1980'!E10/'dat_file 1980'!E$60,4) -> 0.1372 | F10: ='dat_file 1980'!F10 -> 1.2467 | G10: ='dat_file 1980'!G10 -> 1.2463 | H10: =ROUND('dat_file 1980'!H10/'dat_file 1980'!H$60,4) -> 0.2468
B11: =+Sheet3!A11 -> 1956 | C11: =ROUND('dat_file 1980'!C11/'dat_file 1980'!C$60,4) -> 0.1739 | D11: =ROUND('dat_file 1980'!D11/'dat_file 1980'!D$60,4) -> 0.1596 | E11: =ROUND('dat_file 1980'!E11/'dat_file 1980'!E$60,4) -> 0.1393 | F11: ='dat_file 1980'!F11 -> 1.2276 | G11: ='dat_file 1980'!G11 -> 1.2279 | H11: =ROUND('dat_file 1980'!H11/'dat_file 1980'!H$60,4) -> 0.2479
B12: =+Sheet3!A12 -> 1957 | C12: =ROUND('dat_file 1980'!C12/'dat_file 1980'!C$60,4) -> 0.1792 | D12: =ROUND('dat_file 1980'!D12/'dat_file 1980'!D$60,4) -> 0.1648 | E12: =ROUND('dat_file 1980'!E12/'dat_file 1980'!E$60,4) -> 0.1439 | F12: ='dat_file 1980'!F12 -> 1.1886 | G12: ='dat_file 1980'!G12 -> 1.1886 | H12: =ROUND('dat_file 1980'!H12/'dat_file 1980'!H$60,4) -> 0.2533
B13: =+Sheet3!A13 -> 1958 | C13: =ROUND('dat_file 1980'!C13/'dat_file 1980'!C$60,4) -> 0.1834 | D13: =ROUND('dat_file 1980'!D13/'dat_file 1980'!D$60,4) -> 0.1694 | E13: =ROUND('dat_file 1980'!E13/'dat_file 1980'!E$60,4) -> 0.148 | F13: ='dat_file 1980'!F13 -> 1.1567 | G13: ='dat_file 1980'!G13 -> 1.1557 | H13: =ROUND('dat_file 1980'!H13/'dat_file 1980'!H$60,4) -> 0.2575
... B75: =+Sheet3!A75 -> 2020 | C75: =ROUND('dat_file 1980'!C75/'dat_file 1980'!C$60,4) -> 1.2793 | D75: =ROUND('dat_file 1980'!D75/'dat_file 1980'!D$60,4) -> 1.3296 | E75: =ROUND('dat_file 1980'!E75/'dat_file 1980'!E$60,4) -> 1.3252 | F75: ='dat_file 1980'!F75 -> 0.1473 | G75: ='dat_file 1980'!G75 -> 0.1291 | H75: =ROUND('dat_file 1980'!H75/'dat_file 1980'!H$60,4) -> 1.1814

Sheet dat_file 2013
B1: Year | C1: pce | D1: cpi-u-rs | E1: cpiu | F1: cpiu-rs67 | G1: cpiu67 | H1: cpi-u-rs adj
B2: 1947 | C2: =ROUND('dat_file 1980'!C2/'dat_file 1980'!C$68,4) -> 0.1232 | D2: =ROUND('dat_file 1980'!D2/'dat_file 1980'!D$68,4) -> 0.1096 | E2: =ROUND('dat_file 1980'!E2/'dat_file 1980'!E$68,4) -> 0.0957 | F2: ='dat_file 1980'!F2 -> 1.496 | G2: ='dat_file 1980'!G2 -> 1.4978 | H2: =ROUND('dat_file 1980'!H2/'dat_file 1980'!H$68,4) -> 0.2
B3: 1948 | C3: =ROUND('dat_file 1980'!C3/'dat_file 1980'!C$68,4) -> 0.1302 | D3: =ROUND('dat_file 1980'!D3/'dat_file 1980'!D$68,4) -> 0.1184 | E3: =ROUND('dat_file 1980'!E3/'dat_file 1980'!E$68,4) -> 0.1035 | F3: ='dat_file 1980'!F3 -> 1.3852 | G3: ='dat_file 1980'!G3 -> 1.3859 | H3: =ROUND('dat_file 1980'!H3/'dat_file 1980'!H$68,4) -> 0.2137
B4: 1949 | C4: =ROUND('dat_file 1980'!C4/'dat_file 1980'!C$68,4) -> 0.1292 | D4: =ROUND('dat_file 1980'!D4/'dat_file 1980'!D$68,4) -> 0.117 | E4: =ROUND('dat_file 1980'!E4/'dat_file 1980'!E$68,4) -> 0.1022 | F4: ='dat_file 1980'!F4 -> 1.4025 | G4: ='dat_file 1980'!G4 -> 1.4034 | H4: =ROUND('dat_file 1980'!H4/'dat_file 1980'!H$68,4) -> 0.2087
B5: 1950 | C5: =ROUND('dat_file 1980'!C5/'dat_file 1980'!C$68,4) -> 0.1307 | D5: =ROUND('dat_file 1980'!D5/'dat_file 1980'!D$68,4) -> 0.1184 | E5: =ROUND('dat_file 1980'!E5/'dat_file 1980'!E$68,4) -> 0.1035 | F5: ='dat_file 1980'!F5 -> 1.3852 | G5: ='dat_file 1980'!G5 -> 1.3859 | H5: =ROUND('dat_file 1980'!H5/'dat_file 1980'!H$68,4) -> 0.2091
B6: 1951 | C6: =ROUND('dat_file 1980'!C6/'dat_file 1980'!C$68,4) -> 0.1396 | D6: =ROUND('dat_file 1980'!D6/'dat_file 1980'!D$68,4) -> 0.1278 | E6: =ROUND('dat_file 1980'!E6/'dat_file 1980'!E$68,4) -> 0.1116 | F6: ='dat_file 1980'!F6 -> 1.2838 | G6: ='dat_file 1980'!G6 -> 1.2846 | H6: =ROUND('dat_file 1980'!H6/'dat_file 1980'!H$68,4) -> 0.2233
B7: 1952 | C7: =ROUND('dat_file 1980'!C7/'dat_file 1980'!C$68,4) -> 0.1425 | D7: =ROUND('dat_file 1980'!D7/'dat_file 1980'!D$68,4) -> 0.1301 | E7: =ROUND('dat_file 1980'!E7/'dat_file 1980'!E$68,4) -> 0.1138 | F7: ='dat_file 1980'!F7 -> 1.2607 | G7: ='dat_file 1980'!G7 -> 1.2604 | H7: =ROUND('dat_file 1980'!H7/'dat_file 1980'!H$68,4) -> 0.2249
B8: 1953 | C8: =ROUND('dat_file 1980'!C8/'dat_file 1980'!C$68,4) -> 0.1444 | D8: =ROUND('dat_file 1980'!D8/'dat_file 1980'!D$68,4) -> 0.131 | E8: =ROUND('dat_file 1980'!E8/'dat_file 1980'!E$68,4) -> 0.1146 | F8: ='dat_file 1980'!F8 -> 1.2522 | G8: ='dat_file 1980'!G8 -> 1.2509 | H8: =ROUND('dat_file 1980'!H8/'dat_file 1980'!H$68,4) -> 0.2239
B9: 1954 | C9: =ROUND('dat_file 1980'!C9/'dat_file 1980'!C$68,4) -> 0.1456 | D9: =ROUND('dat_file 1980'!D9/'dat_file 1980'!D$68,4) -> 0.1322 | E9: =ROUND('dat_file 1980'!E9/'dat_file 1980'!E$68,4) -> 0.1155 | F9: ='dat_file 1980'!F9 -> 1.2412 | G9: ='dat_file 1980'!G9 -> 1.2416 | H9: =ROUND('dat_file 1980'!H9/'dat_file 1980'!H$68,4) -> 0.2235
B10: 1955 | C10: =ROUND('dat_file 1980'!C10/'dat_file 1980'!C$68,4) -> 0.1462 | D10: =ROUND('dat_file 1980'!D10/'dat_file 1980'!D$68,4) -> 0.1316 | E10: =ROUND('dat_file 1980'!E10/'dat_file 1980'!E$68,4) -> 0.115 | F10: ='dat_file 1980'!F10 -> 1.2467 | G10: ='dat_file 1980'!G10 -> 1.2463 | H10: =ROUND('dat_file 1980'!H10/'dat_file 1980'!H$68,4) -> 0.22
B11: 1956 | C11: =ROUND('dat_file 1980'!C11/'dat_file 1980'!C$68,4) -> 0.1491 | D11: =ROUND('dat_file 1980'!D11/'dat_file 1980'!D$68,4) -> 0.1336 | E11: =ROUND('dat_file 1980'!E11/'dat_file 1980'!E$68,4) -> 0.1168 | F11: ='dat_file 1980'!F11 -> 1.2276 | G11: ='dat_file 1980'!G11 -> 1.2279 | H11: =ROUND('dat_file 1980'!H11/'dat_file 1980'!H$68,4) -> 0.2211
B12: 1957 | C12: =ROUND('dat_file 1980'!C12/'dat_file 1980'!C$68,4) -> 0.1536 | D12: =ROUND('dat_file 1980'!D12/'dat_file 1980'!D$68,4) -> 0.138 | E12: =ROUND('dat_file 1980'!E12/'dat_file 1980'!E$68,4) -> 0.1206 | F12: ='dat_file 1980'!F12 -> 1.1886 | G12: ='dat_file 1980'!G12 -> 1.1886 | H12: =ROUND('dat_file 1980'!H12/'dat_file 1980'!H$68,4) -> 0.2259
B13: 1958 | C13: =ROUND('dat_file 1980'!C13/'dat_file 1980'!C$68,4) -> 0.1572 | D13: =ROUND('dat_file 1980'!D13/'dat_file 1980'!D$68,4) -> 0.1418 | E13: =ROUND('dat_file 1980'!E13/'dat_file 1980'!E$68,4) -> 0.124 | F13: ='dat_file 1980'!F13 -> 1.1567 | G13: ='dat_file 1980'!G13 -> 1.1557 | H13: =ROUND('dat_file 1980'!H13/'dat_file 1980'!H$68,4) -> 0.2296
... B75: 2020 | C75: =ROUND('dat_file 1980'!C75/'dat_file 1980'!C$68,4) -> 1.0966 | D75: =ROUND('dat_file 1980'!D75/'dat_file 1980'!D$68,4) -> 1.1135 | E75: =ROUND('dat_file 1980'!E75/'dat_file 1980'!E$68,4) -> 1.111 | F75: ='dat_file 1980'!F75 -> 0.1473 | G75: ='dat_file 1980'!G75 -> 0.1291 | H75: =ROUND('dat_file 1980'!H75/'dat_file 1980'!H$68,4) -> 1.0535

Sheet dat_file 2018
B1: Year | C1: pce | D1: cpi-u-rs | E1: cpiu | F1: cpiu-rs67 | G1: cpiu67 | H1: cpi-u-rs adj | I1: cpi-u-rs adj03
B2: =+Sheet3!A2 -> 1947 | C2: =ROUND('dat_file 1980'!C2/'dat_file 1980'!C$73,4) -> 0.1153 | D2: =ROUND('dat_file 1980'!D2/'dat_file 1980'!D$73,4) -> 0.1016 | E2: =ROUND('dat_file 1980'!E2/'dat_file 1980'!E$73,4) -> 0.0888 | F2: ='dat_file 1980'!F2 -> 1.496 | G2: ='dat_file 1980'!G2 -> 1.4978 | H2: =ROUND('dat_file 1980'!H2/'dat_file 1980'!H$73,4) -> 0.1927 | I2: =ROUND('dat_file 1980'!J2/'dat_file 1980'!J$73,4) -> 0.1712
B3: =+Sheet3!A3 -> 1948 | C3: =ROUND('dat_file 1980'!C3/'dat_file 1980'!C$73,4) -> 0.1219 | D3: =ROUND('dat_file 1980'!D3/'dat_file 1980'!D$73,4) -> 0.1097 | E3: =ROUND('dat_file 1980'!E3/'dat_file 1980'!E$73,4) -> 0.096 | F3: ='dat_file 1980'!F3 -> 1.3852 | G3: ='dat_file 1980'!G3 -> 1.3859 | H3: =ROUND('dat_file 1980'!H3/'dat_file 1980'!H$73,4) -> 0.206 | I3: =ROUND('dat_file 1980'!J3/'dat_file 1980'!J$73,4) -> 0.1828
B4: =+Sheet3!A4 -> 1949 | C4: =ROUND('dat_file 1980'!C4/'dat_file 1980'!C$73,4) -> 0.1209 | D4: =ROUND('dat_file 1980'!D4/'dat_file 1980'!D$73,4) -> 0.1084 | E4: =ROUND('dat_file 1980'!E4/'dat_file 1980'!E$73,4) -> 0.0948 | F4: ='dat_file 1980'!F4 -> 1.4025 | G4: ='dat_file 1980'!G4 -> 1.4034 | H4: =ROUND('dat_file 1980'!H4/'dat_file 1980'!H$73,4) -> 0.2012 | I4: =ROUND('dat_file 1980'!J4/'dat_file 1980'!J$73,4) -> 0.1786
B5: =+Sheet3!A5 -> 1950 | C5: =ROUND('dat_file 1980'!C5/'dat_file 1980'!C$73,4) -> 0.1223 | D5: =ROUND('dat_file 1980'!D5/'dat_file 1980'!D$73,4) -> 0.1097 | E5: =ROUND('dat_file 1980'!E5/'dat_file 1980'!E$73,4) -> 0.096 | F5: ='dat_file 1980'!F5 -> 1.3852 | G5: ='dat_file 1980'!G5 -> 1.3859 | H5: =ROUND('dat_file 1980'!H5/'dat_file 1980'!H$73,4) -> 0.2015 | I5: =ROUND('dat_file 1980'!J5/'dat_file 1980'!J$73,4) -> 0.1786
B6: =+Sheet3!A6 -> 1951 | C6: =ROUND('dat_file 1980'!C6/'dat_file 1980'!C$73,4) -> 0.1307 | D6: =ROUND('dat_file 1980'!D6/'dat_file 1980'!D$73,4) -> 0.1184 | E6: =ROUND('dat_file 1980'!E6/'dat_file 1980'!E$73,4) -> 0.1035 | F6: ='dat_file 1980'!F6 -> 1.2838 | G6: ='dat_file 1980'!G6 -> 1.2846 | H6: =ROUND('dat_file 1980'!H6/'dat_file 1980'!H$73,4) -> 0.2152 | I6: =ROUND('dat_file 1980'!J6/'dat_file 1980'!J$73,4) -> 0.191
B7: =+Sheet3!A7 -> 1952 | C7: =ROUND('dat_file 1980'!C7/'dat_file 1980'!C$73,4) -> 0.1334 | D7: =ROUND('dat_file 1980'!D7/'dat_file 1980'!D$73,4) -> 0.1206 | E7: =ROUND('dat_file 1980'!E7/'dat_file 1980'!E$73,4) -> 0.1055 | F7: ='dat_file 1980'!F7 -> 1.2607 | G7: ='dat_file 1980'!G7 -> 1.2604 | H7: =ROUND('dat_file 1980'!H7/'dat_file 1980'!H$73,4) -> 0.2168 | I7: =ROUND('dat_file 1980'!J7/'dat_file 1980'!J$73,4) -> 0.1923
B8: =+Sheet3!A8 -> 1953 | C8: =ROUND('dat_file 1980'!C8/'dat_file 1980'!C$73,4) -> 0.1351 | D8: =ROUND('dat_file 1980'!D8/'dat_file 1980'!D$73,4) -> 0.1214 | E8: =ROUND('dat_file 1980'!E8/'dat_file 1980'!E$73,4) -> 0.1063 | F8: ='dat_file 1980'!F8 -> 1.2522 | G8: ='dat_file 1980'!G8 -> 1.2509 | H8: =ROUND('dat_file 1980'!H8/'dat_file 1980'!H$73,4) -> 0.2159 | I8: =ROUND('dat_file 1980'!J8/'dat_file 1980'!J$73,4) -> 0.1915
B9: =+Sheet3!A9 -> 1954 | C9: =ROUND('dat_file 1980'!C9/'dat_file 1980'!C$73,4) -> 0.1363 | D9: =ROUND('dat_file 1980'!D9/'dat_file 1980'!D$73,4) -> 0.1225 | E9: =ROUND('dat_file 1980'!E9/'dat_file 1980'!E$73,4) -> 0.1071 | F9: ='dat_file 1980'!F9 -> 1.2412 | G9: ='dat_file 1980'!G9 -> 1.2416 | H9: =ROUND('dat_file 1980'!H9/'dat_file 1980'!H$73,4) -> 0.2154 | I9: =ROUND('dat_file 1980'!J9/'dat_file 1980'!J$73,4) -> 0.191
B10: =+Sheet3!A10 -> 1955 | C10: =ROUND('dat_file 1980'!C10/'dat_file 1980'!C$73,4) -> 0.1368 | D10: =ROUND('dat_file 1980'!D10/'dat_file 1980'!D$73,4) -> 0.1219 | E10: =ROUND('dat_file 1980'!E10/'dat_file 1980'!E$73,4) -> 0.1067 | F10: ='dat_file 1980'!F10 -> 1.2467 | G10: ='dat_file 1980'!G10 -> 1.2463 | H10: =ROUND('dat_file 1980'!H10/'dat_file 1980'!H$73,4) -> 0.2121 | I10: =ROUND('dat_file 1980'!J10/'dat_file 1980'!J$73,4) -> 0.1881
B11: =+Sheet3!A11 -> 1956 | C11: =ROUND('dat_file 1980'!C11/'dat_file 1980'!C$73,4) -> 0.1395 | D11: =ROUND('dat_file 1980'!D11/'dat_file 1980'!D$73,4) -> 0.1238 | E11: =ROUND('dat_file 1980'!E11/'dat_file 1980'!E$73,4) -> 0.1083 | F11: ='dat_file 1980'!F11 -> 1.2276 | G11: ='dat_file 1980'!G11 -> 1.2279 | H11: =ROUND('dat_file 1980'!H11/'dat_file 1980'!H$73,4) -> 0.2131 | I11: =ROUND('dat_file 1980'!J11/'dat_file 1980'!J$73,4) -> 0.189
B12: =+Sheet3!A12 -> 1957 | C12: =ROUND('dat_file 1980'!C12/'dat_file 1980'!C$73,4) -> 0.1438 | D12: =ROUND('dat_file 1980'!D12/'dat_file 1980'!D$73,4) -> 0.1279 | E12: =ROUND('dat_file 1980'!E12/'dat_file 1980'!E$73,4) -> 0.1119 | F12: ='dat_file 1980'!F12 -> 1.1886 | G12: ='dat_file 1980'!G12 -> 1.1886 | H12: =ROUND('dat_file 1980'!H12/'dat_file 1980'!H$73,4) -> 0.2177 | I12: =ROUND('dat_file 1980'!J12/'dat_file 1980'!J$73,4) -> 0.1931
B13: =+Sheet3!A13 -> 1958 | C13: =ROUND('dat_file 1980'!C13/'dat_file 1980'!C$73,4) -> 0.1471 | D13: =ROUND('dat_file 1980'!D13/'dat_file 1980'!D$73,4) -> 0.1314 | E13: =ROUND('dat_file 1980'!E13/'dat_file 1980'!E$73,4) -> 0.1151 | F13: ='dat_file 1980'!F13 -> 1.1567 | G13: ='dat_file 1980'!G13 -> 1.1557 | H13: =ROUND('dat_file 1980'!H13/'dat_file 1980'!H$73,4) -> 0.2213 | I13: =ROUND('dat_file 1980'!J13/'dat_file 1980'!J$73,4) -> 0.1964
B14: =+Sheet3!A14 -> 1959 | C14: =ROUND('dat_file 1980'!C14/'dat_file 1980'!C$73,4) -> 0.1493 | D14: =ROUND('dat_file 1980'!D14/'dat_file 1980'!D$73,4) -> 0.1325 | E14: =ROUND('dat_file 1980'!E14/'dat_file 1980'!E$73,4) -> 0.1159 | F14: ='dat_file 1980'!F14 -> 1.1472 | G14: ='dat_file 1980'!G14 -> 1.1478 | H14: =ROUND('dat_file 1980'!H14/'dat_file 1980'!H$73,4) -> 0.2207 | I14: =ROUND('dat_file 1980'!J14/'dat_file 1980'!J$73,4) -> 0.1956
B15: =+Sheet3!A15 -> 1960 | C15: =ROUND('dat_file 1980'!C15/'dat_file 1980'!C$73,4) -> 0.1518 | D15: =ROUND('dat_file 1980'!D15/'dat_file 1980'!D$73,4) -> 0.1346 | E15: =ROUND('dat_file 1980'!E15/'dat_file 1980'!E$73,4) -> 0.1179 | F15: ='dat_file 1980'!F15 -> 1.1288 | G15: ='dat_file 1980'!G15 -> 1.1284 | H15: =ROUND('dat_file 1980'!H15/'dat_file 1980'!H$73,4) -> 0.2219 | I15: =ROUND('dat_file 1980'!J15/'dat_file 1980'!J$73,4) -> 0.1969 | K15: ="IF ref_year="&'dat_file 1980'!B15&" THEN cpi_u_rs_18="&ROUND('dat_file 1980'!$D$73/'dat_file 1980'!D15,3)&";" -> IF ref_year=1960 THEN cpi_u_rs_18=7.427; | O15: ="IF ref_year="&'dat_file 1980'!B15&" THEN cpi_u_rs_adj_18="&ROUND('dat_file 1980'!$H$73/'dat_file 1980'!H15,3)&";" -> IF ref_year=1960 THEN cpi_u_rs_adj_18=4.507;
B16: =+Sheet3!A16 -> 1961 | C16: =ROUND('dat_file 1980'!C16/'dat_file 1980'!C$73,4) -> 0.1534 | D16: =ROUND('dat_file 1980'!D16/'dat_file 1980'!D$73,4) -> 0.136 | E16: =ROUND('dat_file 1980'!E16/'dat_file 1980'!E$73,4) -> 0.1191 | F16: ='dat_file 1980'!F16 -> 1.1175 | G16: ='dat_file 1980'!G16 -> 1.1171 | H16: =ROUND('dat_file 1980'!H16/'dat_file 1980'!H$73,4) -> 0.2217 | I16: =ROUND('dat_file 1980'!J16/'dat_file 1980'!J$73,4) -> 0.1969 | K16: ="ELSE IF ref_year="&'dat_file 1980'!B16&" THEN cpi_u_rs_18="&ROUND('dat_file 1980'!$D$73/'dat_file 1980'!D16,3)&";" -> ELSE IF ref_year=1961 THEN cpi_u_rs_18=7.352; | O16: ="ELSE IF ref_year="&'dat_file 1980'!B16&" THEN cpi_u_rs_adj_18="&ROUND('dat_file 1980'!$H$73/'dat_file 1980'!H16,3)&";" -> ELSE IF ref_year=1961 THEN cpi_u_rs_adj_18=4.511;
B17: =+Sheet3!A17 -> 1962 | C17: =ROUND('dat_file 1980'!C17/'dat_file 1980'!C$73,4) -> 0.1552 | D17: =ROUND('dat_file 1980'!D17/'dat_file 1980'!D$73,4) -> 0.1374 | E17: =ROUND('dat_file 1980'!E17/'dat_file 1980'!E$73,4) -> 0.1203 | F17: ='dat_file 1980'!F17 -> 1.1065 | G17: ='dat_file 1980'!G17 -> 1.106 | H17: =ROUND('dat_file 1980'!H17/'dat_file 1980'!H$73,4) -> 0.2215 | I17: =ROUND('dat_file 1980'!J17/'dat_file 1980'!J$73,4) -> 0.1964 | K17: ="ELSE IF ref_year="&'dat_file 1980'!B17&" THEN cpi_u_rs_18="&ROUND('dat_file 1980'!$D$73/'dat_file 1980'!D17,3)&";" -> ELSE IF ref_year=1962 THEN cpi_u_rs_18=7.28; | O17: ="ELSE IF ref_year="&'dat_file 1980'!B17&" THEN cpi_u_rs_adj_18="&ROUND('dat_file 1980'!$H$73/'dat_file 1980'!H17,3)&";" -> ELSE IF ref_year=1962 THEN cpi_u_rs_adj_18=4.515;
B18: =+Sheet3!A18 -> 1963 | C18: =ROUND('dat_file 1980'!C18/'dat_file 1980'!C$73,4) -> 0.157 | D18: =ROUND('dat_file 1980'!D18/'dat_file 1980'!D$73,4) -> 0.1393 | E18: =ROUND('dat_file 1980'!E18/'dat_file 1980'!E$73,4) -> 0.1219 | F18: ='dat_file 1980'!F18 -> 1.0914 | G18: ='dat_file 1980'!G18 -> 1.0915 | H18: =ROUND('dat_file 1980'!H18/'dat_file 1980'!H$73,4) -> 0.2221 | I18: =ROUND('dat_file 1980'!J18/'dat_file 1980'!J$73,4) -> 0.1969 | K18: ="ELSE IF ref_year="&'dat_file 1980'!B18&" THEN cpi_u_rs_18="&ROUND('dat_file 1980'!$D$73/'dat_file 1980'!D18,3)&";" -> ELSE IF ref_year=1963 THEN cpi_u_rs_18=7.181; | O18: ="ELSE IF ref_year="&'dat_file 1980'!B18&" THEN cpi_u_rs_adj_18="&ROUND('dat_file 1980'!$H$73/'dat_file 1980'!H18,3)&";" -> ELSE IF ref_year=1963 THEN cpi_u_rs_adj_18=4.503;
B19: =+Sheet3!A19 -> 1964 | C19: =ROUND('dat_file 1980'!C19/'dat_file 1980'!C$73,4) -> 0.1593 | D19: =ROUND('dat_file 1980'!D19/'dat_file 1980'!D$73,4) -> 0.1412 | E19: =ROUND('dat_file 1980'!E19/'dat_file 1980'!E$73,4) -> 0.1234 | F19: ='dat_file 1980'!F19 -> 1.0768 | G19: ='dat_file 1980'!G19 -> 1.0774 | H19: =ROUND('dat_file 1980'!H19/'dat_file 1980'!H$73,4) -> 0.2227 | I19: =ROUND('dat_file 1980'!J19/'dat_file 1980'!J$73,4) -> 0.1977 | K19: ="ELSE IF ref_year="&'dat_file 1980'!B19&" THEN cpi_u_rs_18="&ROUND('dat_file 1980'!$D$73/'dat_file 1980'!D19,3)&";" -> ELSE IF ref_year=1964 THEN cpi_u_rs_18=7.085; | O19: ="ELSE IF ref_year="&'dat_file 1980'!B19&" THEN cpi_u_rs_adj_18="&ROUND('dat_file 1980'!$H$73/'dat_file 1980'!H19,3)&";" -> ELSE IF ref_year=1964 THEN cpi_u_rs_adj_18=4.491;
B20: =+Sheet3!A20 -> 1965 | C20: =ROUND('dat_file 1980'!C20/'dat_file 1980'!C$73,4) -> 0.1616 | D20: =ROUND('dat_file 1980'!D20/'dat_file 1980'!D$73,4) -> 0.1433 | E20: =ROUND('dat_file 1980'!E20/'dat_file 1980'!E$73,4) -> 0.1255 | F20: ='dat_file 1980'!F20 -> 1.0605 | G20: ='dat_file 1980'!G20 -> 1.0603 | H20: =ROUND('dat_file 1980'!H20/'dat_file 1980'!H$73,4) -> 0.2236 | I20: =ROUND('dat_file 1980'!J20/'dat_file 1980'!J$73,4) -> 0.1985 | K20: ="ELSE IF ref_year="&'dat_file 1980'!B20&" THEN cpi_u_rs_18="&ROUND('dat_file 1980'!$D$73/'dat_file 1980'!D20,3)&";" -> ELSE IF ref_year=1965 THEN cpi_u_rs_18=6.977; | O20: ="ELSE IF ref_year="&'dat_file 1980'!B20&" THEN cpi_u_rs_adj_18="&ROUND('dat_file 1980'!$H$73/'dat_file 1980'!H20,3)&";" -> ELSE IF ref_year=1965 THEN cpi_u_rs_adj_18=4.471;
B21: =+Sheet3!A21 -> 1966 | C21: =ROUND('dat_file 1980'!C21/'dat_file 1980'!C$73,4) -> 0.1657 | D21: =ROUND('dat_file 1980'!D21/'dat_file 1980'!D$73,4) -> 0.1474 | E21: =ROUND('dat_file 1980'!E21/'dat_file 1980'!E$73,4) -> 0.129 | F21: ='dat_file 1980'!F21 -> 1.0313 | G21: ='dat_file 1980'!G21 -> 1.0309 | H21: =ROUND('dat_file 1980'!H21/'dat_file 1980'!H$73,4) -> 0.2275 | I21: =ROUND('dat_file 1980'!J21/'dat_file 1980'!J$73,4) -> 0.2018 | K21: ="ELSE IF ref_year="&'dat_file 1980'!B21&" THEN cpi_u_rs_18="&ROUND('dat_file 1980'!$D$73/'dat_file 1980'!D21,3)&";" -> ELSE IF ref_year=1966 THEN cpi_u_rs_18=6.785; | O21: ="ELSE IF ref_year="&'dat_file 1980'!B21&" THEN cpi_u_rs_adj_18="&ROUND('dat_file 1980'!$H$73/'dat_file 1980'!H21,3)&";" -> ELSE IF ref_year=1966 THEN cpi_u_rs_adj_18=4.395;
B22: =+Sheet3!A22 -> 1967 | C22: =ROUND('dat_file 1980'!C22/'dat_file 1980'!C$73,4) -> 0.1698 | D22: =ROUND('dat_file 1980'!D22/'dat_file 1980'!D$73,4) -> 0.152 | E22: =ROUND('dat_file 1980'!E22/'dat_file 1980'!E$73,4) -> 0.133 | F22: ='dat_file 1980'!F22 -> 1 | G22: ='dat_file 1980'!G22 -> 1 | H22: =ROUND('dat_file 1980'!H22/'dat_file 1980'!H$73,4) -> 0.2321 | I22: =ROUND('dat_file 1980'!J22/'dat_file 1980'!J$73,4) -> 0.206 | K22: ="ELSE IF ref_year="&'dat_file 1980'!B22&" THEN cpi_u_rs_18="&ROUND('dat_file 1980'!$D$73/'dat_file 1980'!D22,3)&";" -> ELSE IF ref_year=1967 THEN cpi_u_rs_18=6.579; | O22: ="ELSE IF ref_year="&'dat_file 1980'!B22&" THEN cpi_u_rs_adj_18="&ROUND('dat_file 1980'!$H$73/'dat_file 1980'!H22,3)&";" -> ELSE IF ref_year=1967 THEN cpi_u_rs_adj_18=4.308;
B23: =+Sheet3!A23 -> 1968 | C23: =ROUND('dat_file 1980'!C23/'dat_file 1980'!C$73,4) -> 0.1765 | D23: =ROUND('dat_file 1980'!D23/'dat_file 1980'!D$73,4) -> 0.158 | E23: =ROUND('dat_file 1980'!E23/'dat_file 1980'!E$73,4) -> 0.1386 | F23: ='dat_file 1980'!F23 -> 0.9623 | G23: ='dat_file 1980'!G23 -> 0.9598 | H23: =ROUND('dat_file 1980'!H23/'dat_file 1980'!H$73,4) -> 0.2387 | I23: =ROUND('dat_file 1980'!J23/'dat_file 1980'!J$73,4) -> 0.2118 | K23: ="ELSE IF ref_year="&'dat_file 1980'!B23&" THEN cpi_u_rs_18="&ROUND('dat_file 1980'!$D$73/'dat_file 1980'!D23,3)&";" -> ELSE IF ref_year=1968 THEN cpi_u_rs_18=6.331; | O23: ="ELSE IF ref_year="&'dat_file 1980'!B23&" THEN cpi_u_rs_adj_18="&ROUND('dat_file 1980'!$H$73/'dat_file 1980'!H23,3)&";" -> ELSE IF ref_year=1968 THEN cpi_u_rs_adj_18=4.19;
B24: =+Sheet3!A24 -> 1969 | C24: =ROUND('dat_file 1980'!C24/'dat_file 1980'!C$73,4) -> 0.1844 | D24: =ROUND('dat_file 1980'!D24/'dat_file 1980'!D$73,4) -> 0.165 | E24: =ROUND('dat_file 1980'!E24/'dat_file 1980'!E$73,4) -> 0.1462 | F24: ='dat_file 1980'!F24 -> 0.9212 | G24: ='dat_file 1980'!G24 -> 0.9101 | H24: =ROUND('dat_file 1980'!H24/'dat_file 1980'!H$73,4) -> 0.2467 | I24: =ROUND('dat_file 1980'!J24/'dat_file 1980'!J$73,4) -> 0.2188 | K24: ="ELSE IF ref_year="&'dat_file 1980'!B24&" THEN cpi_u_rs_18="&ROUND('dat_file 1980'!$D$73/'dat_file 1980'!D24,3)&";" -> ELSE IF ref_year=1969 THEN cpi_u_rs_18=6.06; | O24: ="ELSE IF ref_year="&'dat_file 1980'!B24&" THEN cpi_u_rs_adj_18="&ROUND('dat_file 1980'!$H$73/'dat_file 1980'!H24,3)&";" -> ELSE IF ref_year=1969 THEN cpi_u_rs_adj_18=4.054;
B25: =+Sheet3!A25 -> 1970 | C25: =ROUND('dat_file 1980'!C25/'dat_file 1980'!C$73,4) -> 0.1931 | D25: =ROUND('dat_file 1980'!D25/'dat_file 1980'!D$73,4) -> 0.1731 | E25: =ROUND('dat_file 1980'!E25/'dat_file 1980'!E$73,4) -> 0.1545 | F25: ='dat_file 1980'!F25 -> 0.8779 | G25: ='dat_file 1980'!G25 -> 0.8608 | H25: =ROUND('dat_file 1980'!H25/'dat_file 1980'!H$73,4) -> 0.2561 | I25: =ROUND('dat_file 1980'!J25/'dat_file 1980'!J$73,4) -> 0.2271 | K25: ="ELSE IF ref_year="&'dat_file 1980'!B25&" THEN cpi_u_rs_18="&ROUND('dat_file 1980'!$D$73/'dat_file 1980'!D25,3)&";" -> ELSE IF ref_year=1970 THEN cpi_u_rs_18=5.776; | O25: ="ELSE IF ref_year="&'dat_file 1980'!B25&" THEN cpi_u_rs_adj_18="&ROUND('dat_file 1980'!$H$73/'dat_file 1980'!H25,3)&";" -> ELSE IF ref_year=1970 THEN cpi_u_rs_adj_18=3.904;
B26: =+Sheet3!A26 -> 1971 | C26: =ROUND('dat_file 1980'!C26/'dat_file 1980'!C$73,4) -> 0.2012 | D26: =ROUND('dat_file 1980'!D26/'dat_file 1980'!D$73,4) -> 0.1807 | E26: =ROUND('dat_file 1980'!E26/'dat_file 1980'!E$73,4) -> 0.1613 | F26: ='dat_file 1980'!F26 -> 0.8411 | G26: ='dat_file 1980'!G26 -> 0.8247 | H26: =ROUND('dat_file 1980'!H26/'dat_file 1980'!H$73,4) -> 0.2646 | I26: =ROUND('dat_file 1980'!J26/'dat_file 1980'!J$73,4) -> 0.2346 | K26: ="ELSE IF ref_year="&'dat_file 1980'!B26&" THEN cpi_u_rs_18="&ROUND('dat_file 1980'!$D$73/'dat_file 1980'!D26,3)&";" -> ELSE IF ref_year=1971 THEN cpi_u_rs_18=5.534; | O26: ="ELSE IF ref_year="&'dat_file 1980'!B26&" THEN cpi_u_rs_adj_18="&ROUND('dat_file 1980'!$H$73/'dat_file 1980'!H26,3)&";" -> ELSE IF ref_year=1971 THEN cpi_u_rs_adj_18=3.78;
B27: =+Sheet3!A27 -> 1972 | C27: =ROUND('dat_file 1980'!C27/'dat_file 1980'!C$73,4) -> 0.2081 | D27: =ROUND('dat_file 1980'!D27/'dat_file 1980'!D$73,4) -> 0.1861 | E27: =ROUND('dat_file 1980'!E27/'dat_file 1980'!E$73,4) -> 0.1665 | F27: ='dat_file 1980'!F27 -> 0.8166 | G27: ='dat_file 1980'!G27 -> 0.799 | H27: =ROUND('dat_file 1980'!H27/'dat_file 1980'!H$73,4) -> 0.2696 | I27: =ROUND('dat_file 1980'!J27/'dat_file 1980'!J$73,4) -> 0.2391 | K27: ="ELSE IF ref_year="&'dat_file 1980'!B27&" THEN cpi_u_rs_18="&ROUND('dat_file 1980'!$D$73/'dat_file 1980'!D27,3)&";" -> ELSE IF ref_year=1972 THEN cpi_u_rs_18=5.373; | O27: ="ELSE IF ref_year="&'dat_file 1980'!B27&" THEN cpi_u_rs_adj_18="&ROUND('dat_file 1980'!$H$73/'dat_file 1980'!H27,3)&";" -> ELSE IF ref_year=1972 THEN cpi_u_rs_adj_18=3.71;
... B73: =+Sheet3!A73 -> 2018 | C73: =ROUND('dat_file 1980'!C73/'dat_file 1980'!C$73,4) -> 1 | D73: =ROUND('dat_file 1980'!D73/'dat_file 1980'!D$73,4) -> 1 | E73: =ROUND('dat_file 1980'!E73/'dat_file 1980'!E$73,4) -> 1 | F73: ='dat_file 1980'!F73 -> 0.152 | G73: ='dat_file 1980'!G73 -> 0.133 | H73: =ROUND('dat_file 1980'!H73/'dat_file 1980'!H$73,4) -> 1 | I73: =ROUND('dat_file 1980'!J73/'dat_file 1980'!J$73,4) -> 1 | K73: ="ELSE IF ref_year="&'dat_file 1980'!B73&" THEN cpi_u_rs_18="&ROUND('dat_file 1980'!$D$73/'dat_file 1980'!D73,3)&";" -> ELSE IF ref_year=2018 THEN cpi_u_rs_18=1; | O73: ="ELSE IF ref_year="&'dat_file 1980'!B73&" THEN cpi_u_rs_adj_18="&ROUND('dat_file 1980'!$H$73/'dat_file 1980'!H73,3)&";" -> ELSE IF ref_year=2018 THEN cpi_u_rs_adj_18=1;
B74: =+Sheet3!A74 -> 2019 | C74: =ROUND('dat_file 1980'!C74/'dat_file 1980'!C$73,4) -> 1.0149 | D74: =ROUND('dat_file 1980'!D74/'dat_file 1980'!D$73,4) -> 1.0181 | E74: =ROUND('dat_file 1980'!E74/'dat_file 1980'!E$73,4) -> 1.0181 | F74: ='dat_file 1980'!F74 -> 0.1493 | G74: ='dat_file 1980'!G74 -> 0.1306 | H74: =ROUND('dat_file 1980'!H74/'dat_file 1980'!H$73,4) -> 1.0101 | I74: =ROUND('dat_file 1980'!J74/'dat_file 1980'!J$73,4) -> 1.0133
B75: =+Sheet3!A75 -> 2020 | C75: =ROUND('dat_file 1980'!C75/'dat_file 1980'!C$73,4) -> 1.0261 | D75: =ROUND('dat_file 1980'!D75/'dat_file 1980'!D$73,4) -> 1.0317 | E75: =ROUND('dat_file 1980'!E75/'dat_file 1980'!E$73,4) -> 1.0307 | F75: ='dat_file 1980'!F75 -> 0.1473 | G75: ='dat_file 1980'!G75 -> 0.1291 | H75: =ROUND('dat_file 1980'!H75/'dat_file 1980'!H$73,4) -> 1.0155 | I75: =ROUND('dat_file 1980'!J75/'dat_file 1980'!J$73,4) -> 1.0215

Sheet dat_file 2019
B1: Year | C1: pce | D1: cpi-u-rs | E1: cpiu | F1: cpiu-rs67 | G1: cpiu67 | H1: cpi-u-rs adj | I1: cpi-u-rs adj03
B2: =+Sheet3!A2 -> 1947 | C2: =ROUND('dat_file 1980'!C2/'dat_file 1980'!C$74,4) -> 0.1136 | D2: =ROUND('dat_file 1980'!D2/'dat_file 1980'!D$74,4) -> 0.0998 | E2: =ROUND('dat_file 1980'!E2/'dat_file 1980'!E$74,4) -> 0.0872 | F2: ='dat_file 1980'!F2 -> 1.496 | G2: ='dat_file 1980'!G2 -> 1.4978 | H2: =ROUND('dat_file 1980'!H2/'dat_file 1980'!H$74,4) -> 0.1908 | I2: =ROUND('dat_file 1980'!J2/'dat_file 1980'!J$74,4) -> 0.1689
B3: =+Sheet3!A3 -> 1948 | C3: =ROUND('dat_file 1980'!C3/'dat_file 1980'!C$74,4) -> 0.1201 | D3: =ROUND('dat_file 1980'!D3/'dat_file 1980'!D$74,4) -> 0.1078 | E3: =ROUND('dat_file 1980'!E3/'dat_file 1980'!E$74,4) -> 0.0943 | F3: ='dat_file 1980'!F3 -> 1.3852 | G3: ='dat_file 1980'!G3 -> 1.3859 | H3: =ROUND('dat_file 1980'!H3/'dat_file 1980'!H$74,4) -> 0.204 | I3: =ROUND('dat_file 1980'!J3/'dat_file 1980'!J$74,4) -> 0.1804
B4: =+Sheet3!A4 -> 1949 | C4: =ROUND('dat_file 1980'!C4/'dat_file 1980'!C$74,4) -> 0.1191 | D4: =ROUND('dat_file 1980'!D4/'dat_file 1980'!D$74,4) -> 0.1064 | E4: =ROUND('dat_file 1980'!E4/'dat_file 1980'!E$74,4) -> 0.0931 | F4: ='dat_file 1980'!F4 -> 1.4025 | G4: ='dat_file 1980'!G4 -> 1.4034 | H4: =ROUND('dat_file 1980'!H4/'dat_file 1980'!H$74,4) -> 0.1992 | I4: =ROUND('dat_file 1980'!J4/'dat_file 1980'!J$74,4) -> 0.1763
B5: =+Sheet3!A5 -> 1950 | C5: =ROUND('dat_file 1980'!C5/'dat_file 1980'!C$74,4) -> 0.1205 | D5: =ROUND('dat_file 1980'!D5/'dat_file 1980'!D$74,4) -> 0.1078 | E5: =ROUND('dat_file 1980'!E5/'dat_file 1980'!E$74,4) -> 0.0943 | F5: ='dat_file 1980'!F5 -> 1.3852 | G5: ='dat_file 1980'!G5 -> 1.3859 | H5: =ROUND('dat_file 1980'!H5/'dat_file 1980'!H$74,4) -> 0.1995 | I5: =ROUND('dat_file 1980'!J5/'dat_file 1980'!J$74,4) -> 0.1763
B6: =+Sheet3!A6 -> 1951 | C6: =ROUND('dat_file 1980'!C6/'dat_file 1980'!C$74,4) -> 0.1288 | D6: =ROUND('dat_file 1980'!D6/'dat_file 1980'!D$74,4) -> 0.1163 | E6: =ROUND('dat_file 1980'!E6/'dat_file 1980'!E$74,4) -> 0.1017 | F6: ='dat_file 1980'!F6 -> 1.2838 | G6: ='dat_file 1980'!G6 -> 1.2846 | H6: =ROUND('dat_file 1980'!H6/'dat_file 1980'!H$74,4) -> 0.2131 | I6: =ROUND('dat_file 1980'!J6/'dat_file 1980'!J$74,4) -> 0.1885
B7: =+Sheet3!A7 -> 1952 | C7: =ROUND('dat_file 1980'!C7/'dat_file 1980'!C$74,4) -> 0.1314 | D7: =ROUND('dat_file 1980'!D7/'dat_file 1980'!D$74,4) -> 0.1184 | E7: =ROUND('dat_file 1980'!E7/'dat_file 1980'!E$74,4) -> 0.1037 | F7: ='dat_file 1980'!F7 -> 1.2607 | G7: ='dat_file 1980'!G7 -> 1.2604 | H7: =ROUND('dat_file 1980'!H7/'dat_file 1980'!H$74,4) -> 0.2146 | I7: =ROUND('dat_file 1980'!J7/'dat_file 1980'!J$74,4) -> 0.1898
B8: =+Sheet3!A8 -> 1953 | C8: =ROUND('dat_file 1980'!C8/'dat_file 1980'!C$74,4) -> 0.1331 | D8: =ROUND('dat_file 1980'!D8/'dat_file 1980'!D$74,4) -> 0.1192 | E8: =ROUND('dat_file 1980'!E8/'dat_file 1980'!E$74,4) -> 0.1044 | F8: ='dat_file 1980'!F8 -> 1.2522 | G8: ='dat_file 1980'!G8 -> 1.2509 | H8: =ROUND('dat_file 1980'!H8/'dat_file 1980'!H$74,4) -> 0.2137 | I8: =ROUND('dat_file 1980'!J8/'dat_file 1980'!J$74,4) -> 0.189
B9: =+Sheet3!A9 -> 1954 | C9: =ROUND('dat_file 1980'!C9/'dat_file 1980'!C$74,4) -> 0.1343 | D9: =ROUND('dat_file 1980'!D9/'dat_file 1980'!D$74,4) -> 0.1203 | E9: =ROUND('dat_file 1980'!E9/'dat_file 1980'!E$74,4) -> 0.1052 | F9: ='dat_file 1980'!F9 -> 1.2412 | G9: ='dat_file 1980'!G9 -> 1.2416 | H9: =ROUND('dat_file 1980'!H9/'dat_file 1980'!H$74,4) -> 0.2133 | I9: =ROUND('dat_file 1980'!J9/'dat_file 1980'!J$74,4) -> 0.1885
B10: =+Sheet3!A10 -> 1955 | C10: =ROUND('dat_file 1980'!C10/'dat_file 1980'!C$74,4) -> 0.1348 | D10: =ROUND('dat_file 1980'!D10/'dat_file 1980'!D$74,4) -> 0.1198 | E10: =ROUND('dat_file 1980'!E10/'dat_file 1980'!E$74,4) -> 0.1048 | F10: ='dat_file 1980'!F10 -> 1.2467 | G10: ='dat_file 1980'!G10 -> 1.2463 | H10: =ROUND('dat_file 1980'!H10/'dat_file 1980'!H$74,4) -> 0.21 | I10: =ROUND('dat_file 1980'!J10/'dat_file 1980'!J$74,4) -> 0.1857
B11: =+Sheet3!A11 -> 1956 | C11: =ROUND('dat_file 1980'!C11/'dat_file 1980'!C$74,4) -> 0.1374 | D11: =ROUND('dat_file 1980'!D11/'dat_file 1980'!D$74,4) -> 0.1216 | E11: =ROUND('dat_file 1980'!E11/'dat_file 1980'!E$74,4) -> 0.1064 | F11: ='dat_file 1980'!F11 -> 1.2276 | G11: ='dat_file 1980'!G11 -> 1.2279 | H11: =ROUND('dat_file 1980'!H11/'dat_file 1980'!H$74,4) -> 0.2109 | I11: =ROUND('dat_file 1980'!J11/'dat_file 1980'!J$74,4) -> 0.1865
B12: =+Sheet3!A12 -> 1957 | C12: =ROUND('dat_file 1980'!C12/'dat_file 1980'!C$74,4) -> 0.1416 | D12: =ROUND('dat_file 1980'!D12/'dat_file 1980'!D$74,4) -> 0.1256 | E12: =ROUND('dat_file 1980'!E12/'dat_file 1980'!E$74,4) -> 0.1099 | F12: ='dat_file 1980'!F12 -> 1.1886 | G12: ='dat_file 1980'!G12 -> 1.1886 | H12: =ROUND('dat_file 1980'!H12/'dat_file 1980'!H$74,4) -> 0.2155 | I12: =ROUND('dat_file 1980'!J12/'dat_file 1980'!J$74,4) -> 0.1906
B13: =+Sheet3!A13 -> 1958 | C13: =ROUND('dat_file 1980'!C13/'dat_file 1980'!C$74,4) -> 0.145 | D13: =ROUND('dat_file 1980'!D13/'dat_file 1980'!D$74,4) -> 0.1291 | E13: =ROUND('dat_file 1980'!E13/'dat_file 1980'!E$74,4) -> 0.113 | F13: ='dat_file 1980'!F13 -> 1.1567 | G13: ='dat_file 1980'!G13 -> 1.1557 | H13: =ROUND('dat_file 1980'!H13/'dat_file 1980'!H$74,4) -> 0.2191 | I13: =ROUND('dat_file 1980'!J13/'dat_file 1980'!J$74,4) -> 0.1939
B14: =+Sheet3!A14 -> 1959 | C14: =ROUND('dat_file 1980'!C14/'dat_file 1980'!C$74,4) -> 0.1471 | D14: =ROUND('dat_file 1980'!D14/'dat_file 1980'!D$74,4) -> 0.1301 | E14: =ROUND('dat_file 1980'!E14/'dat_file 1980'!E$74,4) -> 0.1138 | F14: ='dat_file 1980'!F14 -> 1.1472 | G14: ='dat_file 1980'!G14 -> 1.1478 | H14: =ROUND('dat_file 1980'!H14/'dat_file 1980'!H$74,4) -> 0.2185 | I14: =ROUND('dat_file 1980'!J14/'dat_file 1980'!J$74,4) -> 0.193
B15: =+Sheet3!A15 -> 1960 | C15: =ROUND('dat_file 1980'!C15/'dat_file 1980'!C$74,4) -> 0.1495 | D15: =ROUND('dat_file 1980'!D15/'dat_file 1980'!D$74,4) -> 0.1322 | E15: =ROUND('dat_file 1980'!E15/'dat_file 1980'!E$74,4) -> 0.1158 | F15: ='dat_file 1980'!F15 -> 1.1288 | G15: ='dat_file 1980'!G15 -> 1.1284 | H15: =ROUND('dat_file 1980'!H15/'dat_file 1980'!H$74,4) -> 0.2197 | I15: =ROUND('dat_file 1980'!J15/'dat_file 1980'!J$74,4) -> 0.1943 | K15: ="IF ref_year="&'dat_file 1980'!B15&" THEN cpi_u_rs_18="&ROUND('dat_file 1980'!$D$73/'dat_file 1980'!D15,3)&";" -> IF ref_year=1960 THEN cpi_u_rs_18=7.427; | O15: ="IF ref_year="&'dat_file 1980'!B15&" THEN cpi_u_rs_adj_18="&ROUND('dat_file 1980'!$H$73/'dat_file 1980'!H15,3)&";" -> IF ref_year=1960 THEN cpi_u_rs_adj_18=4.507;
B16: =+Sheet3!A16 -> 1961 | C16: =ROUND('dat_file 1980'!C16/'dat_file 1980'!C$74,4) -> 0.1511 | D16: =ROUND('dat_file 1980'!D16/'dat_file 1980'!D$74,4) -> 0.1336 | E16: =ROUND('dat_file 1980'!E16/'dat_file 1980'!E$74,4) -> 0.117 | F16: ='dat_file 1980'!F16 -> 1.1175 | G16: ='dat_file 1980'!G16 -> 1.1171 | H16: =ROUND('dat_file 1980'!H16/'dat_file 1980'!H$74,4) -> 0.2195 | I16: =ROUND('dat_file 1980'!J16/'dat_file 1980'!J$74,4) -> 0.1943 | K16: ="ELSE IF ref_year="&'dat_file 1980'!B16&" THEN cpi_u_rs_18="&ROUND('dat_file 1980'!$D$73/'dat_file 1980'!D16,3)&";" -> ELSE IF ref_year=1961 THEN cpi_u_rs_18=7.352; | O16: ="ELSE IF ref_year="&'dat_file 1980'!B16&" THEN cpi_u_rs_adj_18="&ROUND('dat_file 1980'!$H$73/'dat_file 1980'!H16,3)&";" -> ELSE IF ref_year=1961 THEN cpi_u_rs_adj_18=4.511;
B17: =+Sheet3!A17 -> 1962 | C17: =ROUND('dat_file 1980'!C17/'dat_file 1980'!C$74,4) -> 0.1529 | D17: =ROUND('dat_file 1980'!D17/'dat_file 1980'!D$74,4) -> 0.1349 | E17: =ROUND('dat_file 1980'!E17/'dat_file 1980'!E$74,4) -> 0.1181 | F17: ='dat_file 1980'!F17 -> 1.1065 | G17: ='dat_file 1980'!G17 -> 1.106 | H17: =ROUND('dat_file 1980'!H17/'dat_file 1980'!H$74,4) -> 0.2192 | I17: =ROUND('dat_file 1980'!J17/'dat_file 1980'!J$74,4) -> 0.1939 | K17: ="ELSE IF ref_year="&'dat_file 1980'!B17&" THEN cpi_u_rs_18="&ROUND('dat_file 1980'!$D$73/'dat_file 1980'!D17,3)&";" -> ELSE IF ref_year=1962 THEN cpi_u_rs_18=7.28; | O17: ="ELSE IF ref_year="&'dat_file 1980'!B17&" THEN cpi_u_rs_adj_18="&ROUND('dat_file 1980'!$H$73/'dat_file 1980'!H17,3)&";" -> ELSE IF ref_year=1962 THEN cpi_u_rs_adj_18=4.515;
B18: =+Sheet3!A18 -> 1963 | C18: =ROUND('dat_file 1980'!C18/'dat_file 1980'!C$74,4) -> 0.1547 | D18: =ROUND('dat_file 1980'!D18/'dat_file 1980'!D$74,4) -> 0.1368 | E18: =ROUND('dat_file 1980'!E18/'dat_file 1980'!E$74,4) -> 0.1197 | F18: ='dat_file 1980'!F18 -> 1.0914 | G18: ='dat_file 1980'!G18 -> 1.0915 | H18: =ROUND('dat_file 1980'!H18/'dat_file 1980'!H$74,4) -> 0.2198 | I18: =ROUND('dat_file 1980'!J18/'dat_file 1980'!J$74,4) -> 0.1943 | K18: ="ELSE IF ref_year="&'dat_file 1980'!B18&" THEN cpi_u_rs_18="&ROUND('dat_file 1980'!$D$73/'dat_file 1980'!D18,3)&";" -> ELSE IF ref_year=1963 THEN cpi_u_rs_18=7.181; | O18: ="ELSE IF ref_year="&'dat_file 1980'!B18&" THEN cpi_u_rs_adj_18="&ROUND('dat_file 1980'!$H$73/'dat_file 1980'!H18,3)&";" -> ELSE IF ref_year=1963 THEN cpi_u_rs_adj_18=4.503;
B19: =+Sheet3!A19 -> 1964 | C19: =ROUND('dat_file 1980'!C19/'dat_file 1980'!C$74,4) -> 0.157 | D19: =ROUND('dat_file 1980'!D19/'dat_file 1980'!D$74,4) -> 0.1386 | E19: =ROUND('dat_file 1980'!E19/'dat_file 1980'!E$74,4) -> 0.1213 | F19: ='dat_file 1980'!F19 -> 1.0768 | G19: ='dat_file 1980'!G19 -> 1.0774 | H19: =ROUND('dat_file 1980'!H19/'dat_file 1980'!H$74,4) -> 0.2204 | I19: =ROUND('dat_file 1980'!J19/'dat_file 1980'!J$74,4) -> 0.1951 | K19: ="ELSE IF ref_year="&'dat_file 1980'!B19&" THEN cpi_u_rs_18="&ROUND('dat_file 1980'!$D$73/'dat_file 1980'!D19,3)&";" -> ELSE IF ref_year=1964 THEN cpi_u_rs_18=7.085; | O19: ="ELSE IF ref_year="&'dat_file 1980'!B19&" THEN cpi_u_rs_adj_18="&ROUND('dat_file 1980'!$H$73/'dat_file 1980'!H19,3)&";" -> ELSE IF ref_year=1964 THEN cpi_u_rs_adj_18=4.491;
B20: =+Sheet3!A20 -> 1965 | C20: =ROUND('dat_file 1980'!C20/'dat_file 1980'!C$74,4) -> 0.1592 | D20: =ROUND('dat_file 1980'!D20/'dat_file 1980'!D$74,4) -> 0.1408 | E20: =ROUND('dat_file 1980'!E20/'dat_file 1980'!E$74,4) -> 0.1232 | F20: ='dat_file 1980'!F20 -> 1.0605 | G20: ='dat_file 1980'!G20 -> 1.0603 | H20: =ROUND('dat_file 1980'!H20/'dat_file 1980'!H$74,4) -> 0.2214 | I20: =ROUND('dat_file 1980'!J20/'dat_file 1980'!J$74,4) -> 0.1959 | K20: ="ELSE IF ref_year="&'dat_file 1980'!B20&" THEN cpi_u_rs_18="&ROUND('dat_file 1980'!$D$73/'dat_file 1980'!D20,3)&";" -> ELSE IF ref_year=1965 THEN cpi_u_rs_18=6.977; | O20: ="ELSE IF ref_year="&'dat_file 1980'!B20&" THEN cpi_u_rs_adj_18="&ROUND('dat_file 1980'!$H$73/'dat_file 1980'!H20,3)&";" -> ELSE IF ref_year=1965 THEN cpi_u_rs_adj_18=4.471;
B21: =+Sheet3!A21 -> 1966 | C21: =ROUND('dat_file 1980'!C21/'dat_file 1980'!C$74,4) -> 0.1632 | D21: =ROUND('dat_file 1980'!D21/'dat_file 1980'!D$74,4) -> 0.1448 | E21: =ROUND('dat_file 1980'!E21/'dat_file 1980'!E$74,4) -> 0.1267 | F21: ='dat_file 1980'!F21 -> 1.0313 | G21: ='dat_file 1980'!G21 -> 1.0309 | H21: =ROUND('dat_file 1980'!H21/'dat_file 1980'!H$74,4) -> 0.2253 | I21: =ROUND('dat_file 1980'!J21/'dat_file 1980'!J$74,4) -> 0.1992 | K21: ="ELSE IF ref_year="&'dat_file 1980'!B21&" THEN cpi_u_rs_18="&ROUND('dat_file 1980'!$D$73/'dat_file 1980'!D21,3)&";" -> ELSE IF ref_year=1966 THEN cpi_u_rs_18=6.785; | O21: ="ELSE IF ref_year="&'dat_file 1980'!B21&" THEN cpi_u_rs_adj_18="&ROUND('dat_file 1980'!$H$73/'dat_file 1980'!H21,3)&";" -> ELSE IF ref_year=1966 THEN cpi_u_rs_adj_18=4.395;
B22: =+Sheet3!A22 -> 1967 | C22: =ROUND('dat_file 1980'!C22/'dat_file 1980'!C$74,4) -> 0.1673 | D22: =ROUND('dat_file 1980'!D22/'dat_file 1980'!D$74,4) -> 0.1493 | E22: =ROUND('dat_file 1980'!E22/'dat_file 1980'!E$74,4) -> 0.1306 | F22: ='dat_file 1980'!F22 -> 1 | G22: ='dat_file 1980'!G22 -> 1 | H22: =ROUND('dat_file 1980'!H22/'dat_file 1980'!H$74,4) -> 0.2298 | I22: =ROUND('dat_file 1980'!J22/'dat_file 1980'!J$74,4) -> 0.2033 | K22: ="ELSE IF ref_year="&'dat_file 1980'!B22&" THEN cpi_u_rs_18="&ROUND('dat_file 1980'!$D$73/'dat_file 1980'!D22,3)&";" -> ELSE IF ref_year=1967 THEN cpi_u_rs_18=6.579; | O22: ="ELSE IF ref_year="&'dat_file 1980'!B22&" THEN cpi_u_rs_adj_18="&ROUND('dat_file 1980'!$H$73/'dat_file 1980'!H22,3)&";" -> ELSE IF ref_year=1967 THEN cpi_u_rs_adj_18=4.308;
B23: =+Sheet3!A23 -> 1968 | C23: =ROUND('dat_file 1980'!C23/'dat_file 1980'!C$74,4) -> 0.1739 | D23: =ROUND('dat_file 1980'!D23/'dat_file 1980'!D$74,4) -> 0.1551 | E23: =ROUND('dat_file 1980'!E23/'dat_file 1980'!E$74,4) -> 0.1361 | F23: ='dat_file 1980'!F23 -> 0.9623 | G23: ='dat_file 1980'!G23 -> 0.9598 | H23: =ROUND('dat_file 1980'!H23/'dat_file 1980'!H$74,4) -> 0.2363 | I23: =ROUND('dat_file 1980'!J23/'dat_file 1980'!J$74,4) -> 0.209 | K23: ="ELSE IF ref_year="&'dat_file 1980'!B23&" THEN cpi_u_rs_18="&ROUND('dat_file 1980'!$D$73/'dat_file 1980'!D23,3)&";" -> ELSE IF ref_year=1968 THEN cpi_u_rs_18=6.331; | O23: ="ELSE IF ref_year="&'dat_file 1980'!B23&" THEN cpi_u_rs_adj_18="&ROUND('dat_file 1980'!$H$73/'dat_file 1980'!H23,3)&";" -> ELSE IF ref_year=1968 THEN cpi_u_rs_adj_18=4.19;
B24: =+Sheet3!A24 -> 1969 | C24: =ROUND('dat_file 1980'!C24/'dat_file 1980'!C$74,4) -> 0.1817 | D24: =ROUND('dat_file 1980'!D24/'dat_file 1980'!D$74,4) -> 0.1621 | E24: =ROUND('dat_file 1980'!E24/'dat_file 1980'!E$74,4) -> 0.1436 | F24: ='dat_file 1980'!F24 -> 0.9212 | G24: ='dat_file 1980'!G24 -> 0.9101 | H24: =ROUND('dat_file 1980'!H24/'dat_file 1980'!H$74,4) -> 0.2442 | I24: =ROUND('dat_file 1980'!J24/'dat_file 1980'!J$74,4) -> 0.216 | K24: ="ELSE IF ref_year="&'dat_file 1980'!B24&" THEN cpi_u_rs_18="&ROUND('dat_file 1980'!$D$73/'dat_file 1980'!D24,3)&";" -> ELSE IF ref_year=1969 THEN cpi_u_rs_18=6.06; | O24: ="ELSE IF ref_year="&'dat_file 1980'!B24&" THEN cpi_u_rs_adj_18="&ROUND('dat_file 1980'!$H$73/'dat_file 1980'!H24,3)&";" -> ELSE IF ref_year=1969 THEN cpi_u_rs_adj_18=4.054;
B25: =+Sheet3!A25 -> 1970 | C25: =ROUND('dat_file 1980'!C25/'dat_file 1980'!C$74,4) -> 0.1902 | D25: =ROUND('dat_file 1980'!D25/'dat_file 1980'!D$74,4) -> 0.1701 | E25: =ROUND('dat_file 1980'!E25/'dat_file 1980'!E$74,4) -> 0.1518 | F25: ='dat_file 1980'!F25 -> 0.8779 | G25: ='dat_file 1980'!G25 -> 0.8608 | H25: =ROUND('dat_file 1980'!H25/'dat_file 1980'!H$74,4) -> 0.2536 | I25: =ROUND('dat_file 1980'!J25/'dat_file 1980'!J$74,4) -> 0.2241 | K25: ="ELSE IF ref_year="&'dat_file 1980'!B25&" THEN cpi_u_rs_18="&ROUND('dat_file 1980'!$D$73/'dat_file 1980'!D25,3)&";" -> ELSE IF ref_year=1970 THEN cpi_u_rs_18=5.776; | O25: ="ELSE IF ref_year="&'dat_file 1980'!B25&" THEN cpi_u_rs_adj_18="&ROUND('dat_file 1980'!$H$73/'dat_file 1980'!H25,3)&";" -> ELSE IF ref_year=1970 THEN cpi_u_rs_adj_18=3.904;
B26: =+Sheet3!A26 -> 1971 | C26: =ROUND('dat_file 1980'!C26/'dat_file 1980'!C$74,4) -> 0.1983 | D26: =ROUND('dat_file 1980'!D26/'dat_file 1980'!D$74,4) -> 0.1775 | E26: =ROUND('dat_file 1980'!E26/'dat_file 1980'!E$74,4) -> 0.1584 | F26: ='dat_file 1980'!F26 -> 0.8411 | G26: ='dat_file 1980'!G26 -> 0.8247 | H26: =ROUND('dat_file 1980'!H26/'dat_file 1980'!H$74,4) -> 0.2619 | I26: =ROUND('dat_file 1980'!J26/'dat_file 1980'!J$74,4) -> 0.2315 | K26: ="ELSE IF ref_year="&'dat_file 1980'!B26&" THEN cpi_u_rs_18="&ROUND('dat_file 1980'!$D$73/'dat_file 1980'!D26,3)&";" -> ELSE IF ref_year=1971 THEN cpi_u_rs_18=5.534; | O26: ="ELSE IF ref_year="&'dat_file 1980'!B26&" THEN cpi_u_rs_adj_18="&ROUND('dat_file 1980'!$H$73/'dat_file 1980'!H26,3)&";" -> ELSE IF ref_year=1971 THEN cpi_u_rs_adj_18=3.78;
B27: =+Sheet3!A27 -> 1972 | C27: =ROUND('dat_file 1980'!C27/'dat_file 1980'!C$74,4) -> 0.2051 | D27: =ROUND('dat_file 1980'!D27/'dat_file 1980'!D$74,4) -> 0.1828 | E27: =ROUND('dat_file 1980'!E27/'dat_file 1980'!E$74,4) -> 0.1635 | F27: ='dat_file 1980'!F27 -> 0.8166 | G27: ='dat_file 1980'!G27 -> 0.799 | H27: =ROUND('dat_file 1980'!H27/'dat_file 1980'!H$74,4) -> 0.2669 | I27: =ROUND('dat_file 1980'!J27/'dat_file 1980'!J$74,4) -> 0.236 | K27: ="ELSE IF ref_year="&'dat_file 1980'!B27&" THEN cpi_u_rs_18="&ROUND('dat_file 1980'!$D$73/'dat_file 1980'!D27,3)&";" -> ELSE IF ref_year=1972 THEN cpi_u_rs_18=5.373; | O27: ="ELSE IF ref_year="&'dat_file 1980'!B27&" THEN cpi_u_rs_adj_18="&ROUND('dat_file 1980'!$H$73/'dat_file 1980'!H27,3)&";" -> ELSE IF ref_year=1972 THEN cpi_u_rs_adj_18=3.71;
... B73: =+Sheet3!A73 -> 2018 | C73: =ROUND('dat_file 1980'!C73/'dat_file 1980'!C$74,4) -> 0.9853 | D73: =ROUND('dat_file 1980'!D73/'dat_file 1980'!D$74,4) -> 0.9822 | E73: =ROUND('dat_file 1980'!E73/'dat_file 1980'!E$74,4) -> 0.9822 | F73: ='dat_file 1980'!F73 -> 0.152 | G73: ='dat_file 1980'!G73 -> 0.133 | H73: =ROUND('dat_file 1980'!H73/'dat_file 1980'!H$74,4) -> 0.99 | I73: =ROUND('dat_file 1980'!J73/'dat_file 1980'!J$74,4) -> 0.9869 | K73: ="ELSE IF ref_year="&'dat_file 1980'!B73&" THEN cpi_u_rs_18="&ROUND('dat_file 1980'!$D$73/'dat_file 1980'!D73,3)&";" -> ELSE IF ref_year=2018 THEN cpi_u_rs_18=1; | O73: ="ELSE IF ref_year="&'dat_file 1980'!B73&" THEN cpi_u_rs_adj_18="&ROUND('dat_file 1980'!$H$73/'dat_file 1980'!H73,3)&";" -> ELSE IF ref_year=2018 THEN cpi_u_rs_adj_18=1;
B74: =+Sheet3!A74 -> 2019 | C74: =ROUND('dat_file 1980'!C74/'dat_file 1980'!C$74,4) -> 1 | D74: =ROUND('dat_file 1980'!D74/'dat_file 1980'!D$74,4) -> 1 | E74: =ROUND('dat_file 1980'!E74/'dat_file 1980'!E$74,4) -> 1 | F74: ='dat_file 1980'!F74 -> 0.1493 | G74: ='dat_file 1980'!G74 -> 0.1306 | H74: =ROUND('dat_file 1980'!H74/'dat_file 1980'!H$74,4) -> 1 | I74: =ROUND('dat_file 1980'!J74/'dat_file 1980'!J$74,4) -> 1
B75: =+Sheet3!A75 -> 2020 | C75: =ROUND('dat_file 1980'!C75/'dat_file 1980'!C$74,4) -> 1.011 | D75: =ROUND('dat_file 1980'!D75/'dat_file 1980'!D$74,4) -> 1.0133 | E75: =ROUND('dat_file 1980'!E75/'dat_file 1980'!E$74,4) -> 1.0123 | F75: ='dat_file 1980'!F75 -> 0.1473 | G75: ='dat_file 1980'!G75 -> 0.1291 | H75: =ROUND('dat_file 1980'!H75/'dat_file 1980'!H$74,4) -> 1.0053 | I75: =ROUND('dat_file 1980'!J75/'dat_file 1980'!J$74,4) -> 1.0082
